Workbook

Sheet Data
A1: Data Source | B1: World Development Indicators
A2: Last Updated Date | B2: 45937
A4: Country Name | B4: Country Code | C4: Indicator Name | D4: Indicator Code | E4: 1960 | F4: 1961 | G4: 1962 | H4: 1963 | I4: 1964 | J4: 1965 | K4: 1966 | L4: 1967 | M4: 1968 | N4: 1969 | O4: 1970 | P4: 1971 | Q4: 1972 | R4: 1973 | S4: 1974 | T4: 1975 | U4: 1976 | V4: 1977 | W4: 1978 | X4: 1979 | Y4: 1980 | Z4: 1981 | AA4: 1982 | AB4: 1983 | AC4: 1984 | AD4: 1985 | AE4: 1986 | AF4: 1987 | AG4: 1988 | AH4: 1989 | AI4: 1990 | AJ4: 1991 | AK4: 1992 | AL4: 1993 | AM4: 1994 | AN4: 1995 | AO4: 1996 | AP4: 1997 | AQ4: 1998 | AR4: 1999 | AS4: 2000 | AT4: 2001 | AU4: 2002 | AV4: 2003 | AW4: 2004 | AX4: 2005 | AY4: 2006 | AZ4: 2007 | BA4: 2008 | BB4: 2009 | BC4: 2010 | BD4: 2011 | BE4: 2012 | BF4: 2013 | BG4: 2014 | BH4: 2015 | BI4: 2016 | BJ4: 2017 | BK4: 2018 | BL4: 2019 | BM4: 2020 | BN4: 2021 | BO4: 2022 | BP4: 2023 | BQ4: 2024
A5: Aruba | B5: ABW | C5: Gini index | D5: SI.POV.GINI
A6: Africa Eastern and Southern | B6: AFE | C6: Gini index | D6: SI.POV.GINI | BS6: =MIN(E5:BQ270) -> 20.2
A7: Afghanistan | B7: AFG | C7: Gini index | D7: SI.POV.GINI
A8: Africa Western and Central | B8: AFW | C8: Gini index | D8: SI.POV.GINI
A9: Angola | B9: AGO | C9: Gini index | D9: SI.POV.GINI | AS9: 51.9 | BA9: 42.7 | BH9: =BA9+((BK9-BA9)/(BK4-BA4))*(BH4-BA4) -> 48.72 | BK9: 51.3
A10: Albania | B10: ALB | C10: Gini index | D10: SI.POV.GINI | AO10: 27 | AU10: 31.7 | AX10: 30.6 | BA10: 30 | BE10: 29 | BG10: 34.6 | BH10: 32.8 | BI10: 33.7 | BJ10: 33.1 | BK10: 30.1 | BL10: 30.1 | BM10: 29.4
A11: Andorra | B11: AND | C11: Gini index | D11: SI.POV.GINI
A12: Arab World | B12: ARB | C12: Gini index | D12: SI.POV.GINI
A13: United Arab Emirates | B13: ARE | C13: Gini index | D13: SI.POV.GINI | BF13: 32.5 | BK13: 26.4
A14: Argentina | B14: ARG | C14: Gini index | D14: SI.POV.GINI | Y14: 40.8 | AE14: 42.8 | AF14: 45.3 | AJ14: 46.8 | AK14: 45.5 | AL14: 44.8 | AM14: 45.9 | AN14: 48.9 | AO14: 49.5 | AP14: 49.1 | AQ14: 50.7 | AR14: 49.8 | AS14: 51 | AT14: 53.3 | AU14: 53.8 | AV14: 51 | AW14: 48.5 | AX14: 47.8 | AY14: 46.4 | AZ14: 46.3 | BA14: 45 | BB14: 43.8 | BC14: 43.7 | BD14: 42.7 | BE14: 41.4 | BF14: 41.1 | BG14: 41.8 | BI14: 42.3 | BJ14: 41.4 | BK14: 41.7 | BL14: 43.3 | BM14: 42.7 | BN14: 42.4 | BO14: 40.7 | BP14: 42.4 | BQ14: 42.4
A15: Armenia | B15: ARM | C15: Gini index | D15: SI.POV.GINI | AO15: 44.4 | AR15: 36.2 | AT15: 35.4 | AU15: 34.8 | AV15: 33 | AW15: 37.5 | AX15: 36 | AY15: 29.7 | AZ15: 31.2 | BA15: 29.2 | BB15: 28 | BC15: 30 | BD15: 29.4 | BE15: 29.6 | BF15: 30.6 | BG15: 31.5 | BH15: 32.4 | BI15: 32.5 | BJ15: 33.6 | BK15: 34.4 | BL15: 30 | BM15: 25.1 | BN15: 27.9 | BO15: 27.9 | BP15: 27.2
A16: American Samoa | B16: ASM | C16: Gini index | D16: SI.POV.GINI
A17: Antigua and Barbuda | B17: ATG | C17: Gini index | D17: SI.POV.GINI
A18: Australia | B18: AUS | C18: Gini index | D18: SI.POV.GINI | Z18: 31.3 | AD18: 32.5 | AH18: 33.2 | AN18: 32.6 | AT18: 33.5 | AV18: 33.5 | AW18: 33.1 | BA18: 35.4 | BC18: 34.7 | BG18: 34.4 | BI18: 33.7 | BK18: 34.3 | BM18: 33.8
A19: Austria | B19: AUT | C19: Gini index | D19: SI.POV.GINI | AM19: 30.8 | AN19: 29.9 | AO19: 29.3 | AP19: 29.1 | AQ19: 31.3 | AR19: 29.7 | AS19: 29 | AV19: 29.5 | AW19: 29.8 | AX19: 28.7 | AY19: 29.6 | AZ19: 30.6 | BA19: 30.4 | BB19: 31.5 | BC19: 30.3 | BD19: 30.8 | BE19: 30.5 | BF19: 30.8 | BG19: 30.5 | BH19: 30.5 | BI19: 30.8 | BJ19: 29.7 | BK19: 30.8 | BL19: 30.2 | BM19: 29.8 | BN19: 30.7 | BO19: 30.9 | BP19: 31.2
A20: Azerbaijan | B20: AZE | C20: Gini index | D20: SI.POV.GINI | AN20: 34.6 | AT20: 36.5 | AU20: 25.3 | AV20: 26.8 | AW20: 26.6 | AX20: 26.6
A21: Burundi | B21: BDI | C21: Gini index | D21: SI.POV.GINI | AK21: 33.3 | AQ21: 42.1 | AY21: 33.4 | BF21: 38.6 | BM21: 37.5
A22: Belgium | B22: BEL | C22: Gini index | D22: SI.POV.GINI | AD22: 25.2 | AG22: 25.7 | AK22: 24.9 | AN22: 28.4 | AP22: 26.8 | AS22: 33.1 | AV22: 28.1 | AW22: 30.5 | AX22: 29.3 | AY22: 28.1 | AZ22: 29.2 | BA22: 28.4 | BB22: 28.6 | BC22: 28.4 | BD22: 28.1 | BE22: 27.5 | BF22: 27.7 | BG22: 28.1 | BH22: 27.7 | BI22: 27.6 | BJ22: 27.4 | BK22: 27.2 | BL22: 27.2 | BM22: 26 | BN22: 26.6 | BO22: 26.4 | BP22: 26.8 | BS22: =[1]Data!$F$12 -> 46445.406
A23: Benin | B23: BEN | C23: Gini index | D23: SI.POV.GINI | AV23: 38.6 | BD23: 43.4 | BH23: 47.6 | BK23: 37.9 | BN23: 34.4
A24: Burkina Faso | B24: BFA | C24: Gini index | D24: SI.POV.GINI | AM24: 48 | AQ24: 49.9 | AV24: 43.3 | BB24: 39.8 | BG24: 35.3 | BK24: 43 | BN24: 37.4
A25: Bangladesh | B25: BGD | C25: Gini index | D25: SI.POV.GINI | AB25: 25.9 | AD25: 26.9 | AG25: 28.8 | AJ25: 27.6 | AN25: 32.9 | AS25: 33.4 | AX25: 33.2 | BC25: 32.1 | BI25: 32.4 | BO25: 30.9
A26: Bulgaria | B26: BGR | C26: Gini index | D26: SI.POV.GINI | AH26: 23.4 | AK26: 30.7 | AM26: 24.3 | AN26: 32.8 | AP26: 26.4 | AT26: 32.7 | AV26: 28.9 | AY26: 35.7 | AZ26: 36.1 | BA26: 33.6 | BB26: 33.8 | BC26: 35.7 | BD26: 34.3 | BE26: 36 | BF26: 36.6 | BG26: 37.4 | BH26: 38.6 | BI26: 40.6 | BJ26: 40.4 | BK26: 41.3 | BL26: 40.3 | BM26: 40.5 | BN26: 39 | BO26: 38.2 | BP26: 39.5
A27: Bahrain | B27: BHR | C27: Gini index | D27: SI.POV.GINI
A28: Bahamas, The | B28: BHS | C28: Gini index | D28: SI.POV.GINI
A29: Bosnia and Herzegovina | B29: BIH | C29: Gini index | D29: SI.POV.GINI | AT29: 30 | AW29: 34 | AZ29: 33.1 | BD29: 33
A30: Belarus | B30: BLR | C30: Gini index | D30: SI.POV.GINI | AL30: 21.6 | AN30: 28.7 | AQ30: 32 | AR30: 31.7 | AS30: 31.2 | AT30: 30.6 | AU30: 30.3 | AV30: 28.8 | AW30: 26.5 | AX30: 27.6 | AY30: 28.3 | AZ30: 29.6 | BA30: 27.8 | BB30: 27.7 | BC30: 28.6 | BD30: 27.2 | BE30: 26.5 | BF30: 26.6 | BG30: 27.2 | BH30: 25.6 | BI30: 25.3 | BJ30: 25.4 | BK30: 25.2 | BL30: 25.3 | BM30: 24.4 | BS30: =[1]Data!$F$11 -> 17917.185
A31: Belize | B31: BLZ | C31: Gini index | D31: SI.POV.GINI | AL31: 60.2 | AM31: 60.9 | AN31: 57.5 | AO31: 56.6 | AP31: 60.4 | AQ31: 54.9 | AR31: 53.2 | BK31: 39.9
A32: Bermuda | B32: BMU | C32: Gini index | D32: SI.POV.GINI
A33: Bolivia | B33: BOL | C33: Gini index | D33: SI.POV.GINI | AI33: 42 | AK33: 49.1 | AP33: 58.1 | AR33: 58 | AS33: 61.6 | AT33: 57.4 | AU33: 59.3 | AW33: 55 | AX33: 58.5 | AY33: 56.7 | AZ33: 54.5 | BA33: 50.8 | BB33: 49.2 | BD33: 46.1 | BE33: 46.6 | BF33: 47.6 | BG33: 47.8 | BH33: 46.7 | BI33: 45.2 | BJ33: 44.6 | BK33: 42.6 | BL33: 41.6 | BM33: 43.6 | BN33: 40.9 | BO33: 41.2 | BP33: 42.1
A34: Brazil | B34: BRA | C34: Gini index | D34: SI.POV.GINI | Z34: 57.9 | AA34: 58.4 | AB34: 58.9 | AC34: 58.3 | AD34: 55.5 | AE34: 58.4 | AF34: 59.6 | AG34: 61.4 | AH34: 63.2 | AI34: 60.5 | AK34: 53.1 | AL34: 60.1 | AN34: 59.5 | AO34: 59.8 | AP34: 59.8 | AQ34: 59.6 | AR34: 59 | AT34: 58.4 | AU34: 58.1 | AV34: 57.6 | AW34: 56.5 | AX34: 56.3 | AY34: 55.6 | AZ34: 54.9 | BA34: 54 | BB34: 53.7 | BD34: 52.9 | BE34: 53.4 | BF34: 52.7 | BG34: 52 | BH34: 51.9 | BI34: 53.4 | BJ34: 53.3 | BK34: 53.9 | BL34: 53.5 | BM34: 48.9 | BN34: 52.9 | BO34: 52 | BP34: 51.6
A35: Barbados | B35: BRB | C35: Gini index | D35: SI.POV.GINI | BI35: 34.1
A36: Brunei Darussalam | B36: BRN | C36: Gini index | D36: SI.POV.GINI
A37: Bhutan | B37: BTN | C37: Gini index | D37: SI.POV.GINI | AV37: 40.9 | AZ37: 38.1 | BE37: 38.8 | BJ37: 37.4 | BO37: 28.5
A38: Botswana | B38: BWA | C38: Gini index | D38: SI.POV.GINI | AD38: 54.2 | AL38: 60.1 | AU38: 61.5 | BB38: 56.9 | BH38: 54.9
A39: Central African Republic | B39: CAF | C39: Gini index | D39: SI.POV.GINI | AK39: 59.7 | BA39: 56.2 | BN39: 43
A40: Canada | B40: CAN | C40: Gini index | D40: SI.POV.GINI | P40: 37.2 | R40: 34.9 | T40: 34.1 | V40: 33.7 | X40: 33.5 | Z40: 33 | AA40: 32.9 | AC40: 33.5 | AD40: 33.2 | AE40: 31.7 | AF40: 31.7 | AG40: 31.2 | AH40: 31 | AI40: 31.4 | AJ40: 31.9 | AK40: 31.6 | AL40: 31.7 | AM40: 31.3 | AN40: 31.5 | AO40: 32.8 | AP40: 33.1 | AQ40: 33.2 | AR40: 33.1 | AS40: 33.4 | AT40: 33.6 | AU40: 33.6 | AV40: 33.8 | AW40: 33.8 | AX40: 33.6 | AY40: 34.1 | AZ40: 33.8 | BA40: 33.9 | BB40: 34 | BC40: 33.6 | BD40: 32.7 | BE40: 33.5 | BF40: 33.8 | BG40: 33.2 | BH40: 33.7 | BI40: 32.7 | BJ40: 33.3 | BK40: 32.5 | BL40: 31.7 | BM40: 29.9 | BN40: 31.1
A41: Central Europe and the Baltics | B41: CEB | C41: Gini index | D41: SI.POV.GINI
A42: Switzerland | B42: CHE | C42: Gini index | D42: SI.POV.GINI | AA42: 36 | AK42: 33.9 | AS42: 33.4 | AU42: 31.7 | AW42: 31.6 | AY42: 33.9 | AZ42: 34.3 | BA42: 33.8 | BB42: 32.9 | BC42: 32.6 | BD42: 31.7 | BE42: 31.6 | BF42: 32.5 | BG42: 32.5 | BH42: 32.3 | BI42: 33 | BJ42: 32.7 | BK42: 33.1 | BL42: 34 | BM42: 33.7 | BN42: 33.8 | BO42: 33.8
A43: Channel Islands | B43: CHI | C43: Gini index | D43: SI.POV.GINI
A44: Chile | B44: CHL | C44: Gini index | D44: SI.POV.GINI | AF44: 56.2 | AI44: 57.2 | AK44: 54.8 | AM44: 56.4 | AO44: 54.9 | AQ44: 55.5 | AS44: 52.8 | AV44: 51.5 | AY44: 47.7 | BB44: 47.4 | BD44: 46.9 | BF44: 46.8 | BH44: 45.3 | BJ44: 45.3 | BM44: 47 | BO44: 43
A45: China | B45: CHN | C45: Gini index | D45: SI.POV.GINI | Z45: 28.2 | AC45: 27.1 | AF45: 29.4 | AI45: 32.2 | AL45: 33.9 | AO45: 35.2 | AR45: 38.7 | AU45: 42 | AX45: 40.9 | BA45: 43 | BC45: 43.7 | BD45: 42.4 | BE45: 42.2 | BF45: 39.7 | BG45: 39.2 | BH45: 38.6 | BI45: 38.5 | BJ45: 39.1 | BK45: 38.5 | BL45: 38.2 | BM45: 37.1 | BN45: 35.7 | BO45: 36
A46: Cote d'Ivoire | B46: CIV | C46: Gini index | D46: SI.POV.GINI | AD46: 45.5 | AE46: 38 | AF46: 40.5 | AG46: 36.9 | AK46: 39.4 | AN46: 40.6 | AQ46: 39 | AU46: 41.3 | BA46: 43.2 | BH46: 41.5 | BK46: 37.2 | BN46: 35.3
A47: Cameroon | B47: CMR | C47: Gini index | D47: SI.POV.GINI | AO47: 44.4 | AT47: 42.1 | AZ47: 42.8 | BG47: 46.6 | BN47: 42.2
A48: Congo, Dem. Rep. | B48: COD | C48: Gini index | D48: SI.POV.GINI | AW48: 41.6 | BE48: 42.1 | BH48: =BE48+((BM48-BE48)/(BM$4-BE$4))*($BH$4-BE$4) -> 43.075 | BM48: 44.7
A49: Congo, Rep. | B49: COG | C49: Gini index | D49: SI.POV.GINI | AX49: 47.3 | BD49: 48.9
A50: Colombia | B50: COL | C50: Gini index | D50: SI.POV.GINI | Y50: 55.1 | AG50: 53.1 | AH50: 52.8 | AJ50: 51.3 | AK50: 51.3 | AO50: 56.8 | AR50: 58.5 | AS50: 58.4 | AT50: 57.3 | AU50: 56 | AV50: 53.6 | AW50: 55 | AX50: 53.9 | BA50: 55.3 | BB50: 54.3 | BC50: 54.6 | BD50: 53.5 | BE50: 52.6 | BF50: 52.6 | BG50: 52.5 | BH50: 51 | BI50: 50.6 | BJ50: 49.7 | BK50: 50.4 | BL50: 51.3 | BM50: 53.5 | BN50: 55.1 | BO50: 54.8 | BP50: 53.9
A51: Comoros | B51: COM | C51: Gini index | D51: SI.POV.GINI | AW51: 55.9 | BG51: 45.3
A52: Cabo Verde | B52: CPV | C52: Gini index | D52: SI.POV.GINI | AT52: 52.5 | AZ52: 47.2 | BH52: 42.4
A53: Costa Rica | B53: CRI | C53: Gini index | D53: SI.POV.GINI | Z53: 47.5 | AE53: 34.4 | AH53: 45.5 | AI53: 45.2 | AJ53: 46.6 | AK53: 45.6 | AL53: 45.9 | AM53: 46.7 | AN53: 45.7 | AO53: 46.5 | AP53: 45.6 | AQ53: 45.6 | AR53: 47.6 | AS53: 47.4 | AT53: 51.5 | AU53: 51.8 | AV53: 49.3 | AW53: 48.4 | AX53: 47.5 | AY53: 49.3 | AZ53: 49.3 | BA53: 48.6 | BB53: 50.6 | BC53: 48 | BD53: 48.8 | BE53: 48.4 | BF53: 49.2 | BG53: 48.6 | BH53: 48.4 | BI53: 48.7 | BJ53: 48.3 | BK53: 48 | BL53: 48.2 | BM53: 49.2 | BN53: 48.7 | BO53: 47.2 | BP53: 46.7 | BQ53: 45.8
A54: Caribbean small states | B54: CSS | C54: Gini index | D54: SI.POV.GINI
A55: Cuba | B55: CUB | C55: Gini index | D55: SI.POV.GINI
A56: Curacao | B56: CUW | C56: Gini index | D56: SI.POV.GINI
A57: Cayman Islands | B57: CYM | C57: Gini index | D57: SI.POV.GINI
A58: Cyprus | B58: CYP | C58: Gini index | D58: SI.POV.GINI | AW58: 30.1 | AX58: 30.3 | AY58: 31.1 | AZ58: 31.1 | BA58: 31.7 | BB58: 32.1 | BC58: 31.5 | BD58: 32.6 | BE58: 34.3 | BF58: 37 | BG58: 35.6 | BH58: 34 | BI58: 32.9 | BJ58: 31.4 | BK58: 32.7 | BL58: 31.2 | BM58: 31.7 | BN58: 31.3 | BO58: 31.5 | BP58: 31.8
A59: Czechia | B59: CZE | C59: Gini index | D59: SI.POV.GINI | AK59: 20.7 | AL59: 26.6 | AO59: 25.8 | AU59: 26.6 | AW59: 27.5 | AX59: 26.9 | AY59: 26.7 | AZ59: 26 | BA59: 26.3 | BB59: 26.2 | BC59: 26.6 | BD59: 26.4 | BE59: 26.1 | BF59: 26.5 | BG59: 25.9 | BH59: 25.9 | BI59: 25.4 | BJ59: 24.9 | BK59: 25 | BL59: 25.3 | BM59: 26.2 | BN59: 26.2 | BO59: 25.9 | BP59: 25.7 | BS59: =[1]Data!$F$31 -> 33991.851
A60: Germany | B60: DEU | C60: Gini index | D60: SI.POV.GINI | AJ60: 29.5 | AK60: 29.1 | AL60: 28.6 | AM60: 29.2 | AN60: 28.8 | AO60: 28 | AP60: 28.2 | AQ60: 28.3 | AR60: 29 | AS60: 28.9 | AT60: 29.9 | AU60: 29.8 | AV60: 29.8 | AW60: 30.2 | AX60: 31.7 | AY60: 31 | AZ60: 31.2 | BA60: 30.8 | BB60: 30.5 | BC60: 30.2 | BD60: 30.6 | BE60: 31.1 | BF60: 31.5 | BG60: 30.8 | BH60: 31.7 | BI60: 31.4 | BJ60: 31.3 | BK60: 31.9 | BL60: 31.8 | BM60: 32.4
A61: Djibouti | B61: DJI | C61: Gini index | D61: SI.POV.GINI | AU61: 40 | BE61: 45.1 | BF61: 44.1 | BJ61: 41.6
A62: Dominica | B62: DMA | C62: Gini index | D62: SI.POV.GINI
A63: Denmark | B63: DNK | C63: Gini index | D63: SI.POV.GINI | AF63: 26.2 | AK63: 24.7 | AN63: 23 | AS63: 23.8 | AV63: 25.6 | AW63: 24.9 | AX63: 25.2 | AY63: 25.9 | AZ63: 26.2 | BA63: 25.2 | BB63: 26.7 | BC63: 27.2 | BD63: 27.3 | BE63: 27.8 | BF63: 28.5 | BG63: 28.4 | BH63: 28.2 | BI63: 28.2 | BJ63: 28.7 | BK63: 28.2 | BL63: 27.7 | BM63: 27.5 | BN63: 28.3 | BO63: 29.3 | BP63: 29.9 | BS63: =[1]Data!$F$32 -> 49213.699
A64: Dominican Republic | B64: DOM | C64: Gini index | D64: SI.POV.GINI | AE64: 47.8 | AH64: 50.4 | AK64: 51.1 | AO64: 47.4 | AP64: 48.9 | AS64: 51.5 | AT64: 50 | AU64: 49.7 | AV64: 52.1 | AW64: 52.1 | AX64: 50 | AY64: 52 | AZ64: 48.9 | BA64: 48.1 | BB64: 48.9 | BC64: 47.3 | BD64: 47.7 | BE64: 46.1 | BF64: 47.7 | BG64: 44.3 | BH64: 45.2 | BI64: 45.7 | BJ64: 42.2 | BK64: 43.7 | BL64: 41.9 | BM64: 39.6 | BN64: 38.5 | BO64: 37 | BP64: 38.4 | BQ64: 39
A65: Algeria | B65: DZA | C65: Gini index | D65: SI.POV.GINI | AG65: 37.4 | AN65: 35.3 | BD65: 27.6
A66: East Asia & Pacific (excluding high income) | B66: EAP | C66: Gini index | D66: SI.POV.GINI
A67: Early-demographic dividend | B67: EAR | C67: Gini index | D67: SI.POV.GINI
A68: East Asia & Pacific | B68: EAS | C68: Gini index | D68: SI.POV.GINI
A69: Europe & Central Asia (excluding high income) | B69: ECA | C69: Gini index | D69: SI.POV.GINI
A70: Europe & Central Asia | B70: ECS | C70: Gini index | D70: SI.POV.GINI
A71: Ecuador | B71: ECU | C71: Gini index | D71: SI.POV.GINI | AF71: 50.5 | AM71: 53.3 | AN71: 50.8 | AQ71: 49.6 | AR71: 58.6 | AS71: 56.3 | AV71: 53.5 | AW71: 53.9 | AX71: 53.1 | AY71: 52.3 | AZ71: 53.4 | BA71: 49.8 | BB71: 48.5 | BC71: 48.8 | BD71: 45.9 | BE71: 46.1 | BF71: 46.9 | BG71: 45 | BH71: 46 | BI71: 45 | BJ71: 44.7 | BK71: 45.4 | BL71: 45.7 | BM71: 47.3 | BN71: 45.8 | BO71: 45.5 | BP71: 44.6 | BQ71: 45.2
A72: Egypt, Arab Rep. | B72: EGY | C72: Gini index | D72: SI.POV.GINI | AI72: 32 | AN72: 30.1 | AR72: 30.8 | AW72: 31.8 | BA72: 31.1 | BC72: 30.2 | BE72: 28.3 | BH72: 31.8 | BJ72: 31.5 | BL72: 31.9 | BN72: 28.5
A73: Euro area | B73: EMU | C73: Gini index | D73: SI.POV.GINI
A74: Eritrea | B74: ERI | C74: Gini index | D74: SI.POV.GINI
A75: Spain | B75: ESP | C75: Gini index | D75: SI.POV.GINI | Y75: 34.5 | AD75: 34.4 | AI75: 32 | AL75: 35.7 | AM75: 35.1 | AN75: 35.7 | AO75: 36.5 | AP75: 35.3 | AQ75: 34.6 | AR75: 33.8 | AS75: 34.1 | AV75: 31.8 | AW75: 33.3 | AX75: 32.4 | AY75: 33.5 | AZ75: 34.1 | BA75: 34.2 | BB75: 34.9 | BC75: 35.2 | BD75: 35.7 | BE75: 35.4 | BF75: 36.2 | BG75: 36.1 | BH75: 36.2 | BI75: 35.8 | BJ75: 34.7 | BK75: 34.7 | BL75: 34.3 | BM75: 34.9 | BN75: 33.9 | BO75: 33.6 | BP75: 33.4
A76: Estonia | B76: EST | C76: Gini index | D76: SI.POV.GINI | AL76: 39.4 | AN76: 30.1 | AQ76: 37.6 | AS76: 35.8 | AT76: 36 | AU76: 35.8 | AV76: 37.2 | AW76: 33.6 | AX76: 33.4 | AY76: 33.7 | AZ76: 31.2 | BA76: 31.9 | BB76: 31.4 | BC76: 32 | BD76: 32.5 | BE76: 32.9 | BF76: 35.1 | BG76: 34.6 | BH76: 32.7 | BI76: 31.2 | BJ76: 30.4 | BK76: 30.3 | BL76: 30.8 | BM76: 30.7 | BN76: 31.8 | BO76: 32.3 | BP76: 30.7
A77: Ethiopia | B77: ETH | C77: Gini index | D77: SI.POV.GINI | AN77: 44.6 | AR77: 30 | AW77: 29.8 | BC77: 33.2 | BH77: 35 | BN77: 31.1
A78: European Union | B78: EUU | C78: Gini index | D78: SI.POV.GINI
A79: Fragile and conflict affected situations | B79: FCS | C79: Gini index | D79: SI.POV.GINI
A80: Finland | B80: FIN | C80: Gini index | D80: SI.POV.GINI | AF80: 22.2 | AJ80: 22.9 | AN80: 23.5 | AS80: 27.2 | AV80: 27.7 | AW80: 27.9 | AX80: 27.6 | AY80: 28 | AZ80: 28.3 | BA80: 27.8 | BB80: 27.5 | BC80: 27.7 | BD80: 27.6 | BE80: 27.1 | BF80: 27.2 | BG80: 26.8 | BH80: 27.1 | BI80: 27.1 | BJ80: 27.4 | BK80: 27.3 | BL80: 27.7 | BM80: 27.1 | BN80: 27.7 | BO80: 27.9 | BP80: 27.4 | BS80: =[1]Data!$F$39 -> 42558.079
A81: Fiji | B81: FJI | C81: Gini index | D81: SI.POV.GINI | AU81: 38.1 | BA81: 40.4 | BF81: 36.7 | BL81: 30.7
A82: France | B82: FRA | C82: Gini index | D82: SI.POV.GINI | O82: 37.1 | T82: 35.9 | X82: 34 | AC82: 33.4 | AI82: 32.1 | AO82: 32 | AP82: 31.9 | AQ82: 31.7 | AR82: 32.5 | AS82: 32.6 | AT82: 32.5 | AU82: 31.8 | AV82: 31.4 | AW82: 30.6 | AX82: 29.8 | AY82: 29.7 | AZ82: 32.4 | BA82: 33 | BB82: 32.7 | BC82: 33.7 | BD82: 33.3 | BE82: 33.1 | BF82: 32.5 | BG82: 32.3 | BH82: 32.7 | BI82: 31.9 | BJ82: 31.6 | BK82: 32.4 | BL82: 31.2 | BM82: 30.7 | BN82: 31.5 | BO82: 31.2 | BP82: 31.8
A83: Faroe Islands | B83: FRO | C83: Gini index | D83: SI.POV.GINI
A84: Micronesia, Fed. Sts. | B84: FSM | C84: Gini index | D84: SI.POV.GINI | AX84: 42.4 | BF84: 40.1
A85: Gabon | B85: GAB | C85: Gini index | D85: SI.POV.GINI | AX85: 42.2 | BJ85: 38
A86: United Kingdom | B86: GBR | C86: Gini index | D86: SI.POV.GINI | M86: 26.8 | N86: 27.9 | O86: 28 | P86: 29.3 | Q86: 28.8 | R86: 28.8 | S86: 29 | T86: 27.9 | U86: 27.6 | V86: 27.1 | W86: 27.2 | X86: 27.4 | Y86: 28.5 | Z86: 29.7 | AA86: 29.9 | AB86: 29.8 | AC86: 29.2 | AD86: 30.4 | AE86: 31.9 | AF86: 33.9 | AG86: 34.3 | AH86: 33.4 | AI86: 35.7 | AJ86: 35 | AK86: 35 | AL86: 35.1 | AM86: 36 | AN86: 35.5 | AO86: 35.3 | AP86: 35.7 | AQ86: 36.6 | AR86: 36.8 | AS86: 38.8 | AT86: 37.1 | AU86: 35.1 | AV86: 34.9 | AW86: 34.8 | AX86: 35.5 | AY86: 35.9 | AZ86: 34.4 | BA86: 35.4 | BB86: 35.1 | BC86: 33.7 | BD86: 33.2 | BE86: 33.1 | BF86: 32.7 | BG86: 33.1 | BH86: 33.3 | BI86: 33.1 | BJ86: 32.6 | BK86: 33.7 | BL86: 32.8 | BM86: 32.6 | BN86: 32.4
A87: Georgia | B87: GEO | C87: Gini index | D87: SI.POV.GINI | AO87: 37.1 | AP87: 40.7 | AQ87: 41.2 | AR87: 40.1 | AS87: 40.5 | AT87: 39.6 | AU87: 37.2 | AV87: 36.6 | AW87: 36.2 | AX87: 37.4 | AY87: 36.9 | AZ87: 38.1 | BA87: 38.5 | BB87: 38.2 | BC87: 39.5 | BD87: 39.6 | BE87: 39 | BF87: 38.6 | BG87: 37.6 | BH87: 36.5 | BI87: 36.6 | BJ87: 37.9 | BK87: 36.4 | BL87: 35.9 | BM87: 34.5 | BN87: 34.2 | BO87: 33.5 | BP87: 34.8 | BQ87: 33.9
A88: Ghana | B88: GHA | C88: Gini index | D88: SI.POV.GINI | AF88: 35.3 | AG88: 36 | AJ88: 38.4 | AQ88: 40.1 | AX88: 42.8 | BE88: 42.4 | BI88: 43.5
A89: Gibraltar | B89: GIB | C89: Gini index | D89: SI.POV.GINI
A90: Guinea | B90: GIN | C90: Gini index | D90: SI.POV.GINI | AJ90: 45.6 | AM90: 46.1 | AU90: 43 | AZ90: 39.4 | BE90: 33.7 | BK90: 29.6
A91: Gambia, The | B91: GMB | C91: Gini index | D91: SI.POV.GINI | AQ91: 48.3 | AV91: 47.3 | BC91: 43.6 | BH91: 35.9 | BM91: 38.8
A92: Guinea-Bissau | B92: GNB | C92: Gini index | D92: SI.POV.GINI | AJ92: 55.8 | AL92: 43.6 | AU92: 35.6 | BC92: 50.6 | BK92: 34.8 | BN92: 33.4
A93: Equatorial Guinea | B93: GNQ | C93: Gini index | D93: SI.POV.GINI | BO93: 38.5
A94: Greece | B94: GRC | C94: Gini index | D94: SI.POV.GINI | AN94: 37 | AS94: 34.4 | AU94: 35.5 | AV94: 32.8 | AW94: 33.6 | AX94: 34.6 | AY94: 35.1 | AZ94: 34 | BA94: 33.6 | BB94: 33.6 | BC94: 34.1 | BD94: 34.8 | BE94: 36.3 | BF94: 36.1 | BG94: 35.8 | BH94: 36 | BI94: 35 | BJ94: 34.4 | BK94: 32.9 | BL94: 33.1 | BM94: 33.6 | BN94: 32.9 | BO94: 33.4 | BP94: 33.4
A95: Grenada | B95: GRD | C95: Gini index | D95: SI.POV.GINI | BK95: 43.8
A96: Greenland | B96: GRL | C96: Gini index | D96: SI.POV.GINI
A97: Guatemala | B97: GTM | C97: Gini index | D97: SI.POV.GINI | AE97: 54.1 | AH97: 58.8 | AQ97: 49.4 | AS97: 54.2 | AY97: 54.5 | BG97: 48.3 | BP97: 45.2
A98: Guam | B98: GUM | C98: Gini index | D98: SI.POV.GINI
A99: Guyana | B99: GUY | C99: Gini index | D99: SI.POV.GINI | AK99: 39.5 | AQ99: 45.1
A100: High income | B100: HIC | C100: Gini index | D100: SI.POV.GINI
A101: Hong Kong SAR, China | B101: HKG | C101: Gini index | D101: SI.POV.GINI
...

Sheet Gini_2015
A1: Country Name | B1: Country Code | C1: Gini_2015
A2: Aruba | B2: ABW | C2: =VLOOKUP(A2,Data!$A$5:$BH$270,60,0)/100 -> 0
A3: Africa Eastern and Southern | B3: AFE | C3: =VLOOKUP(A3,Data!$A$5:$BH$270,60,0)/100 -> 0
A4: Afghanistan | B4: AFG | C4: =VLOOKUP(A4,Data!$A$5:$BH$270,60,0)/100 -> 0
A5: Africa Western and Central | B5: AFW | C5: =VLOOKUP(A5,Data!$A$5:$BH$270,60,0)/100 -> 0
A6: Angola | B6: AGO | C6: =VLOOKUP(A6,Data!$A$5:$BH$270,60,0)/100 -> 0.4872
A7: Albania | B7: ALB | C7: =VLOOKUP(A7,Data!$A$5:$BH$270,60,0)/100 -> 0.328
A8: Andorra | B8: AND | C8: =VLOOKUP(A8,Data!$A$5:$BH$270,60,0)/100 -> 0
A9: Arab World | B9: ARB | C9: =VLOOKUP(A9,Data!$A$5:$BH$270,60,0)/100 -> 0
A10: United Arab Emirates | B10: ARE | C10: =VLOOKUP(A10,Data!$A$5:$BH$270,60,0)/100 -> 0
A11: Argentina | B11: ARG | C11: =VLOOKUP(A11,Data!$A$5:$BH$270,60,0)/100 -> 0
A12: Armenia | B12: ARM | C12: =VLOOKUP(A12,Data!$A$5:$BH$270,60,0)/100 -> 0.324
A13: American Samoa | B13: ASM | C13: =VLOOKUP(A13,Data!$A$5:$BH$270,60,0)/100 -> 0
... A267: Zimbabwe | B267: ZWE | C267: =VLOOKUP(A267,Data!$A$5:$BH$270,60,0)/100 -> 0.43933333

Sheet Metadata - Countries
A1: Country Code | B1: Region | C1: IncomeGroup | D1: SpecialNotes | E1: TableName
A2: ABW | B2: Latin America & Caribbean | C2: High income | E2: Aruba
A3: AFE | D3: 26 countries, stretching from the Red Sea in the North to the Cape of Good Hope in the South (https://www.worldbank.org/en/region/afr/eastern-and-southern-africa) | E3: Africa Eastern and Southern
A4: AFG | B4: Middle East & North Africa | C4: Low income | D4: The reporting period for national accounts data is designated as either calendar year basis (CY) or fiscal year basis (FY). For this country, it is fiscal year-based (fiscal year-end: March 20). Also, an estimate (PA.NUS.ATLS) of the exchange rate covers the same period and thus differs from the official exchange rate (CY). In addition, the World Bank systematically assesses the appropriateness of official exchange rates as conversion factors. In this country, multiple or dual exchange rate activity exists and must be accounted for appropriately in underlying statistics. An alternative estimate (“alternative conversion factor” - PA.NUS.ATLS) is thus calculated as a weighted average of the different exchange rates in use in the country. Doing so better reflects economic reality and leads to more accurate cross-country comparisons and country classifications by income level. For this country, this applies to the period 1960-2006. Alternative conversion factors are used in the Atlas methodology and elsewhere in World Development Indicators as single-year conversion factors. | E4: Afghanistan
A5: AFW | D5: 22 countries, stretching from the westernmost point of Africa, across the equator, and partly along the Atlantic Ocean till the Republic of Congo in the South (https://www.worldbank.org/en/region/afr/western-and-central-africa) | E5: Africa Western and Central
A6: AGO | B6: Sub-Saharan Africa | C6: Lower middle income | D6: The World Bank systematically assesses the appropriateness of official exchange rates as conversion factors. In this country, multiple or dual exchange rate activity exists and must be accounted for appropriately in underlying statistics. An alternative estimate (“alternative conversion factor” - PA.NUS.ATLS) is thus calculated as a weighted average of the different exchange rates in use in the country. Doing so better reflects economic reality and leads to more accurate cross-country comparisons and country classifications by income level. For this country, this applies to the period 1994-2024. Alternative conversion factors are used in the Atlas methodology and elsewhere in World Development Indicators as single-year conversion factors. | E6: Angola
A7: ALB | B7: Europe & Central Asia | C7: Upper middle income | E7: Albania
A8: AND | B8: Europe & Central Asia | C8: High income | E8: Andorra
A9: ARB | D9: Arab World aggregate. Arab World is composed of members of the League of Arab States. | E9: Arab World
A10: ARE | B10: Middle East & North Africa | C10: High income | E10: United Arab Emirates
A11: ARG | B11: Latin America & Caribbean | C11: Upper middle income | D11: The World Bank systematically assesses the appropriateness of official exchange rates as conversion factors. In this country, multiple or dual exchange rate activity exists and must be accounted for appropriately in underlying statistics. An alternative estimate (“alternative conversion factor” - PA.NUS.ATLS) is thus calculated as a weighted average of the different exchange rates in use in the country. Doing so better reflects economic reality and leads to more accurate cross-country comparisons and country classifications by income level. For this country, this applies to the period 1971-2018. Alternative conversion factors are used in the Atlas methodology and elsewhere in World Development Indicators as single-year conversion factors. | E11: Argentina
A12: ARM | B12: Europe & Central Asia | C12: Upper middle income | E12: Armenia
A13: ASM | B13: East Asia & Pacific | C13: High income | E13: American Samoa
A14: ATG | B14: Latin America & Caribbean | C14: High income | E14: Antigua and Barbuda
A15: AUS | B15: East Asia & Pacific | C15: High income | D15: The reporting period for national accounts data is designated as either calendar year basis (CY) or fiscal year basis (FY). For this country, it is fiscal year-based (fiscal year-end: June 30). Also, an estimate (PA.NUS.ATLS) of the exchange rate covers the same period and thus differs from the official exchange rate (CY). | E15: Australia
A16: AUT | B16: Europe & Central Asia | C16: High income | D16: A simple multiplier is used to convert the national currencies of EMU members to euros. The following irrevocable euro conversion rate was adopted by the EU Council on January 1, 1999: 1 euro = 13.7603 Austrian schilling. Please note that historical data before 1999 are not actual euros and are not comparable or suitable for aggregation across countries. | E16: Austria
A17: AZE | B17: Europe & Central Asia | C17: Upper middle income | E17: Azerbaijan
A18: BDI | B18: Sub-Saharan Africa | C18: Low income | D18: The World Bank systematically assesses the appropriateness of official exchange rates as conversion factors. In this country, multiple or dual exchange rate activity exists and must be accounted for appropriately in underlying statistics. An alternative estimate (“alternative conversion factor” - PA.NUS.ATLS) is thus calculated as a weighted average of the different exchange rates in use in the country. Doing so better reflects economic reality and leads to more accurate cross-country comparisons and country classifications by income level. For this country, this applies to the period 1983-2024. Alternative conversion factors are used in the Atlas methodology and elsewhere in World Development Indicators as single-year conversion factors. | E18: Burundi
A19: BEL | B19: Europe & Central Asia | C19: High income | D19: A simple multiplier is used to convert the national currencies of EMU members to euros. The following irrevocable euro conversion rate was adopted by the EU Council on January 1, 1999: 1 euro = 40.3399 Belgian franc. Please note that historical data before 1999 are not actual euros and are not comparable or suitable for aggregation across countries. | E19: Belgium
A20: BEN | B20: Sub-Saharan Africa | C20: Lower middle income | E20: Benin
A21: BFA | B21: Sub-Saharan Africa | C21: Low income | E21: Burkina Faso
A22: BGD | B22: South Asia | C22: Lower middle income | D22: The reporting period for national accounts data is designated as either calendar year basis (CY) or fiscal year basis (FY). For this country, it is fiscal year-based (fiscal year-end: June 30). Also, an estimate (PA.NUS.ATLS) of the exchange rate covers the same period and thus differs from the official exchange rate (CY). | E22: Bangladesh
A23: BGR | B23: Europe & Central Asia | C23: High income | E23: Bulgaria
A24: BHR | B24: Middle East & North Africa | C24: High income | E24: Bahrain
A25: BHS | B25: Latin America & Caribbean | C25: High income | E25: Bahamas, The
A26: BIH | B26: Europe & Central Asia | C26: Upper middle income | E26: Bosnia and Herzegovina
A27: BLR | B27: Europe & Central Asia | C27: Upper middle income | D27: Data before 2015 were adjusted to reflect the new denomination effective from July 1, 2016 (BYN), a decrease of 10,000 times (1 BYN = 10,000 BYR) | E27: Belarus
A28: BLZ | B28: Latin America & Caribbean | C28: Upper middle income | E28: Belize
A29: BMU | B29: North America | C29: High income | E29: Bermuda
A30: BOL | B30: Latin America & Caribbean | C30: Lower middle income | E30: Bolivia
A31: BRA | B31: Latin America & Caribbean | C31: Upper middle income | E31: Brazil
A32: BRB | B32: Latin America & Caribbean | C32: High income | E32: Barbados
A33: BRN | B33: East Asia & Pacific | C33: High income | E33: Brunei Darussalam
A34: BTN | B34: South Asia | C34: Lower middle income | E34: Bhutan
A35: BWA | B35: Sub-Saharan Africa | C35: Upper middle income | E35: Botswana
A36: CAF | B36: Sub-Saharan Africa | C36: Low income | E36: Central African Republic
A37: CAN | B37: North America | C37: High income | D37: Fiscal year end: March 31; reporting period for national accounts data: CY. | E37: Canada
A38: CEB | D38: Central Europe and the Baltics aggregate. | E38: Central Europe and the Baltics
A39: CHE | B39: Europe & Central Asia | C39: High income | E39: Switzerland
A40: CHI | B40: Europe & Central Asia | C40: High income | E40: Channel Islands
A41: CHL | B41: Latin America & Caribbean | C41: High income | E41: Chile
A42: CHN | B42: East Asia & Pacific | C42: Upper middle income | D42: On 1 July 1997 China resumed its exercise of sovereignty over Hong Kong, and on 20 December 1999, China resumed its exercise of sovereignty over Macao. Unless otherwise noted, data for China do not include data for Hong Kong SAR, China; Macao SAR, China; or Taiwan, China. The World Bank systematically assesses the appropriateness of official exchange rates as conversion factors. In this country, multiple or dual exchange rate activity exists and must be accounted for appropriately in underlying statistics. An alternative estimate (“alternative conversion factor” - PA.NUS.ATLS) is thus calculated as a weighted average of the different exchange rates in use in the country. Doing so better reflects economic reality and leads to more accurate cross-country comparisons and country classifications by income level. For this country, this applies to the period 1978-1993. Alternative conversion factors are used in the Atlas methodology and elsewhere in World Development Indicators as single-year conversion factors. | E42: China
A43: CIV | B43: Sub-Saharan Africa | C43: Lower middle income | E43: Côte d'Ivoire
A44: CMR | B44: Sub-Saharan Africa | C44: Lower middle income | E44: Cameroon
A45: COD | B45: Sub-Saharan Africa | C45: Low income | D45: The World Bank systematically assesses the appropriateness of official exchange rates as conversion factors. In this country, multiple or dual exchange rate activity exists and must be accounted for appropriately in underlying statistics. An alternative estimate (“alternative conversion factor” - PA.NUS.ATLS) is thus calculated as a weighted average of the different exchange rates in use in the country. Doing so better reflects economic reality and leads to more accurate cross-country comparisons and country classifications by income level. For this country, this applies to the period 1999-2004. Alternative conversion factors are used in the Atlas methodology and elsewhere in World Development Indicators as single-year conversion factors. | E45: Congo, Dem. Rep.
A46: COG | B46: Sub-Saharan Africa | C46: Lower middle income | E46: Congo, Rep.
A47: COL | B47: Latin America & Caribbean | C47: Upper middle income | E47: Colombia
A48: COM | B48: Sub-Saharan Africa | C48: Lower middle income | E48: Comoros
A49: CPV | B49: Sub-Saharan Africa | C49: Upper middle income | E49: Cabo Verde
A50: CRI | B50: Latin America & Caribbean | C50: High income | E50: Costa Rica
A51: CSS | D51: Caribbean small states aggregate. | E51: Caribbean small states
A52: CUB | B52: Latin America & Caribbean | C52: Upper middle income | E52: Cuba
A53: CUW | B53: Latin America & Caribbean | C53: High income | E53: Curaçao
A54: CYM | B54: Latin America & Caribbean | C54: High income | E54: Cayman Islands
A55: CYP | B55: Europe & Central Asia | C55: High income | D55: A simple multiplier is used to convert the national currencies of EMU members to euros. The following irrevocable euro conversion rate entered into force on January 1, 2008: 1 euro = 0.585274 Cyprus pounds. Please note that historical data are not actual euros and are not comparable or suitable for aggregation across countries. | E55: Cyprus
A56: CZE | B56: Europe & Central Asia | C56: High income | E56: Czechia
A57: DEU | B57: Europe & Central Asia | C57: High income | D57: A simple multiplier is used to convert the national currencies of EMU members to euros. The following irrevocable euro conversion rate was adopted by the EU Council on January 1, 1999: 1 euro = 1.95583 Deutsche Mark. Please note that historical data before 1999 are not actual euros and are not comparable or suitable for aggregation across countries. GDP data before 1991 are calculated by applying backward GDP growth rates of the former Federal Republic of Germany starting from the first official GDP value for the unified Germany (1991). | E57: Germany
A58: DJI | B58: Middle East & North Africa | C58: Lower middle income | E58: Djibouti
A59: DMA | B59: Latin America & Caribbean | C59: Upper middle income | E59: Dominica
A60: DNK | B60: Europe & Central Asia | C60: High income | E60: Denmark
A61: DOM | B61: Latin America & Caribbean | C61: Upper middle income | E61: Dominican Republic
A62: DZA | B62: Middle East & North Africa | C62: Upper middle income | E62: Algeria
A63: EAP | E63: East Asia & Pacific (excluding high income)
A64: EAR | D64: Early-dividend countries are mostly lower-middle-income countries further along the fertility transition. Fertility rates have fallen below four births per woman and the working-age share of the population is likely rising considerably. | E64: Early-demographic dividend
A65: EAS | D65: East Asia and Pacific regional aggregate (includes all income levels). | E65: East Asia & Pacific
A66: ECA | E66: Europe & Central Asia (excluding high income)
A67: ECS | D67: Europe and Central Asia regional aggregate (includes all income levels). | E67: Europe & Central Asia
A68: ECU | B68: Latin America & Caribbean | C68: Upper middle income | E68: Ecuador
A69: EGY | B69: Middle East & North Africa | C69: Lower middle income | D69: The reporting period for national accounts data is designated as either calendar year basis (CY) or fiscal year basis (FY). For this country, it is fiscal year-based (fiscal year-end: June 30) for the years 1980 and after. The data from 1973 to 1979 refer to the calendar year data. Also, an estimate (PA.NUS.ATLS) of the exchange rate covers the same period and thus differs from the official exchange rate (CY). In addition, the World Bank systematically assesses the appropriateness of official exchange rates as conversion factors. In this country, multiple or dual exchange rate activity exists and must be accounted for appropriately in underlying statistics. An alternative estimate (“alternative conversion factor” - PA.NUS.ATLS) is thus calculated as a weighted average of the different exchange rates in use in the country. Doing so better reflects economic reality and leads to more accurate cross-country comparisons and country classifications by income level. For this country, this applies to the period 1965-2021. Alternative conversion factors are used in the Atlas methodology and elsewhere in World Development Indicators as single-year conversion factors. The national accounts data for Egypt has been updated to reflect local constant prices in the year 2022, moving from the previous reference of 2017. | E69: Egypt, Arab Rep.
A70: EMU | D70: Euro area aggregate. | E70: Euro area
A71: ERI | B71: Sub-Saharan Africa | C71: Low income | D71: The World Bank systematically assesses the appropriateness of official exchange rates as conversion factors. In this country, multiple or dual exchange rate activity exists and must be accounted for appropriately in underlying statistics. An alternative estimate (“alternative conversion factor” - PA.NUS.ATLS) is thus calculated as a weighted average of the different exchange rates in use in the country. Doing so better reflects economic reality and leads to more accurate cross-country comparisons and country classifications by income level. For this country, this applies to the period 1992-1997. Alternative conversion factors are used in the Atlas methodology and elsewhere in World Development Indicators as single-year conversion factors. | E71: Eritrea
A72: ESP | B72: Europe & Central Asia | C72: High income | D72: A simple multiplier is used to convert the national currencies of EMU members to euros. The following irrevocable euro conversion rate was adopted by the EU Council on January 1, 1999: 1 euro = 166.386 Spanish peseta. Please note that historical data before 1999 are not actual euros and are not comparable or suitable for aggregation across countries. | E72: Spain
A73: EST | B73: Europe & Central Asia | C73: High income | D73: The following irrevocable euro conversion rate entered into force on January 1, 2011: 1 euro = 15.6466 Estonian kroon. Please note that historical data are not actual euros and are not comparable or suitable for aggregation across countries. | E73: Estonia
A74: ETH | B74: Sub-Saharan Africa | D74: The reporting period for national accounts data is designated as either calendar year basis (CY) or fiscal year basis (FY). For this country, it is fiscal year-based (fiscal year-end: July 7). Also, an estimate (PA.NUS.ATLS) of the exchange rate covers the same period and thus differs from the official exchange rate (CY). | E74: Ethiopia
A75: EUU | D75: European Union aggregate. | E75: European Union
A76: FCS | D76: Fragile and conflict-affected situations aggregate as of FY25 (July 1, 2024-June 30, 2025). Countries are distinguished based on the nature and severity of issues they face and classified into two categories: (i) Countries with significant institutional and social fragility, determined by indicators of policy quality and fragility. (ii) Countries experiencing violent conflict, classified by conflict-related deaths per capita and further divided into high-intensity and medium-intensity conflict subcategories. For more information, please visit https://www.worldbank.org/en/topic/fragilityconflictviolence/brief/classification-of-fragile-and-conflict-affected-situations. | E76: Fragile and conflict affected situations
A77: FIN | B77: Europe & Central Asia | C77: High income | D77: A simple multiplier is used to convert the national currencies of EMU members to euros. The following irrevocable euro conversion rate was adopted by the EU Council on January 1, 1999: 1 euro = 5.94573 Finnish markka. Please note that historical data before 1999 are not actual euros and are not comparable or suitable for aggregation across countries. | E77: Finland
A78: FJI | B78: East Asia & Pacific | C78: Upper middle income | E78: Fiji
A79: FRA | B79: Europe & Central Asia | C79: High income | D79: The following irrevocable euro conversion rate was adopted by the EU Council on January 1, 1999: 1 euro = 6.55957 French franc. Please note that historical data before 1999 are not actual euros and are not comparable or suitable for aggregation across countries. | E79: France
A80: FRO | B80: Europe & Central Asia | C80: High income | E80: Faroe Islands
A81: FSM | B81: East Asia & Pacific | C81: Lower middle income | D81: Fiscal year ends on September 30; reporting period for national accounts data: FY. The source for national accounts data is the Pacific and Virgin Islands Training Initiative. | E81: Micronesia, Fed. Sts.
A82: GAB | B82: Sub-Saharan Africa | C82: Upper middle income | E82: Gabon
A83: GBR | B83: Europe & Central Asia | C83: High income | E83: United Kingdom
A84: GEO | B84: Europe & Central Asia | C84: Upper middle income | D84: Includes self-governed areas only, which mostly exclude Abkhazia and South Ossetia, but small areas in Abkhazia and South Ossetia are included before 2008 or 2009 because of the changes in self-governed areas. | E84: Georgia
A85: GHA | B85: Sub-Saharan Africa | C85: Lower middle income | D85: The World Bank systematically assesses the appropriateness of official exchange rates as conversion factors. In this country, multiple or dual exchange rate activity exists and must be accounted for appropriately in underlying statistics. An alternative estimate (“alternative conversion factor” - PA.NUS.ATLS) is thus calculated as a weighted average of the different exchange rates in use in the country. Doing so better reflects economic reality and leads to more accurate cross-country comparisons and country classifications by income level. For this country, this applies to the period 1974-1987. Alternative conversion factors are used in the Atlas methodology and elsewhere in World Development Indicators as single-year conversion factors. | E85: Ghana
A86: GIB | B86: Europe & Central Asia | C86: High income | D86: The DEC conversion is not reported when national accounts data are unavailable. | E86: Gibraltar
A87: GIN | B87: Sub-Saharan Africa | C87: Lower middle income | E87: Guinea
A88: GMB | B88: Sub-Saharan Africa | C88: Low income | E88: Gambia, The
A89: GNB | B89: Sub-Saharan Africa | C89: Low income | E89: Guinea-Bissau
A90: GNQ | B90: Sub-Saharan Africa | C90: Upper middle income | E90: Equatorial Guinea
A91: GRC | B91: Europe & Central Asia | C91: High income | D91: A simple multiplier is used to convert the national currencies of EMU members to euros. The following irrevocable euro conversion rate was adopted by the EU Council on January 1, 1999: 1 euro = 340.75 Greek drachma. Please note that historical data before 1999 are not actual euros and are not comparable or suitable for aggregation across countries. | E91: Greece
A92: GRD | B92: Latin America & Caribbean | C92: Upper middle income | E92: Grenada
A93: GRL | B93: Europe & Central Asia | C93: High income | E93: Greenland
A94: GTM | B94: Latin America & Caribbean | C94: Upper middle income | D94: The World Bank systematically assesses the appropriateness of official exchange rates as conversion factors. In this country, multiple or dual exchange rate activity exists and must be accounted for appropriately in underlying statistics. An alternative estimate (“alternative conversion factor” - PA.NUS.ATLS) is thus calculated as a weighted average of the different exchange rates in use in the country. Doing so better reflects economic reality and leads to more accurate cross-country comparisons and country classifications by income level. For this country, this applies to the period 1985-2003. Alternative conversion factors are used in the Atlas methodology and elsewhere in World Development Indicators as single-year conversion factors. | E94: Guatemala
A95: GUM | B95: East Asia & Pacific | C95: High income | E95: Guam
A96: GUY | B96: Latin America & Caribbean | C96: High income | E96: Guyana
A97: HIC | D97: High income group aggregate. High-income economies are those in which 2024 Atlas GNI per capita was more than $13,935. | E97: High income
A98: HKG | B98: East Asia & Pacific | C98: High income | D98: On 1 July 1997 China resumed its exercise of sovereignty over Hong Kong. Unless otherwise noted, data for China do not include data for Hong Kong SAR, China; Macao SAR, China; or Taiwan, China. Agriculture value added includes mining and quarrying. | E98: Hong Kong SAR, China
A99: HND | B99: Latin America & Caribbean | C99: Lower middle income | D99: The World Bank systematically assesses the appropriateness of official exchange rates as conversion factors. In this country, multiple or dual exchange rate activity exists and must be accounted for appropriately in underlying statistics. An alternative estimate (“alternative conversion factor” - PA.NUS.ATLS) is thus calculated as a weighted average of the different exchange rates in use in the country. Doing so better reflects economic reality and leads to more accurate cross-country comparisons and country classifications by income level. For this country, this applies to the period 1988-1989. Alternative conversion factors are used in the Atlas methodology and elsewhere in World Development Indicators as single-year conversion factors. | E99: Honduras
A100: HPC | D100: The Heavily Indebted Poor Countries (HIPC) Initiative, launched in 1996 by the IMF and World Bank, aims to reduce the external debt burdens of the most indebted poor countries. Most participants have completed the program, receiving a total of $76 billion in debt-service relief. For more information, visit https://www.imf.org/en/About/Factsheets/Sheets/2016/08/01/16/11/Debt-Relief-Under-the-Heavily-Indebted-Poor-Countries-Initiative. Data presented are aggregates for HIPC countries. | E100: Heavily indebted poor countries (HIPC)
...

Sheet Metadata - Indicators
A1: INDICATOR_CODE | B1: INDICATOR_NAME | C1: SOURCE_NOTE | D1: SOURCE_ORGANIZATION
A2: SI.POV.GINI | B2: Gini index | C2: Gini index measures the extent to which the distribution of income (or, in some cases, consumption expenditure) among individuals or households within an economy deviates from a perfectly equal distribution. A Lorenz curve plots the cumulative percentages of total income received against the cumulative number of recipients, starting with the poorest individual or household. The Gini index measures the area between the Lorenz curve and a hypothetical line of absolute equality, expressed as a percentage of the maximum area under the line. Thus a Gini index of 0 represents perfect equality, while an index of 100 implies perfect inequality. | D2: World Bank, Poverty and Inequality Platform. Data are based on primary household survey data obtained from government statistical agencies and World Bank country departments. Data for high-income economies are mostly from the Luxembourg Income Study database. For more information and methodology, please see http://pip.worldbank.org., World Bank (WB), uri: http://pip.worldbank.org, note: Data are based on primary household survey data obtained from government statistical agencies and World Bank country departments. Data for high-income economies are mostly from the Luxembourg Income Study database.
