Workbook

Sheet lowest_10
A1: Data Source | B1: World Development Indicators
A2: Last Updated Date | B2: 46007
A4: Country Name | B4: Country Code | C4: Indicator Name | D4: Indicator Code | E4: 1960 | F4: 1961 | G4: 1962 | H4: 1963 | I4: 1964 | J4: 1965 | K4: 1966 | L4: 1967 | M4: 1968 | N4: 1969 | O4: 1970 | P4: 1971 | Q4: 1972 | R4: 1973 | S4: 1974 | T4: 1975 | U4: 1976 | V4: 1977 | W4: 1978 | X4: 1979 | Y4: 1980 | Z4: 1981 | AA4: 1982 | AB4: 1983 | AC4: 1984 | AD4: 1985 | AE4: 1986 | AF4: 1987 | AG4: 1988 | AH4: 1989 | AI4: 1990 | AJ4: 1991 | AK4: 1992 | AL4: 1993 | AM4: 1994 | AN4: 1995 | AO4: 1996 | AP4: 1997 | AQ4: 1998 | AR4: 1999 | AS4: 2000 | AT4: 2001 | AU4: 2002 | AV4: 2003 | AW4: 2004 | AX4: 2005 | AY4: 2006 | AZ4: 2007 | BA4: 2008 | BB4: 2009 | BC4: 2010 | BD4: 2011 | BE4: 2012 | BF4: 2013 | BG4: 2014 | BH4: 2015 | BI4: 2016 | BJ4: 2017 | BK4: 2018 | BL4: 2019 | BM4: 2020 | BN4: 2021 | BO4: 2022 | BP4: 2023 | BQ4: 2024
A5: Aruba | B5: ABW | C5: Income share held by lowest 10% | D5: SI.DST.FRST.10
A6: Africa Eastern and Southern | B6: AFE | C6: Income share held by lowest 10% | D6: SI.DST.FRST.10
A7: Afghanistan | B7: AFG | C7: Income share held by lowest 10% | D7: SI.DST.FRST.10
A8: Africa Western and Central | B8: AFW | C8: Income share held by lowest 10% | D8: SI.DST.FRST.10
A9: Angola | B9: AGO | C9: Income share held by lowest 10% | D9: SI.DST.FRST.10 | AS9: 1 | BA9: 2.1 | BK9: 1.3
A10: Albania | B10: ALB | C10: Income share held by lowest 10% | D10: SI.DST.FRST.10 | AO10: 3.9 | AU10: 3.5 | AX10: 3.5 | BA10: 3.7 | BE10: 3.7 | BG10: 2.9 | BH10: 3.2 | BI10: 3 | BJ10: 3.1 | BK10: 3.2 | BL10: 3.5 | BM10: 3.4
A11: Andorra | B11: AND | C11: Income share held by lowest 10% | D11: SI.DST.FRST.10
A12: Arab World | B12: ARB | C12: Income share held by lowest 10% | D12: SI.DST.FRST.10
A13: United Arab Emirates | B13: ARE | C13: Income share held by lowest 10% | D13: SI.DST.FRST.10 | BF13: 2.3 | BK13: 2.8
A14: Argentina | B14: ARG | C14: Income share held by lowest 10% | D14: SI.DST.FRST.10 | Y14: 2 | AE14: 1.8 | AF14: 1.6 | AJ14: 1.8 | AK14: 1.6 | AL14: 1.5 | AM14: 1.5 | AN14: 1.2 | AO14: 1.1 | AP14: 1.1 | AQ14: 1.1 | AR14: 1.1 | AS14: 1 | AT14: 0.7 | AU14: 0.9 | AV14: 1.1 | AW14: 1.2 | AX14: 1.3 | AY14: 1.3 | AZ14: 1.4 | BA14: 1.4 | BB14: 1.4 | BC14: 1.6 | BD14: 1.7 | BE14: 1.7 | BF14: 1.8 | BG14: 1.8 | BI14: 1.7 | BJ14: 1.8 | BK14: 1.7 | BL14: 1.6 | BM14: 1.7 | BN14: 1.8 | BO14: 2 | BP14: 1.9 | BQ14: 1.9
A15: Armenia | B15: ARM | C15: Income share held by lowest 10% | D15: SI.DST.FRST.10 | AO15: 2.3 | AR15: 3 | AT15: 3.2 | AU15: 3.3 | AV15: 3.7 | AW15: 3.1 | AX15: 3.3 | AY15: 3.7 | AZ15: 3.5 | BA15: 3.9 | BB15: 4 | BC15: 3.9 | BD15: 3.8 | BE15: 3.8 | BF15: 3.6 | BG15: 3.5 | BH15: 3.4 | BI15: 3.3 | BJ15: 3.5 | BK15: 3.3 | BL15: 3.7 | BM15: 4.4 | BN15: 4 | BO15: 3.9 | BP15: 4
A16: American Samoa | B16: ASM | C16: Income share held by lowest 10% | D16: SI.DST.FRST.10
A17: Antigua and Barbuda | B17: ATG | C17: Income share held by lowest 10% | D17: SI.DST.FRST.10
A18: Australia | B18: AUS | C18: Income share held by lowest 10% | D18: SI.DST.FRST.10 | Z18: 2.9 | AD18: 2.7 | AH18: 2.7 | AN18: 2.9 | AT18: 2.8 | AV18: 2.8 | AW18: 3.1 | BA18: 2.8 | BC18: 2.8 | BG18: 2.9 | BI18: 2.9 | BK18: 2.8 | BM18: 2.7
A19: Austria | B19: AUT | C19: Income share held by lowest 10% | D19: SI.DST.FRST.10 | AM19: 3.1 | AN19: 3.3 | AO19: 3.5 | AP19: 3.4 | AQ19: 3.3 | AR19: 3.6 | AS19: 3.5 | AV19: 3.3 | AW19: 3.4 | AX19: 3.5 | AY19: 3.4 | AZ19: 3.1 | BA19: 3 | BB19: 2.8 | BC19: 3.1 | BD19: 2.9 | BE19: 2.8 | BF19: 3.1 | BG19: 3.1 | BH19: 3 | BI19: 2.8 | BJ19: 3 | BK19: 3 | BL19: 2.9 | BM19: 2.9 | BN19: 2.8 | BO19: 2.8 | BP19: 2.8
A20: Azerbaijan | B20: AZE | C20: Income share held by lowest 10% | D20: SI.DST.FRST.10 | AN20: 2.7 | AT20: 3.1 | AU20: 4.8 | AV20: 4.5 | AW20: 4.8 | AX20: 4.8
A21: Burundi | B21: BDI | C21: Income share held by lowest 10% | D21: SI.DST.FRST.10 | AK21: 3.4 | AQ21: 1.9 | AY21: 4 | BF21: 2.8 | BM21: 2.9
A22: Belgium | B22: BEL | C22: Income share held by lowest 10% | D22: SI.DST.FRST.10 | AD22: 4.2 | AG22: 4 | AK22: 3.9 | AN22: 3.4 | AP22: 3.6 | AS22: 3.4 | AV22: 3.3 | AW22: 3.4 | AX22: 3.4 | AY22: 3.4 | AZ22: 3.4 | BA22: 3.4 | BB22: 3.2 | BC22: 3.3 | BD22: 3.3 | BE22: 3.4 | BF22: 3.3 | BG22: 3.4 | BH22: 3.4 | BI22: 3.4 | BJ22: 3.4 | BK22: 3.5 | BL22: 3.6 | BM22: 3.7 | BN22: 3.6 | BO22: 3.8 | BP22: 3.7
A23: Benin | B23: BEN | C23: Income share held by lowest 10% | D23: SI.DST.FRST.10 | AV23: 2.9 | BD23: 2.5 | BH23: 1.1 | BK23: 2.9 | BN23: 3.1
A24: Burkina Faso | B24: BFA | C24: Income share held by lowest 10% | D24: SI.DST.FRST.10 | AM24: 2.3 | AQ24: 2 | AV24: 2.3 | BB24: 2.7 | BG24: 3.6 | BK24: 2.6 | BN24: 3
A25: Bangladesh | B25: BGD | C25: Income share held by lowest 10% | D25: SI.DST.FRST.10 | AB25: 4.1 | AD25: 4.5 | AG25: 4.2 | AJ25: 4.1 | AN25: 3.8 | AS25: 3.7 | AX25: 3.8 | BC25: 3.9 | BI25: 3.7 | BO25: 3.7
A26: Bulgaria | B26: BGR | C26: Income share held by lowest 10% | D26: SI.DST.FRST.10 | AH26: 4.6 | AK26: 3.5 | AM26: 4.4 | AN26: 3 | AP26: 4.5 | AT26: 2.6 | AV26: 3.4 | AY26: 1.6 | AZ26: 2.2 | BA26: 2.4 | BB26: 2.4 | BC26: 2.1 | BD26: 2.1 | BE26: 2 | BF26: 1.8 | BG26: 2 | BH26: 1.5 | BI26: 1.6 | BJ26: 1.9 | BK26: 1.9 | BL26: 1.9 | BM26: 2.2 | BN26: 2 | BO26: 2.1 | BP26: 2.1
A27: Bahrain | B27: BHR | C27: Income share held by lowest 10% | D27: SI.DST.FRST.10
A28: Bahamas, The | B28: BHS | C28: Income share held by lowest 10% | D28: SI.DST.FRST.10
A29: Bosnia and Herzegovina | B29: BIH | C29: Income share held by lowest 10% | D29: SI.DST.FRST.10 | AT29: 3.6 | AW29: 2.9 | AZ29: 3 | BD29: 2.9
A30: Belarus | B30: BLR | C30: Income share held by lowest 10% | D30: SI.DST.FRST.10 | AL30: 4.9 | AN30: 3.5 | AQ30: 3.1 | AR30: 3 | AS30: 3.1 | AT30: 3.3 | AU30: 3.3 | AV30: 3.5 | AW30: 3.8 | AX30: 3.6 | AY30: 3.6 | AZ30: 3.5 | BA30: 3.7 | BB30: 3.7 | BC30: 3.6 | BD30: 3.8 | BE30: 4 | BF30: 4 | BG30: 3.9 | BH30: 4.1 | BI30: 4.2 | BJ30: 4.3 | BK30: 4.3 | BL30: 4.2 | BM30: 4.5
A31: Belize | B31: BLZ | C31: Income share held by lowest 10% | D31: SI.DST.FRST.10 | AL31: 0.9 | AM31: 1 | AN31: 0.8 | AO31: 1 | AP31: 0.7 | AQ31: 1.1 | AR31: 0.9 | BK31: 2.2
A32: Bermuda | B32: BMU | C32: Income share held by lowest 10% | D32: SI.DST.FRST.10
A33: Bolivia | B33: BOL | C33: Income share held by lowest 10% | D33: SI.DST.FRST.10 | AI33: 2.3 | AK33: 1.7 | AP33: 0.5 | AR33: 0.3 | AS33: 0.3 | AT33: 0.5 | AU33: 0.4 | AW33: 0.9 | AX33: 0.5 | AY33: 0.6 | AZ33: 0.8 | BA33: 0.9 | BB33: 0.8 | BD33: 1.1 | BE33: 0.9 | BF33: 1 | BG33: 1.1 | BH33: 1.1 | BI33: 1 | BJ33: 1.1 | BK33: 1.4 | BL33: 1.7 | BM33: 1.5 | BN33: 1.8 | BO33: 1.7 | BP33: 1.8
A34: Brazil | B34: BRA | C34: Income share held by lowest 10% | D34: SI.DST.FRST.10 | Z34: 0.9 | AA34: 0.9 | AB34: 0.9 | AC34: 0.9 | AD34: 1 | AE34: 0.9 | AF34: 0.8 | AG34: 0.7 | AH34: 0.6 | AI34: 0.8 | AK34: 0.9 | AL34: 0.7 | AN34: 0.8 | AO34: 0.7 | AP34: 0.7 | AQ34: 0.8 | AR34: 0.8 | AT34: 0.8 | AU34: 0.9 | AV34: 0.9 | AW34: 0.9 | AX34: 1 | AY34: 1 | AZ34: 1 | BA34: 1 | BB34: 1 | BD34: 1.1 | BE34: 1.1 | BF34: 1.2 | BG34: 1.2 | BH34: 1.2 | BI34: 1.1 | BJ34: 1 | BK34: 1 | BL34: 0.9 | BM34: 1.6 | BN34: 1 | BO34: 1.2 | BP34: 1.3
A35: Barbados | B35: BRB | C35: Income share held by lowest 10% | D35: SI.DST.FRST.10 | BI35: 2.5
A36: Brunei Darussalam | B36: BRN | C36: Income share held by lowest 10% | D36: SI.DST.FRST.10
A37: Bhutan | B37: BTN | C37: Income share held by lowest 10% | D37: SI.DST.FRST.10 | AV37: 2.8 | AZ37: 2.7 | BE37: 2.7 | BJ37: 2.7 | BO37: 3.6
A38: Botswana | B38: BWA | C38: Income share held by lowest 10% | D38: SI.DST.FRST.10 | AD38: 1.4 | AL38: 1.2 | AU38: 1 | BB38: 1.2 | BH38: 1.4
A39: Central African Republic | B39: CAF | C39: Income share held by lowest 10% | D39: SI.DST.FRST.10 | AK39: 1.5 | BA39: 1.2 | BN39: 2.1
A40: Canada | B40: CAN | C40: Income share held by lowest 10% | D40: SI.DST.FRST.10 | P40: 1.8 | R40: 2.1 | T40: 2.3 | V40: 2.3 | X40: 2.3 | Z40: 2.5 | AA40: 2.6 | AC40: 2.4 | AD40: 2.6 | AE40: 2.7 | AF40: 2.8 | AG40: 2.9 | AH40: 2.8 | AI40: 2.6 | AJ40: 2.6 | AK40: 2.8 | AL40: 2.7 | AM40: 2.8 | AN40: 2.8 | AO40: 2.9 | AP40: 2.9 | AQ40: 2.8 | AR40: 2.8 | AS40: 2.8 | AT40: 2.8 | AU40: 2.7 | AV40: 2.7 | AW40: 2.7 | AX40: 2.7 | AY40: 2.8 | AZ40: 2.8 | BA40: 2.7 | BB40: 2.7 | BC40: 2.8 | BD40: 2.9 | BE40: 2.6 | BF40: 2.5 | BG40: 2.7 | BH40: 2.6 | BI40: 2.9 | BJ40: 2.8 | BK40: 2.9 | BL40: 3 | BM40: 3.5 | BN40: 3.3
A41: Central Europe and the Baltics | B41: CEB | C41: Income share held by lowest 10% | D41: SI.DST.FRST.10
A42: Switzerland | B42: CHE | C42: Income share held by lowest 10% | D42: SI.DST.FRST.10 | AA42: 3 | AK42: 2.9 | AS42: 3.2 | AU42: 3.4 | AW42: 3.4 | AY42: 2.9 | AZ42: 2.9 | BA42: 3 | BB42: 3.1 | BC42: 3.1 | BD42: 3.2 | BE42: 3.3 | BF42: 3.3 | BG42: 3.2 | BH42: 3.2 | BI42: 3 | BJ42: 3.1 | BK42: 3 | BL42: 2.9 | BM42: 3 | BN42: 3 | BO42: 2.9
A43: Channel Islands | B43: CHI | C43: Income share held by lowest 10% | D43: SI.DST.FRST.10
A44: Chile | B44: CHL | C44: Income share held by lowest 10% | D44: SI.DST.FRST.10 | AF44: 1.2 | AI44: 1.2 | AK44: 1.4 | AM44: 1.2 | AO44: 1.3 | AQ44: 1.3 | AS44: 1.3 | AV44: 1.4 | AY44: 1.8 | BB44: 1.9 | BD44: 2 | BF44: 2.1 | BH44: 2.2 | BJ44: 2.2 | BM44: 1.7 | BO44: 2.3
A45: China | B45: CHN | C45: Income share held by lowest 10% | D45: SI.DST.FRST.10 | Z45: 3.7 | AC45: 3.8 | AF45: 3.3 | AI45: 3.5 | AL45: 3.3 | AO45: 3.1 | AR45: 2.7 | AU45: 2.3 | AX45: 2.4 | BA45: 2.1 | BC45: 2 | BD45: 2.1 | BE45: 2.1 | BF45: 2.5 | BG45: 2.5 | BH45: 2.6 | BI45: 2.7 | BJ45: 2.6 | BK45: 2.7 | BL45: 2.8 | BM45: 3.1 | BN45: 3.2 | BO45: 3.1
A46: Cote d'Ivoire | B46: CIV | C46: Income share held by lowest 10% | D46: SI.DST.FRST.10 | AD46: 1.8 | AE46: 2.8 | AF46: 2.5 | AG46: 2.7 | AK46: 2.3 | AN46: 2.7 | AQ46: 2.6 | AU46: 2.3 | BA46: 1.8 | BH46: 2.1 | BK46: 2.9 | BN46: 3.1
A47: Cameroon | B47: CMR | C47: Income share held by lowest 10% | D47: SI.DST.FRST.10 | AO47: 2.5 | AT47: 2.5 | AZ47: 2.5 | BG47: 1.7 | BN47: 2.1
A48: Congo, Dem. Rep. | B48: COD | C48: Income share held by lowest 10% | D48: SI.DST.FRST.10 | AW48: 2.6 | BE48: 2.1 | BM48: 2.1
A49: Congo, Rep. | B49: COG | C49: Income share held by lowest 10% | D49: SI.DST.FRST.10 | AX49: 2 | BD49: 1.6
A50: Colombia | B50: COL | C50: Income share held by lowest 10% | D50: SI.DST.FRST.10 | Y50: 1 | AG50: 1.2 | AH50: 1.4 | AJ50: 1.3 | AK50: 1.1 | AO50: 0.6 | AR50: 0.5 | AS50: 0.3 | AT50: 0.6 | AU50: 1.1 | AV50: 1.2 | AW50: 1.2 | AX50: 1.2 | BA50: 1 | BB50: 1.1 | BC50: 1.1 | BD50: 1.2 | BE50: 1.2 | BF50: 1.2 | BG50: 1.2 | BH50: 1.3 | BI50: 1.3 | BJ50: 1.4 | BK50: 1.4 | BL50: 1.2 | BM50: 0.9 | BN50: 1 | BO50: 1 | BP50: 1.1
A51: Comoros | B51: COM | C51: Income share held by lowest 10% | D51: SI.DST.FRST.10 | AW51: 1.5 | BG51: 1.6
A52: Cabo Verde | B52: CPV | C52: Income share held by lowest 10% | D52: SI.DST.FRST.10 | AT52: 1.6 | AZ52: 2 | BH52: 2.2
A53: Costa Rica | B53: CRI | C53: Income share held by lowest 10% | D53: SI.DST.FRST.10 | Z53: 1.1 | AE53: 1.5 | AH53: 1 | AI53: 1 | AJ53: 1 | AK53: 1.1 | AL53: 1.1 | AM53: 1.2 | AN53: 1.2 | AO53: 1.1 | AP53: 1.3 | AQ53: 1.4 | AR53: 1.2 | AS53: 1.2 | AT53: 1.1 | AU53: 1.1 | AV53: 1.1 | AW53: 1.3 | AX53: 1.4 | AY53: 1.4 | AZ53: 1.5 | BA53: 1.5 | BB53: 1.3 | BC53: 1.6 | BD53: 1.5 | BE53: 1.5 | BF53: 1.4 | BG53: 1.5 | BH53: 1.5 | BI53: 1.5 | BJ53: 1.6 | BK53: 1.5 | BL53: 1.6 | BM53: 1.4 | BN53: 1.6 | BO53: 1.7 | BP53: 1.6 | BQ53: 1.7
A54: Caribbean small states | B54: CSS | C54: Income share held by lowest 10% | D54: SI.DST.FRST.10
A55: Cuba | B55: CUB | C55: Income share held by lowest 10% | D55: SI.DST.FRST.10
A56: Curacao | B56: CUW | C56: Income share held by lowest 10% | D56: SI.DST.FRST.10
A57: Cayman Islands | B57: CYM | C57: Income share held by lowest 10% | D57: SI.DST.FRST.10
A58: Cyprus | B58: CYP | C58: Income share held by lowest 10% | D58: SI.DST.FRST.10 | AW58: 3.7 | AX58: 3.8 | AY58: 3.7 | AZ58: 3.7 | BA58: 3.7 | BB58: 3.5 | BC58: 3.6 | BD58: 3.4 | BE58: 3.3 | BF58: 3.1 | BG58: 3 | BH58: 3.2 | BI58: 3.4 | BJ58: 3.4 | BK58: 3.5 | BL58: 3.5 | BM58: 3.6 | BN58: 3.5 | BO58: 3.6 | BP58: 3.6
A59: Czechia | B59: CZE | C59: Income share held by lowest 10% | D59: SI.DST.FRST.10 | AK59: 5.3 | AL59: 4.8 | AO59: 4.2 | AU59: 4.1 | AW59: 3.6 | AX59: 3.8 | AY59: 3.7 | AZ59: 3.9 | BA59: 3.9 | BB59: 3.8 | BC59: 3.7 | BD59: 3.7 | BE59: 3.9 | BF59: 3.8 | BG59: 3.9 | BH59: 3.9 | BI59: 4 | BJ59: 4.2 | BK59: 4.2 | BL59: 4.2 | BM59: 4 | BN59: 3.9 | BO59: 3.8 | BP59: 3.8
A60: Germany | B60: DEU | C60: Income share held by lowest 10% | D60: SI.DST.FRST.10 | AJ60: 3.8 | AK60: 3.7 | AL60: 3.8 | AM60: 3.5 | AN60: 3.5 | AO60: 3.8 | AP60: 3.7 | AQ60: 3.7 | AR60: 3.6 | AS60: 3.6 | AT60: 3.6 | AU60: 3.5 | AV60: 3.5 | AW60: 3.5 | AX60: 3.4 | AY60: 3.4 | AZ60: 3.5 | BA60: 3.5 | BB60: 3.4 | BC60: 3.5 | BD60: 3.5 | BE60: 3.3 | BF60: 3.4 | BG60: 3.2 | BH60: 3.2 | BI60: 3.2 | BJ60: 3.1 | BK60: 3.1 | BL60: 3.1 | BM60: 2.9
A61: Djibouti | B61: DJI | C61: Income share held by lowest 10% | D61: SI.DST.FRST.10 | AU61: 2.3 | BE61: 1.3 | BF61: 1.7 | BJ61: 1.9
A62: Dominica | B62: DMA | C62: Income share held by lowest 10% | D62: SI.DST.FRST.10
A63: Denmark | B63: DNK | C63: Income share held by lowest 10% | D63: SI.DST.FRST.10 | AF63: 3.8 | AK63: 3.9 | AN63: 4.6 | AS63: 4.5 | AV63: 4 | AW63: 4 | AX63: 4 | AY63: 4 | AZ63: 3.9 | BA63: 3.9 | BB63: 3.5 | BC63: 3.7 | BD63: 3.7 | BE63: 3.7 | BF63: 3.6 | BG63: 3.5 | BH63: 3.7 | BI63: 3.7 | BJ63: 3.7 | BK63: 3.7 | BL63: 3.8 | BM63: 3.7 | BN63: 3.7 | BO63: 3.6 | BP63: 3.6
A64: Dominican Republic | B64: DOM | C64: Income share held by lowest 10% | D64: SI.DST.FRST.10 | AE64: 1.4 | AH64: 1.7 | AK64: 1.6 | AO64: 1.5 | AP64: 1.3 | AS64: 1.2 | AT64: 1.5 | AU64: 1.3 | AV64: 1.3 | AW64: 1.4 | AX64: 1.5 | AY64: 1.4 | AZ64: 1.6 | BA64: 1.7 | BB64: 1.7 | BC64: 1.8 | BD64: 1.8 | BE64: 1.9 | BF64: 1.9 | BG64: 1.9 | BH64: 1.9 | BI64: 1.8 | BJ64: 2.3 | BK64: 2.3 | BL64: 2.3 | BM64: 2.4 | BN64: 2.6 | BO64: 2.6 | BP64: 2.3 | BQ64: 2.3
A65: Algeria | B65: DZA | C65: Income share held by lowest 10% | D65: SI.DST.FRST.10 | AG65: 2.8 | AN65: 2.9 | BD65: 4
A66: East Asia & Pacific (excluding high income) | B66: EAP | C66: Income share held by lowest 10% | D66: SI.DST.FRST.10
A67: Early-demographic dividend | B67: EAR | C67: Income share held by lowest 10% | D67: SI.DST.FRST.10
A68: East Asia & Pacific | B68: EAS | C68: Income share held by lowest 10% | D68: SI.DST.FRST.10
A69: Europe & Central Asia (excluding high income) | B69: ECA | C69: Income share held by lowest 10% | D69: SI.DST.FRST.10
A70: Europe & Central Asia | B70: ECS | C70: Income share held by lowest 10% | D70: SI.DST.FRST.10
A71: Ecuador | B71: ECU | C71: Income share held by lowest 10% | D71: SI.DST.FRST.10 | AF71: 1 | AM71: 0.9 | AN71: 1.1 | AQ71: 1.3 | AR71: 0.8 | AS71: 1 | AV71: 1 | AW71: 1 | AX71: 1.1 | AY71: 1.3 | AZ71: 1.1 | BA71: 1.3 | BB71: 1.4 | BC71: 1.4 | BD71: 1.5 | BE71: 1.5 | BF71: 1.6 | BG71: 1.7 | BH71: 1.6 | BI71: 1.6 | BJ71: 1.6 | BK71: 1.6 | BL71: 1.6 | BM71: 1.3 | BN71: 1.6 | BO71: 1.7 | BP71: 1.6 | BQ71: 1.5
A72: Egypt, Arab Rep. | B72: EGY | C72: Income share held by lowest 10% | D72: SI.DST.FRST.10 | AI72: 3.8 | AN72: 4.3 | AR72: 4.1 | AW72: 3.9 | BA72: 3.9 | BC72: 4.1 | BE72: 4.3 | BH72: 3.9 | BJ72: 3.8 | BL72: 3.8 | BN72: 4.2
A73: Euro area | B73: EMU | C73: Income share held by lowest 10% | D73: SI.DST.FRST.10
A74: Eritrea | B74: ERI | C74: Income share held by lowest 10% | D74: SI.DST.FRST.10
A75: Spain | B75: ESP | C75: Income share held by lowest 10% | D75: SI.DST.FRST.10 | Y75: 2.7 | AD75: 2.8 | AI75: 3 | AL75: 2.3 | AM75: 2.3 | AN75: 2.3 | AO75: 2 | AP75: 2.3 | AQ75: 2.4 | AR75: 2.7 | AS75: 2.6 | AV75: 2.6 | AW75: 2.5 | AX75: 2.5 | AY75: 2.3 | AZ75: 2.4 | BA75: 2.3 | BB75: 2.1 | BC75: 2.1 | BD75: 1.9 | BE75: 2 | BF75: 1.8 | BG75: 1.8 | BH75: 1.9 | BI75: 1.8 | BJ75: 2.1 | BK75: 2.1 | BL75: 2 | BM75: 1.9 | BN75: 2.2 | BO75: 2.3 | BP75: 2.2
A76: Estonia | B76: EST | C76: Income share held by lowest 10% | D76: SI.DST.FRST.10 | AL76: 2.7 | AN76: 3.4 | AQ76: 3 | AS76: 2.7 | AT76: 2.7 | AU76: 2.7 | AV76: 2 | AW76: 2.5 | AX76: 2.7 | AY76: 2.8 | AZ76: 3 | BA76: 2.9 | BB76: 2.8 | BC76: 2.5 | BD76: 2.6 | BE76: 2.6 | BF76: 2.4 | BG76: 2.4 | BH76: 2.7 | BI76: 2.9 | BJ76: 3 | BK76: 3.1 | BL76: 3 | BM76: 3 | BN76: 3.1 | BO76: 2.8 | BP76: 3.1
A77: Ethiopia | B77: ETH | C77: Income share held by lowest 10% | D77: SI.DST.FRST.10 | AN77: 2.6 | AR77: 3.9 | AW77: 4.1 | BC77: 3.2 | BH77: 2.9 | BN77: 3.5
A78: European Union | B78: EUU | C78: Income share held by lowest 10% | D78: SI.DST.FRST.10
A79: Fragile and conflict affected situations | B79: FCS | C79: Income share held by lowest 10% | D79: SI.DST.FRST.10
A80: Finland | B80: FIN | C80: Income share held by lowest 10% | D80: SI.DST.FRST.10 | AF80: 4.7 | AJ80: 4.7 | AN80: 4.8 | AS80: 4.1 | AV80: 3.9 | AW80: 3.9 | AX80: 4 | AY80: 3.8 | AZ80: 3.8 | BA80: 3.8 | BB80: 3.8 | BC80: 3.7 | BD80: 3.8 | BE80: 3.9 | BF80: 3.8 | BG80: 3.9 | BH80: 3.8 | BI80: 3.9 | BJ80: 3.8 | BK80: 3.8 | BL80: 3.8 | BM80: 3.9 | BN80: 3.8 | BO80: 3.8 | BP80: 3.7
A81: Fiji | B81: FJI | C81: Income share held by lowest 10% | D81: SI.DST.FRST.10 | AU81: 2.7 | BA81: 2.7 | BF81: 3.1 | BL81: 3.5
A82: France | B82: FRA | C82: Income share held by lowest 10% | D82: SI.DST.FRST.10 | O82: 2.9 | T82: 2.8 | X82: 3 | AC82: 3 | AI82: 3.3 | AO82: 3 | AP82: 3.1 | AQ82: 3.2 | AR82: 3.1 | AS82: 3.1 | AT82: 3.1 | AU82: 3.3 | AV82: 3.3 | AW82: 3.4 | AX82: 3.5 | AY82: 3.4 | AZ82: 3.3 | BA82: 3.2 | BB82: 3 | BC82: 3.1 | BD82: 3.1 | BE82: 3.1 | BF82: 3.2 | BG82: 3.2 | BH82: 3.1 | BI82: 3.2 | BJ82: 3.2 | BK82: 3.2 | BL82: 3.1 | BM82: 3.1 | BN82: 2.9 | BO82: 3 | BP82: 3
A83: Faroe Islands | B83: FRO | C83: Income share held by lowest 10% | D83: SI.DST.FRST.10
A84: Micronesia, Fed. Sts. | B84: FSM | C84: Income share held by lowest 10% | D84: SI.DST.FRST.10 | AX84: 2.3 | BF84: 1.9
A85: Gabon | B85: GAB | C85: Income share held by lowest 10% | D85: SI.DST.FRST.10 | AX85: 2.3 | BJ85: 2.2
A86: United Kingdom | B86: GBR | C86: Income share held by lowest 10% | D86: SI.DST.FRST.10 | M86: 4.3 | N86: 4.1 | O86: 4.2 | P86: 4 | Q86: 3.8 | R86: 4.1 | S86: 3.9 | T86: 4 | U86: 4.1 | V86: 4.1 | W86: 4 | X86: 4.1 | Y86: 3.9 | Z86: 3.7 | AA86: 3.7 | AB86: 3.7 | AC86: 3.7 | AD86: 3.6 | AE86: 3.4 | AF86: 3.3 | AG86: 3.2 | AH86: 3.1 | AI86: 2.9 | AJ86: 2.9 | AK86: 2.9 | AL86: 2.9 | AM86: 2.9 | AN86: 2.9 | AO86: 2.9 | AP86: 2.9 | AQ86: 2.8 | AR86: 2.8 | AS86: 2.7 | AT86: 2.8 | AU86: 2.9 | AV86: 2.9 | AW86: 3 | AX86: 2.9 | AY86: 2.9 | AZ86: 2.9 | BA86: 2.8 | BB86: 2.9 | BC86: 3.1 | BD86: 3.2 | BE86: 3.1 | BF86: 3.2 | BG86: 3.1 | BH86: 3.1 | BI86: 3 | BJ86: 3 | BK86: 2.9 | BL86: 2.9 | BM86: 3.1 | BN86: 3
A87: Georgia | B87: GEO | C87: Income share held by lowest 10% | D87: SI.DST.FRST.10 | AO87: 2.3 | AP87: 1.8 | AQ87: 1.7 | AR87: 1.9 | AS87: 1.8 | AT87: 2 | AU87: 2.3 | AV87: 2.3 | AW87: 2.3 | AX87: 2.3 | AY87: 2.3 | AZ87: 2.3 | BA87: 2.3 | BB87: 2.3 | BC87: 2.1 | BD87: 2 | BE87: 2.2 | BF87: 2.3 | BG87: 2.4 | BH87: 2.6 | BI87: 2.6 | BJ87: 2.3 | BK87: 2.4 | BL87: 2.6 | BM87: 2.7 | BN87: 2.7 | BO87: 2.6 | BP87: 2.7 | BQ87: 2.9
A88: Ghana | B88: GHA | C88: Income share held by lowest 10% | D88: SI.DST.FRST.10 | AF88: 2.8 | AG88: 2.9 | AJ88: 2.6 | AQ88: 2.2 | AX88: 1.9 | BE88: 2 | BI88: 1.6
A89: Gibraltar | B89: GIB | C89: Income share held by lowest 10% | D89: SI.DST.FRST.10
A90: Guinea | B90: GIN | C90: Income share held by lowest 10% | D90: SI.DST.FRST.10 | AJ90: 1.8 | AM90: 2.1 | AU90: 2.3 | AZ90: 2.5 | BE90: 3 | BK90: 3.5
A91: Gambia, The | B91: GMB | C91: Income share held by lowest 10% | D91: SI.DST.FRST.10 | AQ91: 1.6 | AV91: 1.8 | BC91: 2.2 | BH91: 3 | BM91: 2.6
A92: Guinea-Bissau | B92: GNB | C92: Income share held by lowest 10% | D92: SI.DST.FRST.10 | AJ92: 0.6 | AL92: 2.2 | AU92: 2.9 | BC92: 1.7 | BK92: 3.3 | BN92: 3.4
A93: Equatorial Guinea | B93: GNQ | C93: Income share held by lowest 10% | D93: SI.DST.FRST.10 | BO93: 2.6
A94: Greece | B94: GRC | C94: Income share held by lowest 10% | D94: SI.DST.FRST.10 | AN94: 2.1 | AS94: 2.7 | AU94: 2.6 | AV94: 2.8 | AW94: 2.6 | AX94: 2.6 | AY94: 2.5 | AZ94: 2.6 | BA94: 2.6 | BB94: 2.6 | BC94: 2.4 | BD94: 2 | BE94: 1.9 | BF94: 2 | BG94: 2 | BH94: 1.9 | BI94: 2.2 | BJ94: 2.4 | BK94: 2.7 | BL94: 2.5 | BM94: 2.4 | BN94: 2.6 | BO94: 2.7 | BP94: 2.7
A95: Grenada | B95: GRD | C95: Income share held by lowest 10% | D95: SI.DST.FRST.10 | BK95: 2.1
A96: Greenland | B96: GRL | C96: Income share held by lowest 10% | D96: SI.DST.FRST.10
A97: Guatemala | B97: GTM | C97: Income share held by lowest 10% | D97: SI.DST.FRST.10 | AE97: 1.1 | AH97: 0.7 | AQ97: 1.3 | AS97: 1.2 | AY97: 1.1 | BG97: 1.7 | BP97: 1.6
A98: Guam | B98: GUM | C98: Income share held by lowest 10% | D98: SI.DST.FRST.10
A99: Guyana | B99: GUY | C99: Income share held by lowest 10% | D99: SI.DST.FRST.10 | AK99: 2 | AQ99: 1.1
A100: High income | B100: HIC | C100: Income share held by lowest 10% | D100: SI.DST.FRST.10
A101: Hong Kong SAR, China | B101: HKG | C101: Income share held by lowest 10% | D101: SI.DST.FRST.10
...

Sheet lowest_20
A1: Data Source | B1: World Development Indicators
A2: Last Updated Date | B2: 46007
A4: Country Name | B4: Country Code | C4: Indicator Name | D4: Indicator Code | E4: 1960 | F4: 1961 | G4: 1962 | H4: 1963 | I4: 1964 | J4: 1965 | K4: 1966 | L4: 1967 | M4: 1968 | N4: 1969 | O4: 1970 | P4: 1971 | Q4: 1972 | R4: 1973 | S4: 1974 | T4: 1975 | U4: 1976 | V4: 1977 | W4: 1978 | X4: 1979 | Y4: 1980 | Z4: 1981 | AA4: 1982 | AB4: 1983 | AC4: 1984 | AD4: 1985 | AE4: 1986 | AF4: 1987 | AG4: 1988 | AH4: 1989 | AI4: 1990 | AJ4: 1991 | AK4: 1992 | AL4: 1993 | AM4: 1994 | AN4: 1995 | AO4: 1996 | AP4: 1997 | AQ4: 1998 | AR4: 1999 | AS4: 2000 | AT4: 2001 | AU4: 2002 | AV4: 2003 | AW4: 2004 | AX4: 2005 | AY4: 2006 | AZ4: 2007 | BA4: 2008 | BB4: 2009 | BC4: 2010 | BD4: 2011 | BE4: 2012 | BF4: 2013 | BG4: 2014 | BH4: 2015 | BI4: 2016 | BJ4: 2017 | BK4: 2018 | BL4: 2019 | BM4: 2020 | BN4: 2021 | BO4: 2022 | BP4: 2023 | BQ4: 2024
A5: Aruba | B5: ABW | C5: Income share held by lowest 20% | D5: SI.DST.FRST.20
A6: Africa Eastern and Southern | B6: AFE | C6: Income share held by lowest 20% | D6: SI.DST.FRST.20
A7: Afghanistan | B7: AFG | C7: Income share held by lowest 20% | D7: SI.DST.FRST.20
A8: Africa Western and Central | B8: AFW | C8: Income share held by lowest 20% | D8: SI.DST.FRST.20
A9: Angola | B9: AGO | C9: Income share held by lowest 20% | D9: SI.DST.FRST.20 | AS9: 3.2 | BA9: 5.4 | BK9: 3.8
A10: Albania | B10: ALB | C10: Income share held by lowest 20% | D10: SI.DST.FRST.20 | AO10: 9.2 | AU10: 8.4 | AX10: 8.4 | BA10: 8.9 | BE10: 8.9 | BG10: 7 | BH10: 7.7 | BI10: 7.3 | BJ10: 7.6 | BK10: 7.9 | BL10: 8.5 | BM10: 8.4
A11: Andorra | B11: AND | C11: Income share held by lowest 20% | D11: SI.DST.FRST.20
A12: Arab World | B12: ARB | C12: Income share held by lowest 20% | D12: SI.DST.FRST.20
A13: United Arab Emirates | B13: ARE | C13: Income share held by lowest 20% | D13: SI.DST.FRST.20 | BF13: 6.2 | BK13: 8.2
A14: Argentina | B14: ARG | C14: Income share held by lowest 20% | D14: SI.DST.FRST.20 | Y14: 5.3 | AE14: 5.1 | AF14: 4.6 | AJ14: 4.8 | AK14: 4.6 | AL14: 4.5 | AM14: 4.4 | AN14: 3.8 | AO14: 3.5 | AP14: 3.6 | AQ14: 3.4 | AR14: 3.5 | AS14: 3.2 | AT14: 2.6 | AU14: 2.8 | AV14: 3.3 | AW14: 3.6 | AX14: 3.7 | AY14: 3.9 | AZ14: 4.1 | BA14: 4.2 | BB14: 4.3 | BC14: 4.5 | BD14: 4.8 | BE14: 5 | BF14: 5 | BG14: 5 | BI14: 4.9 | BJ14: 5 | BK14: 4.9 | BL14: 4.6 | BM14: 4.7 | BN14: 5 | BO14: 5.4 | BP14: 5.1 | BQ14: 5.1
A15: Armenia | B15: ARM | C15: Income share held by lowest 20% | D15: SI.DST.FRST.20 | AO15: 5.5 | AR15: 7.6 | AT15: 7.7 | AU15: 8 | AV15: 8.7 | AW15: 7.6 | AX15: 8.1 | AY15: 8.9 | AZ15: 8.4 | BA15: 9.1 | BB15: 9.4 | BC15: 9.1 | BD15: 9 | BE15: 9 | BF15: 8.6 | BG15: 8.5 | BH15: 8.2 | BI15: 7.9 | BJ15: 8.4 | BK15: 8.1 | BL15: 8.9 | BM15: 10.2 | BN15: 9.4 | BO15: 9.2 | BP15: 9.5
A16: American Samoa | B16: ASM | C16: Income share held by lowest 20% | D16: SI.DST.FRST.20
A17: Antigua and Barbuda | B17: ATG | C17: Income share held by lowest 20% | D17: SI.DST.FRST.20
A18: Australia | B18: AUS | C18: Income share held by lowest 20% | D18: SI.DST.FRST.20 | Z18: 7.8 | AD18: 7.5 | AH18: 7.4 | AN18: 7.7 | AT18: 7.5 | AV18: 7.5 | AW18: 7.8 | BA18: 7.2 | BC18: 7.3 | BG18: 7.6 | BI18: 7.5 | BK18: 7.4 | BM18: 7.3
A19: Austria | B19: AUT | C19: Income share held by lowest 20% | D19: SI.DST.FRST.20 | AM19: 8.2 | AN19: 8.3 | AO19: 8.6 | AP19: 8.6 | AQ19: 8.3 | AR19: 8.8 | AS19: 8.8 | AV19: 8.5 | AW19: 8.5 | AX19: 8.8 | AY19: 8.6 | AZ19: 8 | BA19: 8 | BB19: 7.7 | BC19: 8 | BD19: 7.8 | BE19: 7.8 | BF19: 8.1 | BG19: 8 | BH19: 7.9 | BI19: 7.7 | BJ19: 8 | BK19: 7.9 | BL19: 7.9 | BM19: 7.9 | BN19: 7.7 | BO19: 7.8 | BP19: 7.7
A20: Azerbaijan | B20: AZE | C20: Income share held by lowest 20% | D20: SI.DST.FRST.20 | AN20: 7.1 | AT20: 7.4 | AU20: 10.9 | AV20: 10.2 | AW20: 10.7 | AX20: 10.8
A21: Burundi | B21: BDI | C21: Income share held by lowest 20% | D21: SI.DST.FRST.20 | AK21: 7.9 | AQ21: 5.3 | AY21: 8.9 | BF21: 6.9 | BM21: 7.1
A22: Belgium | B22: BEL | C22: Income share held by lowest 20% | D22: SI.DST.FRST.20 | AD22: 9.9 | AG22: 9.7 | AK22: 9.7 | AN22: 8.8 | AP22: 9.2 | AS22: 8.5 | AV22: 8.6 | AW22: 8.4 | AX22: 8.7 | AY22: 8.7 | AZ22: 8.6 | BA22: 8.7 | BB22: 8.5 | BC22: 8.6 | BD22: 8.6 | BE22: 8.7 | BF22: 8.6 | BG22: 8.6 | BH22: 8.6 | BI22: 8.6 | BJ22: 8.7 | BK22: 8.9 | BL22: 9 | BM22: 9.4 | BN22: 9.2 | BO22: 9.4 | BP22: 9.1
A23: Benin | B23: BEN | C23: Income share held by lowest 20% | D23: SI.DST.FRST.20 | AV23: 7 | BD23: 6.1 | BH23: 3.3 | BK23: 7 | BN23: 7.6
A24: Burkina Faso | B24: BFA | C24: Income share held by lowest 20% | D24: SI.DST.FRST.20 | AM24: 5.6 | AQ24: 5.2 | AV24: 5.8 | BB24: 6.7 | BG24: 8.3 | BK24: 6.3 | BN24: 7.3
A25: Bangladesh | B25: BGD | C25: Income share held by lowest 20% | D25: SI.DST.FRST.20 | AB25: 9.7 | AD25: 10 | AG25: 9.4 | AJ25: 9.6 | AN25: 8.8 | AS25: 8.6 | AX25: 8.8 | BC25: 8.9 | BI25: 8.6 | BO25: 8.8
A26: Bulgaria | B26: BGR | C26: Income share held by lowest 20% | D26: SI.DST.FRST.20 | AH26: 10.5 | AK26: 8.3 | AM26: 10.2 | AN26: 7.8 | AP26: 10.1 | AT26: 7.1 | AV26: 8.8 | AY26: 5.7 | AZ26: 6.5 | BA26: 6.9 | BB26: 6.8 | BC26: 6.3 | BD26: 6.4 | BE26: 6.2 | BF26: 5.7 | BG26: 6 | BH26: 5.3 | BI26: 5.4 | BJ26: 5.7 | BK26: 5.7 | BL26: 5.7 | BM26: 6.1 | BN26: 6.1 | BO26: 6.2 | BP26: 6
A27: Bahrain | B27: BHR | C27: Income share held by lowest 20% | D27: SI.DST.FRST.20
A28: Bahamas, The | B28: BHS | C28: Income share held by lowest 20% | D28: SI.DST.FRST.20
A29: Bosnia and Herzegovina | B29: BIH | C29: Income share held by lowest 20% | D29: SI.DST.FRST.20 | AT29: 8.8 | AW29: 7.4 | AZ29: 7.5 | BD29: 7.5
A30: Belarus | B30: BLR | C30: Income share held by lowest 20% | D30: SI.DST.FRST.20 | AL30: 11.1 | AN30: 8.5 | AQ30: 7.9 | AR30: 7.6 | AS30: 7.9 | AT30: 8.2 | AU30: 8.3 | AV30: 8.6 | AW30: 9.4 | AX30: 8.9 | AY30: 8.8 | AZ30: 8.6 | BA30: 9 | BB30: 9.1 | BC30: 8.8 | BD30: 9.2 | BE30: 9.5 | BF30: 9.5 | BG30: 9.3 | BH30: 9.7 | BI30: 9.9 | BJ30: 9.9 | BK30: 10.1 | BL30: 10 | BM30: 10.3
A31: Belize | B31: BLZ | C31: Income share held by lowest 20% | D31: SI.DST.FRST.20 | AL31: 3 | AM31: 3.1 | AN31: 2.4 | AO31: 3.4 | AP31: 2.7 | AQ31: 3.3 | AR31: 3.2 | BK31: 5.8
A32: Bermuda | B32: BMU | C32: Income share held by lowest 20% | D32: SI.DST.FRST.20
A33: Bolivia | B33: BOL | C33: Income share held by lowest 20% | D33: SI.DST.FRST.20 | AI33: 5.6 | AK33: 4.6 | AP33: 2 | AR33: 1.3 | AS33: 1.1 | AT33: 1.9 | AU33: 1.7 | AW33: 3.1 | AX33: 2 | AY33: 2.3 | AZ33: 2.9 | BA33: 3.2 | BB33: 3.2 | BD33: 3.8 | BE33: 3.4 | BF33: 3.6 | BG33: 3.8 | BH33: 3.9 | BI33: 3.7 | BJ33: 3.9 | BK33: 4.5 | BL33: 5.1 | BM33: 4.7 | BN33: 5.3 | BO33: 5.1 | BP33: 5.2
A34: Brazil | B34: BRA | C34: Income share held by lowest 20% | D34: SI.DST.FRST.20 | Z34: 2.7 | AA34: 2.6 | AB34: 2.7 | AC34: 2.8 | AD34: 2.9 | AE34: 2.7 | AF34: 2.4 | AG34: 2.2 | AH34: 2 | AI34: 2.3 | AK34: 2.9 | AL34: 2.4 | AN34: 2.5 | AO34: 2.3 | AP34: 2.3 | AQ34: 2.4 | AR34: 2.5 | AT34: 2.5 | AU34: 2.6 | AV34: 2.6 | AW34: 2.9 | AX34: 2.9 | AY34: 3 | AZ34: 3 | BA34: 3.2 | BB34: 3.2 | BD34: 3.3 | BE34: 3.4 | BF34: 3.5 | BG34: 3.6 | BH34: 3.6 | BI34: 3.3 | BJ34: 3.2 | BK34: 3.1 | BL34: 3.1 | BM34: 4.5 | BN34: 3.3 | BO34: 3.6 | BP34: 3.7
A35: Barbados | B35: BRB | C35: Income share held by lowest 20% | D35: SI.DST.FRST.20 | BI35: 6.9
A36: Brunei Darussalam | B36: BRN | C36: Income share held by lowest 20% | D36: SI.DST.FRST.20
A37: Bhutan | B37: BTN | C37: Income share held by lowest 20% | D37: SI.DST.FRST.20 | AV37: 6.5 | AZ37: 6.7 | BE37: 6.7 | BJ37: 6.7 | BO37: 8.8
A38: Botswana | B38: BWA | C38: Income share held by lowest 20% | D38: SI.DST.FRST.20 | AD38: 3.6 | AL38: 3.1 | AU38: 2.7 | BB38: 3.3 | BH38: 3.7
A39: Central African Republic | B39: CAF | C39: Income share held by lowest 20% | D39: SI.DST.FRST.20 | AK39: 3.1 | BA39: 3.4 | BN39: 5.6
A40: Canada | B40: CAN | C40: Income share held by lowest 20% | D40: SI.DST.FRST.20 | P40: 5.7 | R40: 6.4 | T40: 6.7 | V40: 6.7 | X40: 6.8 | Z40: 7.1 | AA40: 7.1 | AC40: 6.9 | AD40: 7.1 | AE40: 7.4 | AF40: 7.5 | AG40: 7.7 | AH40: 7.6 | AI40: 7.4 | AJ40: 7.3 | AK40: 7.5 | AL40: 7.4 | AM40: 7.5 | AN40: 7.5 | AO40: 7.4 | AP40: 7.4 | AQ40: 7.3 | AR40: 7.3 | AS40: 7.2 | AT40: 7.2 | AU40: 7.2 | AV40: 7.1 | AW40: 7.1 | AX40: 7.2 | AY40: 7.2 | AZ40: 7.3 | BA40: 7.2 | BB40: 7.2 | BC40: 7.3 | BD40: 7.5 | BE40: 7 | BF40: 6.8 | BG40: 7.2 | BH40: 7 | BI40: 7.4 | BJ40: 7.3 | BK40: 7.5 | BL40: 7.7 | BM40: 8.6 | BN40: 8.2
A41: Central Europe and the Baltics | B41: CEB | C41: Income share held by lowest 20% | D41: SI.DST.FRST.20
A42: Switzerland | B42: CHE | C42: Income share held by lowest 20% | D42: SI.DST.FRST.20 | AA42: 7.5 | AK42: 7.6 | AS42: 7.9 | AU42: 8.2 | AW42: 8.2 | AY42: 7.4 | AZ42: 7.4 | BA42: 7.5 | BB42: 7.8 | BC42: 7.8 | BD42: 7.9 | BE42: 8.1 | BF42: 7.9 | BG42: 7.8 | BH42: 7.8 | BI42: 7.7 | BJ42: 7.7 | BK42: 7.5 | BL42: 7.4 | BM42: 7.5 | BN42: 7.5 | BO42: 7.4
A43: Channel Islands | B43: CHI | C43: Income share held by lowest 20% | D43: SI.DST.FRST.20
A44: Chile | B44: CHL | C44: Income share held by lowest 20% | D44: SI.DST.FRST.20 | AF44: 3.4 | AI44: 3.4 | AK44: 3.9 | AM44: 3.5 | AO44: 3.7 | AQ44: 3.5 | AS44: 3.8 | AV44: 4 | AY44: 4.9 | BB44: 5.1 | BD44: 5.2 | BF44: 5.4 | BH44: 5.6 | BJ44: 5.6 | BM44: 4.9 | BO44: 5.9
A45: China | B45: CHN | C45: Income share held by lowest 20% | D45: SI.DST.FRST.20 | Z45: 8.8 | AC45: 9 | AF45: 8.2 | AI45: 8.3 | AL45: 7.9 | AO45: 7.4 | AR45: 6.5 | AU45: 5.7 | AX45: 5.9 | BA45: 5.2 | BC45: 5.1 | BD45: 5.4 | BE45: 5.3 | BF45: 6.2 | BG45: 6.2 | BH45: 6.4 | BI45: 6.5 | BJ45: 6.4 | BK45: 6.5 | BL45: 6.7 | BM45: 7.2 | BN45: 7.4 | BO45: 7.3
A46: Cote d'Ivoire | B46: CIV | C46: Income share held by lowest 20% | D46: SI.DST.FRST.20 | AD46: 5 | AE46: 6.9 | AF46: 6.3 | AG46: 6.8 | AK46: 6 | AN46: 6.6 | AQ46: 6.4 | AU46: 6.1 | BA46: 5.1 | BH46: 5.7 | BK46: 7 | BN46: 7.6
A47: Cameroon | B47: CMR | C47: Income share held by lowest 20% | D47: SI.DST.FRST.20 | AO47: 6.1 | AT47: 6.2 | AZ47: 5.8 | BG47: 4.5 | BN47: 5.4
A48: Congo, Dem. Rep. | B48: COD | C48: Income share held by lowest 20% | D48: SI.DST.FRST.20 | AW48: 6.1 | BE48: 5.6 | BM48: 5.5
A49: Congo, Rep. | B49: COG | C49: Income share held by lowest 20% | D49: SI.DST.FRST.20 | AX49: 4.9 | BD49: 4.2
A50: Colombia | B50: COL | C50: Income share held by lowest 20% | D50: SI.DST.FRST.20 | Y50: 2.9 | AG50: 3.3 | AH50: 3.6 | AJ50: 3.6 | AK50: 3.7 | AO50: 2.5 | AR50: 2.2 | AS50: 2.1 | AT50: 2.5 | AU50: 3.2 | AV50: 3.5 | AW50: 3.5 | AX50: 3.6 | BA50: 3 | BB50: 3.3 | BC50: 3.3 | BD50: 3.5 | BE50: 3.5 | BF50: 3.5 | BG50: 3.6 | BH50: 3.8 | BI50: 3.9 | BJ50: 4.1 | BK50: 4 | BL50: 3.7 | BM50: 3.1 | BN50: 3.1 | BO50: 3.2 | BP50: 3.4
A51: Comoros | B51: COM | C51: Income share held by lowest 20% | D51: SI.DST.FRST.20 | AW51: 4 | BG51: 4.5
A52: Cabo Verde | B52: CPV | C52: Income share held by lowest 20% | D52: SI.DST.FRST.20 | AT52: 4.2 | AZ52: 5 | BH52: 5.7
A53: Costa Rica | B53: CRI | C53: Income share held by lowest 20% | D53: SI.DST.FRST.20 | Z53: 3.3 | AE53: 5.2 | AH53: 3.8 | AI53: 3.8 | AJ53: 3.7 | AK53: 4 | AL53: 3.9 | AM53: 4 | AN53: 4 | AO53: 3.8 | AP53: 4.2 | AQ53: 4.3 | AR53: 4 | AS53: 3.9 | AT53: 3.5 | AU53: 3.5 | AV53: 3.7 | AW53: 4 | AX53: 4.2 | AY53: 4.1 | AZ53: 4.3 | BA53: 4.3 | BB53: 4 | BC53: 4.4 | BD53: 4.2 | BE53: 4.2 | BF53: 4.1 | BG53: 4.2 | BH53: 4.3 | BI53: 4.2 | BJ53: 4.4 | BK53: 4.3 | BL53: 4.4 | BM53: 4 | BN53: 4.3 | BO53: 4.5 | BP53: 4.5 | BQ53: 4.6
A54: Caribbean small states | B54: CSS | C54: Income share held by lowest 20% | D54: SI.DST.FRST.20
A55: Cuba | B55: CUB | C55: Income share held by lowest 20% | D55: SI.DST.FRST.20
A56: Curacao | B56: CUW | C56: Income share held by lowest 20% | D56: SI.DST.FRST.20
A57: Cayman Islands | B57: CYM | C57: Income share held by lowest 20% | D57: SI.DST.FRST.20
A58: Cyprus | B58: CYP | C58: Income share held by lowest 20% | D58: SI.DST.FRST.20 | AW58: 8.8 | AX58: 8.9 | AY58: 8.8 | AZ58: 8.7 | BA58: 8.7 | BB58: 8.5 | BC58: 8.6 | BD58: 8.4 | BE58: 8 | BF58: 7.7 | BG58: 7.6 | BH58: 7.9 | BI58: 8.2 | BJ58: 8.4 | BK58: 8.4 | BL58: 8.5 | BM58: 8.5 | BN58: 8.6 | BO58: 8.7 | BP58: 8.6
A59: Czechia | B59: CZE | C59: Income share held by lowest 20% | D59: SI.DST.FRST.20 | AK59: 11.9 | AL59: 10.5 | AO59: 10 | AU59: 9.6 | AW59: 9 | AX59: 9.3 | AY59: 9.3 | AZ59: 9.7 | BA59: 9.8 | BB59: 9.6 | BC59: 9.4 | BD59: 9.3 | BE59: 9.6 | BF59: 9.4 | BG59: 9.7 | BH59: 9.7 | BI59: 10 | BJ59: 10.2 | BK59: 10.2 | BL59: 10.1 | BM59: 9.8 | BN59: 9.7 | BO59: 9.8 | BP59: 9.5
A60: Germany | B60: DEU | C60: Income share held by lowest 20% | D60: SI.DST.FRST.20 | AJ60: 8.9 | AK60: 9 | AL60: 9.1 | AM60: 8.7 | AN60: 8.7 | AO60: 9.1 | AP60: 9 | AQ60: 9.1 | AR60: 8.9 | AS60: 8.9 | AT60: 8.8 | AU60: 8.7 | AV60: 8.7 | AW60: 8.7 | AX60: 8.3 | AY60: 8.5 | AZ60: 8.5 | BA60: 8.6 | BB60: 8.5 | BC60: 8.6 | BD60: 8.6 | BE60: 8.3 | BF60: 8.3 | BG60: 8.2 | BH60: 8.1 | BI60: 8 | BJ60: 8 | BK60: 8 | BL60: 7.9 | BM60: 7.8
A61: Djibouti | B61: DJI | C61: Income share held by lowest 20% | D61: SI.DST.FRST.20 | AU61: 6 | BE61: 4.3 | BF61: 5 | BJ61: 5.4
A62: Dominica | B62: DMA | C62: Income share held by lowest 20% | D62: SI.DST.FRST.20
A63: Denmark | B63: DNK | C63: Income share held by lowest 20% | D63: SI.DST.FRST.20 | AF63: 9.5 | AK63: 9.9 | AN63: 10.9 | AS63: 10.6 | AV63: 9.8 | AW63: 9.9 | AX63: 9.8 | AY63: 9.8 | AZ63: 9.8 | BA63: 9.8 | BB63: 9.2 | BC63: 9.3 | BD63: 9.4 | BE63: 9.3 | BF63: 9.1 | BG63: 9.1 | BH63: 9.4 | BI63: 9.2 | BJ63: 9.1 | BK63: 9.3 | BL63: 9.5 | BM63: 9.4 | BN63: 9.2 | BO63: 9 | BP63: 9.1
A64: Dominican Republic | B64: DOM | C64: Income share held by lowest 20% | D64: SI.DST.FRST.20 | AE64: 3.9 | AH64: 4.2 | AK64: 4.3 | AO64: 4.3 | AP64: 4 | AS64: 3.7 | AT64: 4.1 | AU64: 3.8 | AV64: 3.8 | AW64: 3.9 | AX64: 4.1 | AY64: 3.9 | AZ64: 4.4 | BA64: 4.6 | BB64: 4.5 | BC64: 4.6 | BD64: 4.7 | BE64: 4.9 | BF64: 4.8 | BG64: 5.1 | BH64: 5 | BI64: 4.9 | BJ64: 5.9 | BK64: 5.8 | BL64: 6 | BM64: 6.2 | BN64: 6.6 | BO64: 6.6 | BP64: 6.2 | BQ64: 6.1
A65: Algeria | B65: DZA | C65: Income share held by lowest 20% | D65: SI.DST.FRST.20 | AG65: 6.8 | AN65: 7 | BD65: 9.4
A66: East Asia & Pacific (excluding high income) | B66: EAP | C66: Income share held by lowest 20% | D66: SI.DST.FRST.20
A67: Early-demographic dividend | B67: EAR | C67: Income share held by lowest 20% | D67: SI.DST.FRST.20
A68: East Asia & Pacific | B68: EAS | C68: Income share held by lowest 20% | D68: SI.DST.FRST.20
A69: Europe & Central Asia (excluding high income) | B69: ECA | C69: Income share held by lowest 20% | D69: SI.DST.FRST.20
A70: Europe & Central Asia | B70: ECS | C70: Income share held by lowest 20% | D70: SI.DST.FRST.20
A71: Ecuador | B71: ECU | C71: Income share held by lowest 20% | D71: SI.DST.FRST.20 | AF71: 3.3 | AM71: 3.3 | AN71: 3.8 | AQ71: 4 | AR71: 2.6 | AS71: 3.1 | AV71: 3.3 | AW71: 3.2 | AX71: 3.3 | AY71: 3.7 | AZ71: 3.5 | BA71: 3.8 | BB71: 4.1 | BC71: 4.1 | BD71: 4.4 | BE71: 4.3 | BF71: 4.5 | BG71: 4.8 | BH71: 4.6 | BI71: 4.7 | BJ71: 4.7 | BK71: 4.6 | BL71: 4.5 | BM71: 4.1 | BN71: 4.6 | BO71: 4.7 | BP71: 4.7 | BQ71: 4.3
A72: Egypt, Arab Rep. | B72: EGY | C72: Income share held by lowest 20% | D72: SI.DST.FRST.20 | AI72: 8.7 | AN72: 9.5 | AR72: 9.2 | AW72: 9 | BA72: 9.2 | BC72: 9.4 | BE72: 9.8 | BH72: 9.1 | BJ72: 9 | BL72: 9 | BN72: 9.7
A73: Euro area | B73: EMU | C73: Income share held by lowest 20% | D73: SI.DST.FRST.20
A74: Eritrea | B74: ERI | C74: Income share held by lowest 20% | D74: SI.DST.FRST.20
A75: Spain | B75: ESP | C75: Income share held by lowest 20% | D75: SI.DST.FRST.20 | Y75: 7 | AD75: 7.3 | AI75: 7.8 | AL75: 6.5 | AM75: 6.6 | AN75: 6.5 | AO75: 6.1 | AP75: 6.6 | AQ75: 6.7 | AR75: 7.2 | AS75: 7 | AV75: 7.2 | AW75: 6.9 | AX75: 7 | AY75: 6.7 | AZ75: 6.7 | BA75: 6.6 | BB75: 6.3 | BC75: 6.3 | BD75: 6 | BE75: 6.1 | BF75: 5.7 | BG75: 5.7 | BH75: 5.8 | BI75: 5.8 | BJ75: 6.2 | BK75: 6.2 | BL75: 6.2 | BM75: 6 | BN75: 6.4 | BO75: 6.6 | BP75: 6.5
A76: Estonia | B76: EST | C76: Income share held by lowest 20% | D76: SI.DST.FRST.20 | AL76: 6.5 | AN76: 8.1 | AQ76: 7 | AS76: 6.9 | AT76: 7 | AU76: 6.9 | AV76: 6.2 | AW76: 7.1 | AX76: 7.4 | AY76: 7.6 | AZ76: 8 | BA76: 7.8 | BB76: 7.7 | BC76: 7.2 | BD76: 7.3 | BE76: 7.3 | BF76: 6.8 | BG76: 7 | BH76: 7.5 | BI76: 7.8 | BJ76: 8.1 | BK76: 8.1 | BL76: 8.1 | BM76: 8.1 | BN76: 8.1 | BO76: 7.7 | BP76: 8.3
A77: Ethiopia | B77: ETH | C77: Income share held by lowest 20% | D77: SI.DST.FRST.20 | AN77: 6.3 | AR77: 9.1 | AW77: 9.4 | BC77: 8 | BH77: 7.3 | BN77: 8.3
A78: European Union | B78: EUU | C78: Income share held by lowest 20% | D78: SI.DST.FRST.20
A79: Fragile and conflict affected situations | B79: FCS | C79: Income share held by lowest 20% | D79: SI.DST.FRST.20
A80: Finland | B80: FIN | C80: Income share held by lowest 20% | D80: SI.DST.FRST.20 | AF80: 11 | AJ80: 10.9 | AN80: 11 | AS80: 9.7 | AV80: 9.4 | AW80: 9.4 | AX80: 9.5 | AY80: 9.3 | AZ80: 9.2 | BA80: 9.3 | BB80: 9.3 | BC80: 9.2 | BD80: 9.3 | BE80: 9.4 | BF80: 9.3 | BG80: 9.4 | BH80: 9.4 | BI80: 9.4 | BJ80: 9.4 | BK80: 9.3 | BL80: 9.2 | BM80: 9.5 | BN80: 9.3 | BO80: 9.3 | BP80: 9.2
A81: Fiji | B81: FJI | C81: Income share held by lowest 20% | D81: SI.DST.FRST.20 | AU81: 6.7 | BA81: 6.6 | BF81: 7.5 | BL81: 8.4
A82: France | B82: FRA | C82: Income share held by lowest 20% | D82: SI.DST.FRST.20 | O82: 7.1 | T82: 7.2 | X82: 7.5 | AC82: 7.6 | AI82: 8 | AO82: 7.7 | AP82: 7.7 | AQ82: 7.9 | AR82: 7.8 | AS82: 7.8 | AT82: 7.8 | AU82: 8.1 | AV82: 8.2 | AW82: 8.4 | AX82: 8.6 | AY82: 8.5 | AZ82: 8.1 | BA82: 7.9 | BB82: 7.7 | BC82: 7.7 | BD82: 7.8 | BE82: 7.9 | BF82: 8 | BG82: 8 | BH82: 7.9 | BI82: 8 | BJ82: 8.1 | BK82: 8 | BL82: 7.8 | BM82: 8 | BN82: 7.7 | BO82: 7.8 | BP82: 7.7
A83: Faroe Islands | B83: FRO | C83: Income share held by lowest 20% | D83: SI.DST.FRST.20
A84: Micronesia, Fed. Sts. | B84: FSM | C84: Income share held by lowest 20% | D84: SI.DST.FRST.20 | AX84: 5.6 | BF84: 5.5
A85: Gabon | B85: GAB | C85: Income share held by lowest 20% | D85: SI.DST.FRST.20 | AX85: 5.8 | BJ85: 6
A86: United Kingdom | B86: GBR | C86: Income share held by lowest 20% | D86: SI.DST.FRST.20 | M86: 10 | N86: 9.6 | O86: 9.7 | P86: 9.2 | Q86: 9.1 | R86: 9.4 | S86: 9.2 | T86: 9.4 | U86: 9.5 | V86: 9.7 | W86: 9.5 | X86: 9.6 | Y86: 9.2 | Z86: 8.8 | AA86: 8.8 | AB86: 8.8 | AC86: 8.8 | AD86: 8.6 | AE86: 8.2 | AF86: 7.9 | AG86: 7.8 | AH86: 7.7 | AI86: 7.2 | AJ86: 7.3 | AK86: 7.2 | AL86: 7.1 | AM86: 7.1 | AN86: 7.2 | AO86: 7.2 | AP86: 7.1 | AQ86: 7 | AR86: 6.9 | AS86: 6.8 | AT86: 7 | AU86: 7.3 | AV86: 7.4 | AW86: 7.4 | AX86: 7.2 | AY86: 7.2 | AZ86: 7.3 | BA86: 7.2 | BB86: 7.3 | BC86: 7.6 | BD86: 7.7 | BE86: 7.7 | BF86: 7.9 | BG86: 7.7 | BH86: 7.6 | BI86: 7.6 | BJ86: 7.6 | BK86: 7.4 | BL86: 7.5 | BM86: 7.7 | BN86: 7.7
A87: Georgia | B87: GEO | C87: Income share held by lowest 20% | D87: SI.DST.FRST.20 | AO87: 6.1 | AP87: 5.1 | AQ87: 5.2 | AR87: 5.4 | AS87: 5.4 | AT87: 5.8 | AU87: 6.3 | AV87: 6.3 | AW87: 6.3 | AX87: 6.2 | AY87: 6.3 | AZ87: 6.2 | BA87: 6.1 | BB87: 6.1 | BC87: 5.7 | BD87: 5.6 | BE87: 5.9 | BF87: 6.1 | BG87: 6.4 | BH87: 6.7 | BI87: 6.7 | BJ87: 6.3 | BK87: 6.5 | BL87: 6.8 | BM87: 7 | BN87: 7 | BO87: 7 | BP87: 7 | BQ87: 7.3
A88: Ghana | B88: GHA | C88: Income share held by lowest 20% | D88: SI.DST.FRST.20 | AF88: 7 | AG88: 7 | AJ88: 6.6 | AQ88: 5.8 | AX88: 5.3 | BE88: 5.4 | BI88: 4.7
A89: Gibraltar | B89: GIB | C89: Income share held by lowest 20% | D89: SI.DST.FRST.20
A90: Guinea | B90: GIN | C90: Income share held by lowest 20% | D90: SI.DST.FRST.20 | AJ90: 3.9 | AM90: 5.2 | AU90: 5.8 | AZ90: 6.3 | BE90: 7.6 | BK90: 8.5
A91: Gambia, The | B91: GMB | C91: Income share held by lowest 20% | D91: SI.DST.FRST.20 | AQ91: 4.4 | AV91: 4.8 | BC91: 5.7 | BH91: 7.4 | BM91: 6.6
A92: Guinea-Bissau | B92: GNB | C92: Income share held by lowest 20% | D92: SI.DST.FRST.20 | AJ92: 2.2 | AL92: 5.6 | AU92: 7.3 | BC92: 4.5 | BK92: 7.8 | BN92: 7.9
A93: Equatorial Guinea | B93: GNQ | C93: Income share held by lowest 20% | D93: SI.DST.FRST.20 | BO93: 6.4
A94: Greece | B94: GRC | C94: Income share held by lowest 20% | D94: SI.DST.FRST.20 | AN94: 6 | AS94: 6.9 | AU94: 6.8 | AV94: 7.2 | AW94: 7.1 | AX94: 6.9 | AY94: 6.7 | AZ94: 7 | BA94: 7.1 | BB94: 7 | BC94: 6.7 | BD94: 6.1 | BE94: 5.8 | BF94: 5.9 | BG94: 5.9 | BH94: 5.8 | BI94: 6.3 | BJ94: 6.6 | BK94: 7.2 | BL94: 7 | BM94: 6.7 | BN94: 7.1 | BO94: 7.2 | BP94: 7.2
A95: Grenada | B95: GRD | C95: Income share held by lowest 20% | D95: SI.DST.FRST.20 | BK95: 5.5
A96: Greenland | B96: GRL | C96: Income share held by lowest 20% | D96: SI.DST.FRST.20
A97: Guatemala | B97: GTM | C97: Income share held by lowest 20% | D97: SI.DST.FRST.20 | AE97: 3 | AH97: 2.2 | AQ97: 3.7 | AS97: 3.5 | AY97: 3.1 | BG97: 4.5 | BP97: 4.6
A98: Guam | B98: GUM | C98: Income share held by lowest 20% | D98: SI.DST.FRST.20
A99: Guyana | B99: GUY | C99: Income share held by lowest 20% | D99: SI.DST.FRST.20 | AK99: 5.3 | AQ99: 4.3
A100: High income | B100: HIC | C100: Income share held by lowest 20% | D100: SI.DST.FRST.20
A101: Hong Kong SAR, China | B101: HKG | C101: Income share held by lowest 20% | D101: SI.DST.FRST.20
...

Sheet second_20
A1: Data Source | B1: World Development Indicators
A2: Last Updated Date | B2: 46007
A4: Country Name | B4: Country Code | C4: Indicator Name | D4: Indicator Code | E4: 1960 | F4: 1961 | G4: 1962 | H4: 1963 | I4: 1964 | J4: 1965 | K4: 1966 | L4: 1967 | M4: 1968 | N4: 1969 | O4: 1970 | P4: 1971 | Q4: 1972 | R4: 1973 | S4: 1974 | T4: 1975 | U4: 1976 | V4: 1977 | W4: 1978 | X4: 1979 | Y4: 1980 | Z4: 1981 | AA4: 1982 | AB4: 1983 | AC4: 1984 | AD4: 1985 | AE4: 1986 | AF4: 1987 | AG4: 1988 | AH4: 1989 | AI4: 1990 | AJ4: 1991 | AK4: 1992 | AL4: 1993 | AM4: 1994 | AN4: 1995 | AO4: 1996 | AP4: 1997 | AQ4: 1998 | AR4: 1999 | AS4: 2000 | AT4: 2001 | AU4: 2002 | AV4: 2003 | AW4: 2004 | AX4: 2005 | AY4: 2006 | AZ4: 2007 | BA4: 2008 | BB4: 2009 | BC4: 2010 | BD4: 2011 | BE4: 2012 | BF4: 2013 | BG4: 2014 | BH4: 2015 | BI4: 2016 | BJ4: 2017 | BK4: 2018 | BL4: 2019 | BM4: 2020 | BN4: 2021 | BO4: 2022 | BP4: 2023 | BQ4: 2024
A5: Aruba | B5: ABW | C5: Income share held by second 20% | D5: SI.DST.02ND.20
A6: Africa Eastern and Southern | B6: AFE | C6: Income share held by second 20% | D6: SI.DST.02ND.20
A7: Afghanistan | B7: AFG | C7: Income share held by second 20% | D7: SI.DST.02ND.20
A8: Africa Western and Central | B8: AFW | C8: Income share held by second 20% | D8: SI.DST.02ND.20
A9: Angola | B9: AGO | C9: Income share held by second 20% | D9: SI.DST.02ND.20 | AS9: 7.9 | BA9: 9.6 | BK9: 7.7
A10: Albania | B10: ALB | C10: Income share held by second 20% | D10: SI.DST.02ND.20 | AO10: 13.9 | AU10: 12.6 | AX10: 12.9 | BA10: 13.1 | BE10: 13.2 | BG10: 11.5 | BH10: 12.1 | BI10: 11.9 | BJ10: 12 | BK10: 13 | BL10: 13 | BM10: 13.2
A11: Andorra | B11: AND | C11: Income share held by second 20% | D11: SI.DST.02ND.20
A12: Arab World | B12: ARB | C12: Income share held by second 20% | D12: SI.DST.02ND.20
A13: United Arab Emirates | B13: ARE | C13: Income share held by second 20% | D13: SI.DST.02ND.20 | BF13: 12 | BK13: 14.8
A14: Argentina | B14: ARG | C14: Income share held by second 20% | D14: SI.DST.02ND.20 | Y14: 10.2 | AE14: 9.9 | AF14: 9.3 | AJ14: 9.1 | AK14: 9.2 | AL14: 9.3 | AM14: 9 | AN14: 8.4 | AO14: 8.2 | AP14: 8.2 | AQ14: 7.8 | AR14: 8 | AS14: 7.6 | AT14: 7.1 | AU14: 6.9 | AV14: 7.6 | AW14: 8.1 | AX14: 8.3 | AY14: 8.7 | AZ14: 8.6 | BA14: 9.1 | BB14: 9.4 | BC14: 9.4 | BD14: 9.6 | BE14: 9.9 | BF14: 10 | BG14: 9.7 | BI14: 9.7 | BJ14: 10 | BK14: 9.9 | BL14: 9.5 | BM14: 9.4 | BN14: 9.8 | BO14: 10.1 | BP14: 9.6 | BQ14: 9.7
A15: Armenia | B15: ARM | C15: Income share held by second 20% | D15: SI.DST.02ND.20 | AO15: 9.4 | AR15: 11.6 | AT15: 11.9 | AU15: 12 | AV15: 12.4 | AW15: 11.5 | AX15: 11.8 | AY15: 13.1 | AZ15: 12.8 | BA15: 13.1 | BB15: 13.5 | BC15: 13 | BD15: 13.2 | BE15: 13.2 | BF15: 12.9 | BG15: 12.7 | BH15: 12.6 | BI15: 12.1 | BJ15: 12.4 | BK15: 12.2 | BL15: 13.2 | BM15: 14.3 | BN15: 13.8 | BO15: 13.6 | BP15: 14
A16: American Samoa | B16: ASM | C16: Income share held by second 20% | D16: SI.DST.02ND.20
A17: Antigua and Barbuda | B17: ATG | C17: Income share held by second 20% | D17: SI.DST.02ND.20
A18: Australia | B18: AUS | C18: Income share held by second 20% | D18: SI.DST.02ND.20 | Z18: 12.9 | AD18: 12.6 | AH18: 12.4 | AN18: 12.5 | AT18: 12.2 | AV18: 12.2 | AW18: 12.3 | BA18: 11.6 | BC18: 11.8 | BG18: 12.2 | BI18: 12.2 | BK18: 12.2 | BM18: 12.4
A19: Austria | B19: AUT | C19: Income share held by second 20% | D19: SI.DST.02ND.20 | AM19: 13.2 | AN19: 13.4 | AO19: 13.5 | AP19: 13.5 | AQ19: 13 | AR19: 13.1 | AS19: 13.4 | AV19: 13.4 | AW19: 13.2 | AX19: 13.4 | AY19: 13.3 | AZ19: 13.2 | BA19: 13.3 | BB19: 13 | BC19: 13.2 | BD19: 13.1 | BE19: 13.3 | BF19: 13.1 | BG19: 13.2 | BH19: 13.2 | BI19: 13.2 | BJ19: 13.3 | BK19: 13 | BL19: 13.3 | BM19: 13.5 | BN19: 13.3 | BO19: 13.4 | BP19: 13.2
A20: Azerbaijan | B20: AZE | C20: Income share held by second 20% | D20: SI.DST.02ND.20 | AN20: 12 | AT20: 11.5 | AU20: 14.3 | AV20: 13.9 | AW20: 14 | AX20: 13.9
A21: Burundi | B21: BDI | C21: Income share held by second 20% | D21: SI.DST.02ND.20 | AK21: 12.1 | AQ21: 10.3 | AY21: 11.9 | BF21: 11 | BM21: 11.2
A22: Belgium | B22: BEL | C22: Income share held by second 20% | D22: SI.DST.02ND.20 | AD22: 14.4 | AG22: 14.4 | AK22: 14.6 | AN22: 13.9 | AP22: 14.3 | AS22: 12.9 | AV22: 13.9 | AW22: 13.4 | AX22: 13.7 | AY22: 13.9 | AZ22: 13.6 | BA22: 13.9 | BB22: 13.9 | BC22: 13.9 | BD22: 14 | BE22: 14.2 | BF22: 14.1 | BG22: 13.9 | BH22: 14 | BI22: 14.1 | BJ22: 14.2 | BK22: 14.3 | BL22: 14.2 | BM22: 14.5 | BN22: 14.4 | BO22: 14.5 | BP22: 14.4
A23: Benin | B23: BEN | C23: Income share held by second 20% | D23: SI.DST.02ND.20 | AV23: 10.9 | BD23: 9.6 | BH23: 9.6 | BK23: 11 | BN23: 11.9
A24: Burkina Faso | B24: BFA | C24: Income share held by second 20% | D24: SI.DST.02ND.20 | AM24: 8.7 | AQ24: 8.7 | AV24: 9.7 | BB24: 10.7 | BG24: 11.7 | BK24: 9.8 | BN24: 11.2
A25: Bangladesh | B25: BGD | C25: Income share held by second 20% | D25: SI.DST.02ND.20 | AB25: 14.3 | AD25: 13.8 | AG25: 13.4 | AJ25: 13.6 | AN25: 12.5 | AS25: 12.1 | AX25: 12.2 | BC25: 12.5 | BI25: 12.4 | BO25: 12.8
A26: Bulgaria | B26: BGR | C26: Income share held by second 20% | D26: SI.DST.02ND.20 | AH26: 14.7 | AK26: 13 | AM26: 14.7 | AN26: 12.8 | AP26: 13.9 | AT26: 12.8 | AV26: 13.7 | AY26: 12.6 | AZ26: 11.9 | BA26: 12.6 | BB26: 12.5 | BC26: 12.1 | BD26: 12.7 | BE26: 12.2 | BF26: 12.2 | BG26: 11.8 | BH26: 11.6 | BI26: 11 | BJ26: 11 | BK26: 10.8 | BL26: 11 | BM26: 10.9 | BN26: 11 | BO26: 11.7 | BP26: 11.3
A27: Bahrain | B27: BHR | C27: Income share held by second 20% | D27: SI.DST.02ND.20
A28: Bahamas, The | B28: BHS | C28: Income share held by second 20% | D28: SI.DST.02ND.20
A29: Bosnia and Herzegovina | B29: BIH | C29: Income share held by second 20% | D29: SI.DST.02ND.20 | AT29: 13.3 | AW29: 12.1 | AZ29: 12.2 | BD29: 12.3
A30: Belarus | B30: BLR | C30: Income share held by second 20% | D30: SI.DST.02ND.20 | AL30: 15.3 | AN30: 13.5 | AQ30: 12.6 | AR30: 12.6 | AS30: 12.9 | AT30: 13.1 | AU30: 13.1 | AV30: 13.5 | AW30: 14 | AX30: 13.8 | AY30: 13.5 | AZ30: 13.2 | BA30: 13.6 | BB30: 13.8 | BC30: 13.4 | BD30: 13.9 | BE30: 14 | BF30: 14 | BG30: 14 | BH30: 14.3 | BI30: 14.4 | BJ30: 14.3 | BK30: 14.4 | BL30: 14.3 | BM30: 14.5
A31: Belize | B31: BLZ | C31: Income share held by second 20% | D31: SI.DST.02ND.20 | AL31: 6.5 | AM31: 6.5 | AN31: 5.9 | AO31: 7.1 | AP31: 6.4 | AQ31: 7 | AR31: 7.7 | BK31: 10.5
A32: Bermuda | B32: BMU | C32: Income share held by second 20% | D32: SI.DST.02ND.20
A33: Bolivia | B33: BOL | C33: Income share held by second 20% | D33: SI.DST.02ND.20 | AI33: 9.7 | AK33: 8.5 | AP33: 6.4 | AR33: 5.7 | AS33: 5.3 | AT33: 6.5 | AU33: 6.1 | AW33: 7.2 | AX33: 6.1 | AY33: 6.5 | AZ33: 6.8 | BA33: 8 | BB33: 8.5 | BD33: 9.2 | BE33: 9 | BF33: 8.8 | BG33: 8.8 | BH33: 9 | BI33: 9.3 | BJ33: 9.4 | BK33: 10 | BL33: 10.3 | BM33: 9.8 | BN33: 10.4 | BO33: 10.3 | BP33: 10
A34: Brazil | B34: BRA | C34: Income share held by second 20% | D34: SI.DST.02ND.20 | Z34: 6.2 | AA34: 6 | AB34: 5.9 | AC34: 6 | AD34: 6.5 | AE34: 6 | AF34: 5.7 | AG34: 5.3 | AH34: 5 | AI34: 5.5 | AK34: 7.1 | AL34: 5.8 | AN34: 5.8 | AO34: 5.7 | AP34: 5.7 | AQ34: 5.8 | AR34: 5.9 | AT34: 6 | AU34: 6.1 | AV34: 6.2 | AW34: 6.5 | AX34: 6.5 | AY34: 6.7 | AZ34: 6.9 | BA34: 7.1 | BB34: 7.2 | BD34: 7.5 | BE34: 7.4 | BF34: 7.5 | BG34: 7.7 | BH34: 7.7 | BI34: 7.4 | BJ34: 7.4 | BK34: 7.3 | BL34: 7.3 | BM34: 8.7 | BN34: 7.5 | BO34: 7.7 | BP34: 7.8
A35: Barbados | B35: BRB | C35: Income share held by second 20% | D35: SI.DST.02ND.20 | BI35: 12.2
A36: Brunei Darussalam | B36: BRN | C36: Income share held by second 20% | D36: SI.DST.02ND.20
A37: Bhutan | B37: BTN | C37: Income share held by second 20% | D37: SI.DST.02ND.20 | AV37: 10 | AZ37: 10.8 | BE37: 10.8 | BJ37: 10.8 | BO37: 13.5
A38: Botswana | B38: BWA | C38: Income share held by second 20% | D38: SI.DST.02ND.20 | AD38: 6.9 | AL38: 6 | AU38: 5.3 | BB38: 6.6 | BH38: 6.7
A39: Central African Republic | B39: CAF | C39: Income share held by second 20% | D39: SI.DST.02ND.20 | AK39: 4.9 | BA39: 7 | BN39: 9.7
A40: Canada | B40: CAN | C40: Income share held by second 20% | D40: SI.DST.02ND.20 | P40: 11.7 | R40: 12.3 | T40: 12.5 | V40: 12.5 | X40: 12.5 | Z40: 12.6 | AA40: 12.7 | AC40: 12.7 | AD40: 12.7 | AE40: 13.1 | AF40: 13 | AG40: 13.1 | AH40: 13.2 | AI40: 13.1 | AJ40: 13 | AK40: 13 | AL40: 13 | AM40: 13.1 | AN40: 13 | AO40: 12.6 | AP40: 12.5 | AQ40: 12.6 | AR40: 12.6 | AS40: 12.5 | AT40: 12.5 | AU40: 12.4 | AV40: 12.4 | AW40: 12.4 | AX40: 12.4 | AY40: 12.3 | AZ40: 12.4 | BA40: 12.4 | BB40: 12.3 | BC40: 12.5 | BD40: 12.7 | BE40: 12.4 | BF40: 12.4 | BG40: 12.5 | BH40: 12.5 | BI40: 12.6 | BJ40: 12.4 | BK40: 12.7 | BL40: 12.8 | BM40: 13.3 | BN40: 12.9
A41: Central Europe and the Baltics | B41: CEB | C41: Income share held by second 20% | D41: SI.DST.02ND.20
A42: Switzerland | B42: CHE | C42: Income share held by second 20% | D42: SI.DST.02ND.20 | AA42: 11.6 | AK42: 12.2 | AS42: 12.2 | AU42: 12.4 | AW42: 12.5 | AY42: 12 | AZ42: 12 | BA42: 12 | BB42: 12.3 | BC42: 12.5 | BD42: 12.6 | BE42: 12.7 | BF42: 12.4 | BG42: 12.5 | BH42: 12.5 | BI42: 12.4 | BJ42: 12.5 | BK42: 12.4 | BL42: 12.2 | BM42: 12.2 | BN42: 12.2 | BO42: 12.3
A43: Channel Islands | B43: CHI | C43: Income share held by second 20% | D43: SI.DST.02ND.20
A44: Chile | B44: CHL | C44: Income share held by second 20% | D44: SI.DST.02ND.20 | AF44: 6.7 | AI44: 6.6 | AK44: 7.2 | AM44: 6.7 | AO44: 7.1 | AQ44: 6.9 | AS44: 7.7 | AV44: 7.9 | AY44: 8.8 | BB44: 8.9 | BD44: 9.1 | BF44: 9 | BH44: 9.4 | BJ44: 9.4 | BM44: 9.1 | BO44: 9.9
A45: China | B45: CHN | C45: Income share held by second 20% | D45: SI.DST.02ND.20 | Z45: 13.5 | AC45: 13.8 | AF45: 13.2 | AI45: 12.4 | AL45: 12 | AO45: 11.5 | AR45: 10.5 | AU45: 9.6 | AX45: 10 | BA45: 9.4 | BC45: 9.2 | BD45: 9.6 | BE45: 9.7 | BF45: 10.3 | BG45: 10.5 | BH45: 10.6 | BI45: 10.7 | BJ45: 10.5 | BK45: 10.7 | BL45: 10.7 | BM45: 11 | BN45: 11.4 | BO45: 11.4
A46: Cote d'Ivoire | B46: CIV | C46: Income share held by second 20% | D46: SI.DST.02ND.20 | AD46: 9.3 | AE46: 10.9 | AF46: 10.4 | AG46: 11.3 | AK46: 10.6 | AN46: 10.2 | AQ46: 10.8 | AU46: 11.2 | BA46: 9.9 | BH46: 10.2 | BK46: 11 | BN46: 11.6
A47: Cameroon | B47: CMR | C47: Income share held by second 20% | D47: SI.DST.02ND.20 | AO47: 9.6 | AT47: 10 | AZ47: 9.5 | BG47: 8.5 | BN47: 9.6
A48: Congo, Dem. Rep. | B48: COD | C48: Income share held by second 20% | D48: SI.DST.02ND.20 | AW48: 9.9 | BE48: 10 | BM48: 9.6
A49: Congo, Rep. | B49: COG | C49: Income share held by second 20% | D49: SI.DST.02ND.20 | AX49: 8.6 | BD49: 8.2
A50: Colombia | B50: COL | C50: Income share held by second 20% | D50: SI.DST.02ND.20 | Y50: 6.6 | AG50: 7.2 | AH50: 7.3 | AJ50: 7.6 | AK50: 8 | AO50: 7 | AR50: 6.5 | AS50: 6.7 | AT50: 6.9 | AU50: 6.8 | AV50: 7.5 | AW50: 7.1 | AX50: 7.3 | BA50: 6.9 | BB50: 7.1 | BC50: 7.1 | BD50: 7.3 | BE50: 7.5 | BF50: 7.5 | BG50: 7.6 | BH50: 7.9 | BI50: 8.1 | BJ50: 8.3 | BK50: 8.1 | BL50: 7.9 | BM50: 7.5 | BN50: 7 | BO50: 7.1 | BP50: 7.2
A51: Comoros | B51: COM | C51: Income share held by second 20% | D51: SI.DST.02ND.20 | AW51: 7.3 | BG51: 9.1
A52: Cabo Verde | B52: CPV | C52: Income share held by second 20% | D52: SI.DST.02ND.20 | AT52: 7.6 | AZ52: 8.7 | BH52: 9.7
A53: Costa Rica | B53: CRI | C53: Income share held by second 20% | D53: SI.DST.02ND.20 | Z53: 8.3 | AE53: 12.2 | AH53: 9.4 | AI53: 9.5 | AJ53: 9.1 | AK53: 9.4 | AL53: 9.2 | AM53: 9.1 | AN53: 9.3 | AO53: 9.1 | AP53: 9.2 | AQ53: 9.2 | AR53: 8.8 | AS53: 8.9 | AT53: 7.8 | AU53: 7.8 | AV53: 8.2 | AW53: 8.5 | AX53: 8.7 | AY53: 8.3 | AZ53: 8.4 | BA53: 8.5 | BB53: 8 | BC53: 8.5 | BD53: 8.2 | BE53: 8.4 | BF53: 8.2 | BG53: 8.3 | BH53: 8.4 | BI53: 8.3 | BJ53: 8.4 | BK53: 8.5 | BL53: 8.4 | BM53: 8.1 | BN53: 8.2 | BO53: 8.6 | BP53: 8.7 | BQ53: 8.8
A54: Caribbean small states | B54: CSS | C54: Income share held by second 20% | D54: SI.DST.02ND.20
A55: Cuba | B55: CUB | C55: Income share held by second 20% | D55: SI.DST.02ND.20
A56: Curacao | B56: CUW | C56: Income share held by second 20% | D56: SI.DST.02ND.20
A57: Cayman Islands | B57: CYM | C57: Income share held by second 20% | D57: SI.DST.02ND.20
A58: Cyprus | B58: CYP | C58: Income share held by second 20% | D58: SI.DST.02ND.20 | AW58: 13 | AX58: 12.9 | AY58: 12.8 | AZ58: 12.6 | BA58: 12.5 | BB58: 12.5 | BC58: 12.8 | BD58: 12.5 | BE58: 12.1 | BF58: 11.4 | BG58: 11.8 | BH58: 12.1 | BI58: 12.4 | BJ58: 12.9 | BK58: 12.5 | BL58: 12.8 | BM58: 12.8 | BN58: 12.8 | BO58: 12.7 | BP58: 12.7
A59: Czechia | B59: CZE | C59: Income share held by second 20% | D59: SI.DST.02ND.20 | AK59: 15.7 | AL59: 13.8 | AO59: 14.6 | AU59: 14.4 | AW59: 14.3 | AX59: 14.5 | AY59: 14.5 | AZ59: 14.6 | BA59: 14.6 | BB59: 14.6 | BC59: 14.5 | BD59: 14.6 | BE59: 14.5 | BF59: 14.5 | BG59: 14.6 | BH59: 14.7 | BI59: 14.7 | BJ59: 14.7 | BK59: 14.7 | BL59: 14.5 | BM59: 14.4 | BN59: 14.4 | BO59: 14.5 | BP59: 14.7
A60: Germany | B60: DEU | C60: Income share held by second 20% | D60: SI.DST.02ND.20 | AJ60: 13.1 | AK60: 13.3 | AL60: 13.4 | AM60: 13.4 | AN60: 13.6 | AO60: 13.7 | AP60: 13.6 | AQ60: 13.6 | AR60: 13.5 | AS60: 13.5 | AT60: 13.2 | AU60: 13.2 | AV60: 13.4 | AW60: 13.2 | AX60: 12.8 | AY60: 13 | AZ60: 12.9 | BA60: 13 | BB60: 13.1 | BC60: 13.2 | BD60: 13.1 | BE60: 13 | BF60: 12.9 | BG60: 13.1 | BH60: 12.9 | BI60: 13 | BJ60: 13.1 | BK60: 12.9 | BL60: 13.1 | BM60: 12.8
A61: Djibouti | B61: DJI | C61: Income share held by second 20% | D61: SI.DST.02ND.20 | AU61: 10.6 | BE61: 9.8 | BF61: 9.7 | BJ61: 10.4
A62: Dominica | B62: DMA | C62: Income share held by second 20% | D62: SI.DST.02ND.20
A63: Denmark | B63: DNK | C63: Income share held by second 20% | D63: SI.DST.02ND.20 | AF63: 14.4 | AK63: 14.9 | AN63: 15 | AS63: 14.7 | AV63: 14.3 | AW63: 14.5 | AX63: 14.6 | AY63: 14.3 | AZ63: 14.4 | BA63: 14.5 | BB63: 14.3 | BC63: 14.1 | BD63: 14 | BE63: 14 | BF63: 13.8 | BG63: 13.9 | BH63: 13.9 | BI63: 13.9 | BJ63: 13.7 | BK63: 13.8 | BL63: 14 | BM63: 14 | BN63: 13.9 | BO63: 13.6 | BP63: 13.5
A64: Dominican Republic | B64: DOM | C64: Income share held by second 20% | D64: SI.DST.02ND.20 | AE64: 8.6 | AH64: 7.9 | AK64: 8.1 | AO64: 8.8 | AP64: 8.5 | AS64: 7.7 | AT64: 8.1 | AU64: 8.3 | AV64: 7.7 | AW64: 7.8 | AX64: 8.1 | AY64: 7.7 | AZ64: 8.4 | BA64: 8.6 | BB64: 8.4 | BC64: 8.5 | BD64: 8.6 | BE64: 9 | BF64: 8.7 | BG64: 9.3 | BH64: 9.3 | BI64: 9.1 | BJ64: 10.2 | BK64: 9.8 | BL64: 10.1 | BM64: 10.7 | BN64: 11.1 | BO64: 11.3 | BP64: 11 | BQ64: 10.7
A65: Algeria | B65: DZA | C65: Income share held by second 20% | D65: SI.DST.02ND.20 | AG65: 11.2 | AN65: 11.6 | BD65: 13.7
A66: East Asia & Pacific (excluding high income) | B66: EAP | C66: Income share held by second 20% | D66: SI.DST.02ND.20
A67: Early-demographic dividend | B67: EAR | C67: Income share held by second 20% | D67: SI.DST.02ND.20
A68: East Asia & Pacific | B68: EAS | C68: Income share held by second 20% | D68: SI.DST.02ND.20
A69: Europe & Central Asia (excluding high income) | B69: ECA | C69: Income share held by second 20% | D69: SI.DST.02ND.20
A70: Europe & Central Asia | B70: ECS | C70: Income share held by second 20% | D70: SI.DST.02ND.20
A71: Ecuador | B71: ECU | C71: Income share held by second 20% | D71: SI.DST.02ND.20 | AF71: 8.1 | AM71: 7.7 | AN71: 8.2 | AQ71: 8.1 | AR71: 6.5 | AS71: 6.9 | AV71: 7.3 | AW71: 7.3 | AX71: 7.4 | AY71: 7.7 | AZ71: 7.4 | BA71: 8.1 | BB71: 8.5 | BC71: 8.4 | BD71: 9 | BE71: 9 | BF71: 8.7 | BG71: 9.3 | BH71: 9.1 | BI71: 9.4 | BJ71: 9.4 | BK71: 9.2 | BL71: 9.1 | BM71: 8.9 | BN71: 9 | BO71: 9.1 | BP71: 9.3 | BQ71: 9.1
A72: Egypt, Arab Rep. | B72: EGY | C72: Income share held by second 20% | D72: SI.DST.02ND.20 | AI72: 12.5 | AN72: 13 | AR72: 12.8 | AW72: 12.7 | BA72: 13 | BC72: 13.1 | BE72: 13.6 | BH72: 12.8 | BJ72: 12.8 | BL72: 12.8 | BN72: 13.5
A73: Euro area | B73: EMU | C73: Income share held by second 20% | D73: SI.DST.02ND.20
A74: Eritrea | B74: ERI | C74: Income share held by second 20% | D74: SI.DST.02ND.20
A75: Spain | B75: ESP | C75: Income share held by second 20% | D75: SI.DST.02ND.20 | Y75: 12.2 | AD75: 12.2 | AI75: 12.8 | AL75: 11.9 | AM75: 12 | AN75: 12 | AO75: 11.8 | AP75: 11.9 | AQ75: 12.2 | AR75: 12.4 | AS75: 12.3 | AV75: 13 | AW75: 12.5 | AX75: 12.8 | AY75: 12.5 | AZ75: 12.2 | BA75: 12.3 | BB75: 12.2 | BC75: 12 | BD75: 11.8 | BE75: 11.9 | BF75: 11.7 | BG75: 11.8 | BH75: 11.8 | BI75: 12 | BJ75: 12.2 | BK75: 12.2 | BL75: 12.3 | BM75: 12.1 | BN75: 12.3 | BO75: 12.5 | BP75: 12.6
A76: Estonia | B76: EST | C76: Income share held by second 20% | D76: SI.DST.02ND.20 | AL76: 10.7 | AN76: 12.9 | AQ76: 11 | AS76: 11.7 | AT76: 11.6 | AU76: 11.7 | AV76: 11.9 | AW76: 12.8 | AX76: 12.7 | AY76: 12.6 | AZ76: 13 | BA76: 13 | BB76: 13.3 | BC76: 13.2 | BD76: 13 | BE76: 12.9 | BF76: 12.2 | BG76: 12.3 | BH76: 12.5 | BI76: 12.7 | BJ76: 12.8 | BK76: 12.8 | BL76: 12.9 | BM76: 13 | BN76: 12.3 | BO76: 12.4 | BP76: 13
A77: Ethiopia | B77: ETH | C77: Income share held by second 20% | D77: SI.DST.02ND.20 | AN77: 9.9 | AR77: 13.2 | AW77: 13 | BC77: 12.6 | BH77: 12.1 | BN77: 12.8
A78: European Union | B78: EUU | C78: Income share held by second 20% | D78: SI.DST.02ND.20
A79: Fragile and conflict affected situations | B79: FCS | C79: Income share held by second 20% | D79: SI.DST.02ND.20
A80: Finland | B80: FIN | C80: Income share held by second 20% | D80: SI.DST.02ND.20 | AF80: 15.2 | AJ80: 14.9 | AN80: 14.8 | AS80: 14 | AV80: 13.9 | AW80: 13.8 | AX80: 13.8 | AY80: 13.7 | AZ80: 13.7 | BA80: 13.8 | BB80: 13.9 | BC80: 13.8 | BD80: 13.9 | BE80: 14 | BF80: 14 | BG80: 14.1 | BH80: 14 | BI80: 14 | BJ80: 14 | BK80: 14 | BL80: 13.9 | BM80: 14 | BN80: 13.9 | BO80: 13.8 | BP80: 14
A81: Fiji | B81: FJI | C81: Income share held by second 20% | D81: SI.DST.02ND.20 | AU81: 11 | BA81: 10.8 | BF81: 11.3 | BL81: 12.9
A82: France | B82: FRA | C82: Income share held by second 20% | D82: SI.DST.02ND.20 | O82: 11.1 | T82: 11.7 | X82: 12.2 | AC82: 12.4 | AI82: 12.6 | AO82: 12.7 | AP82: 12.8 | AQ82: 12.8 | AR82: 12.6 | AS82: 12.6 | AT82: 12.6 | AU82: 12.7 | AV82: 12.8 | AW82: 12.9 | AX82: 13.2 | AY82: 13.2 | AZ82: 12.7 | BA82: 12.6 | BB82: 12.7 | BC82: 12.4 | BD82: 12.5 | BE82: 12.6 | BF82: 12.7 | BG82: 12.7 | BH82: 12.8 | BI82: 12.9 | BJ82: 13 | BK82: 12.9 | BL82: 13.1 | BM82: 13.2 | BN82: 13.1 | BO82: 13.1 | BP82: 12.9
A83: Faroe Islands | B83: FRO | C83: Income share held by second 20% | D83: SI.DST.02ND.20
A84: Micronesia, Fed. Sts. | B84: FSM | C84: Income share held by second 20% | D84: SI.DST.02ND.20 | AX84: 9.8 | BF84: 10.7
A85: Gabon | B85: GAB | C85: Income share held by second 20% | D85: SI.DST.02ND.20 | AX85: 10.1 | BJ85: 10.8
A86: United Kingdom | B86: GBR | C86: Income share held by second 20% | D86: SI.DST.02ND.20 | M86: 13.7 | N86: 13.6 | O86: 13.5 | P86: 13.2 | Q86: 13.4 | R86: 13.2 | S86: 13.4 | T86: 13.6 | U86: 13.6 | V86: 13.7 | W86: 13.7 | X86: 13.6 | Y86: 13.6 | Z86: 13.2 | AA86: 13.1 | AB86: 13.1 | AC86: 13.4 | AD86: 12.9 | AE86: 12.6 | AF86: 12.2 | AG86: 12 | AH86: 12.2 | AI86: 11.6 | AJ86: 11.8 | AK86: 11.9 | AL86: 11.9 | AM86: 11.6 | AN86: 11.7 | AO86: 11.8 | AP86: 11.7 | AQ86: 11.5 | AR86: 11.5 | AS86: 11.1 | AT86: 11.5 | AU86: 12 | AV86: 12 | AW86: 12 | AX86: 11.8 | AY86: 11.8 | AZ86: 12 | BA86: 11.9 | BB86: 11.9 | BC86: 12.2 | BD86: 12.3 | BE86: 12.4 | BF86: 12.3 | BG86: 12.3 | BH86: 12.3 | BI86: 12.4 | BJ86: 12.5 | BK86: 12.2 | BL86: 12.5 | BM86: 12.4 | BN86: 12.5
A87: Georgia | B87: GEO | C87: Income share held by second 20% | D87: SI.DST.02ND.20 | AO87: 11.3 | AP87: 10.4 | AQ87: 10.5 | AR87: 10.6 | AS87: 10.6 | AT87: 10.9 | AU87: 11.3 | AV87: 11.4 | AW87: 11.5 | AX87: 11.2 | AY87: 11.4 | AZ87: 11.1 | BA87: 10.9 | BB87: 11 | BC87: 10.7 | BD87: 10.8 | BE87: 10.8 | BF87: 10.8 | BG87: 11.2 | BH87: 11.3 | BI87: 11.5 | BJ87: 11.1 | BK87: 11.5 | BL87: 11.7 | BM87: 12 | BN87: 12.1 | BO87: 12.3 | BP87: 12 | BQ87: 12.2
A88: Ghana | B88: GHA | C88: Income share held by second 20% | D88: SI.DST.02ND.20 | AF88: 11.7 | AG88: 11.5 | AJ88: 10.9 | AQ88: 10.3 | AX88: 9.9 | BE88: 9.8 | BI88: 9.6
A89: Gibraltar | B89: GIB | C89: Income share held by second 20% | D89: SI.DST.02ND.20
A90: Guinea | B90: GIN | C90: Income share held by second 20% | D90: SI.DST.02ND.20 | AJ90: 8.2 | AM90: 8.8 | AU90: 9.8 | AZ90: 10.7 | BE90: 12.2 | BK90: 13.1
A91: Gambia, The | B91: GMB | C91: Income share held by second 20% | D91: SI.DST.02ND.20 | AQ91: 8.6 | AV91: 8.7 | BC91: 9.8 | BH91: 11.6 | BM91: 10.9
A92: Guinea-Bissau | B92: GNB | C92: Income share held by second 20% | D92: SI.DST.02ND.20 | AJ92: 6.6 | AL92: 9.5 | AU92: 11.8 | BC92: 8.3 | BK92: 11.6 | BN92: 11.9
A93: Equatorial Guinea | B93: GNQ | C93: Income share held by second 20% | D93: SI.DST.02ND.20 | BO93: 10.6
A94: Greece | B94: GRC | C94: Income share held by second 20% | D94: SI.DST.02ND.20 | AN94: 11.6 | AS94: 12 | AU94: 11.8 | AV94: 12.4 | AW94: 12.3 | AX94: 12 | AY94: 11.9 | AZ94: 12.3 | BA94: 12.5 | BB94: 12.5 | BC94: 12.3 | BD94: 12.2 | BE94: 11.7 | BF94: 11.8 | BG94: 11.9 | BH94: 11.8 | BI94: 12.2 | BJ94: 12.3 | BK94: 12.4 | BL94: 12.6 | BM94: 12.5 | BN94: 12.5 | BO94: 12.5 | BP94: 12.6
A95: Grenada | B95: GRD | C95: Income share held by second 20% | D95: SI.DST.02ND.20 | BK95: 9.7
A96: Greenland | B96: GRL | C96: Income share held by second 20% | D96: SI.DST.02ND.20
A97: Guatemala | B97: GTM | C97: Income share held by second 20% | D97: SI.DST.02ND.20 | AE97: 6.8 | AH97: 5.8 | AQ97: 7.9 | AS97: 7.4 | AY97: 7 | BG97: 8.6 | BP97: 9.3
A98: Guam | B98: GUM | C98: Income share held by second 20% | D98: SI.DST.02ND.20
A99: Guyana | B99: GUY | C99: Income share held by second 20% | D99: SI.DST.02ND.20 | AK99: 10.5 | AQ99: 9.8
A100: High income | B100: HIC | C100: Income share held by second 20% | D100: SI.DST.02ND.20
A101: Hong Kong SAR, China | B101: HKG | C101: Income share held by second 20% | D101: SI.DST.02ND.20
...

Sheet third_20
A1: Data Source | B1: World Development Indicators
A2: Last Updated Date | B2: 46007
A4: Country Name | B4: Country Code | C4: Indicator Name | D4: Indicator Code | E4: 1960 | F4: 1961 | G4: 1962 | H4: 1963 | I4: 1964 | J4: 1965 | K4: 1966 | L4: 1967 | M4: 1968 | N4: 1969 | O4: 1970 | P4: 1971 | Q4: 1972 | R4: 1973 | S4: 1974 | T4: 1975 | U4: 1976 | V4: 1977 | W4: 1978 | X4: 1979 | Y4: 1980 | Z4: 1981 | AA4: 1982 | AB4: 1983 | AC4: 1984 | AD4: 1985 | AE4: 1986 | AF4: 1987 | AG4: 1988 | AH4: 1989 | AI4: 1990 | AJ4: 1991 | AK4: 1992 | AL4: 1993 | AM4: 1994 | AN4: 1995 | AO4: 1996 | AP4: 1997 | AQ4: 1998 | AR4: 1999 | AS4: 2000 | AT4: 2001 | AU4: 2002 | AV4: 2003 | AW4: 2004 | AX4: 2005 | AY4: 2006 | AZ4: 2007 | BA4: 2008 | BB4: 2009 | BC4: 2010 | BD4: 2011 | BE4: 2012 | BF4: 2013 | BG4: 2014 | BH4: 2015 | BI4: 2016 | BJ4: 2017 | BK4: 2018 | BL4: 2019 | BM4: 2020 | BN4: 2021 | BO4: 2022 | BP4: 2023 | BQ4: 2024
A5: Aruba | B5: ABW | C5: Income share held by third 20% | D5: SI.DST.03RD.20
A6: Africa Eastern and Southern | B6: AFE | C6: Income share held by third 20% | D6: SI.DST.03RD.20
A7: Afghanistan | B7: AFG | C7: Income share held by third 20% | D7: SI.DST.03RD.20
A8: Africa Western and Central | B8: AFW | C8: Income share held by third 20% | D8: SI.DST.03RD.20
A9: Angola | B9: AGO | C9: Income share held by third 20% | D9: SI.DST.03RD.20 | AS9: 12.7 | BA9: 14.5 | BK9: 12.6
A10: Albania | B10: ALB | C10: Income share held by third 20% | D10: SI.DST.03RD.20 | AO10: 17.6 | AU10: 16.5 | AX10: 17 | BA10: 16.8 | BE10: 17.3 | BG10: 16.4 | BH10: 16.5 | BI10: 16.4 | BJ10: 16.5 | BK10: 17.5 | BL10: 17 | BM10: 17.3
A11: Andorra | B11: AND | C11: Income share held by third 20% | D11: SI.DST.03RD.20
A12: Arab World | B12: ARB | C12: Income share held by third 20% | D12: SI.DST.03RD.20
A13: United Arab Emirates | B13: ARE | C13: Income share held by third 20% | D13: SI.DST.03RD.20 | BF13: 18 | BK13: 18.9
A14: Argentina | B14: ARG | C14: Income share held by third 20% | D14: SI.DST.03RD.20 | Y14: 15.4 | AE14: 14.6 | AF14: 14.1 | AJ14: 13.3 | AK14: 13.9 | AL14: 14.3 | AM14: 14 | AN14: 13.3 | AO14: 13.1 | AP14: 13.2 | AQ14: 12.7 | AR14: 13.1 | AS14: 12.8 | AT14: 12.3 | AU14: 12.2 | AV14: 12.7 | AW14: 13.6 | AX14: 13.7 | AY14: 14.2 | AZ14: 14.2 | BA14: 14.5 | BB14: 15 | BC14: 14.9 | BD14: 15 | BE14: 15.4 | BF14: 15.5 | BG14: 15.1 | BI14: 15.1 | BJ14: 15.3 | BK14: 15.3 | BL14: 14.9 | BM14: 15 | BN14: 14.9 | BO14: 15.2 | BP14: 14.9 | BQ14: 14.8
A15: Armenia | B15: ARM | C15: Income share held by third 20% | D15: SI.DST.03RD.20 | AO15: 13.9 | AR15: 15.4 | AT15: 15.6 | AU15: 15.6 | AV15: 15.9 | AW15: 15 | AX15: 15.2 | AY15: 17 | AZ15: 16.7 | BA15: 17 | BB15: 17.2 | BC15: 16.8 | BD15: 17 | BE15: 17.1 | BF15: 16.9 | BG15: 16.9 | BH15: 16.7 | BI15: 17 | BJ15: 15.9 | BK15: 15.9 | BL15: 17 | BM15: 17.8 | BN15: 17.3 | BO15: 17.5 | BP15: 17.5
A16: American Samoa | B16: ASM | C16: Income share held by third 20% | D16: SI.DST.03RD.20
A17: Antigua and Barbuda | B17: ATG | C17: Income share held by third 20% | D17: SI.DST.03RD.20
A18: Australia | B18: AUS | C18: Income share held by third 20% | D18: SI.DST.03RD.20 | Z18: 17 | AD18: 16.6 | AH18: 16.7 | AN18: 16.7 | AT18: 16.5 | AV18: 16.5 | AW18: 16.5 | BA18: 15.9 | BC18: 16.1 | BG18: 16.2 | BI18: 16.5 | BK18: 16.4 | BM18: 16.6
A19: Austria | B19: AUT | C19: Income share held by third 20% | D19: SI.DST.03RD.20 | AM19: 17 | AN19: 17.3 | AO19: 17.4 | AP19: 17.6 | AQ19: 16.9 | AR19: 17.3 | AS19: 17.5 | AV19: 17.4 | AW19: 17.2 | AX19: 17.5 | AY19: 17.2 | AZ19: 17.3 | BA19: 17.5 | BB19: 17.4 | BC19: 17.5 | BD19: 17.4 | BE19: 17.5 | BF19: 17.2 | BG19: 17.5 | BH19: 17.7 | BI19: 17.6 | BJ19: 17.8 | BK19: 17.4 | BL19: 17.5 | BM19: 17.8 | BN19: 17.7 | BO19: 17.7 | BP19: 17.5
A20: Azerbaijan | B20: AZE | C20: Income share held by third 20% | D20: SI.DST.03RD.20 | AN20: 16.4 | AT20: 15.3 | AU20: 17.1 | AV20: 17.1 | AW20: 16.7 | AX20: 16.7
A21: Burundi | B21: BDI | C21: Income share held by third 20% | D21: SI.DST.03RD.20 | AK21: 16.3 | AQ21: 15.2 | AY21: 15.3 | BF21: 15 | BM21: 15.3
A22: Belgium | B22: BEL | C22: Income share held by third 20% | D22: SI.DST.03RD.20 | AD22: 18.3 | AG22: 18.2 | AK22: 18.4 | AN22: 17.8 | AP22: 18 | AS22: 16.3 | AV22: 17.9 | AW22: 17.1 | AX22: 17.3 | AY22: 17.7 | AZ22: 17.4 | BA22: 17.6 | BB22: 17.7 | BC22: 17.8 | BD22: 18 | BE22: 18 | BF22: 18 | BG22: 17.8 | BH22: 18.1 | BI22: 18.1 | BJ22: 18.1 | BK22: 18 | BL22: 17.9 | BM22: 18.1 | BN22: 17.9 | BO22: 17.9 | BP22: 18
A23: Benin | B23: BEN | C23: Income share held by third 20% | D23: SI.DST.03RD.20 | AV23: 15 | BD23: 13.4 | BH23: 14.1 | BK23: 15 | BN23: 16.1
A24: Burkina Faso | B24: BFA | C24: Income share held by third 20% | D24: SI.DST.03RD.20 | AM24: 12 | AQ24: 12.1 | AV24: 14 | BB24: 14.7 | BG24: 15 | BK24: 13.6 | BN24: 15.1
A25: Bangladesh | B25: BGD | C25: Income share held by third 20% | D25: SI.DST.03RD.20 | AB25: 17.9 | AD25: 17.2 | AG25: 17 | AJ25: 17.3 | AN25: 15.7 | AS25: 15.6 | AX25: 15.6 | BC25: 16 | BI25: 16.1 | BO25: 16.5
A26: Bulgaria | B26: BGR | C26: Income share held by third 20% | D26: SI.DST.03RD.20 | AH26: 18.3 | AK26: 17.1 | AM26: 18.1 | AN26: 16.5 | AP26: 17.4 | AT26: 17.2 | AV26: 17.3 | AY26: 17.1 | AZ26: 16.3 | BA26: 16.9 | BB26: 17 | BC26: 16.7 | BD26: 17.1 | BE26: 16.6 | BF26: 16.7 | BG26: 16.2 | BH26: 16.2 | BI26: 15.5 | BJ26: 15.4 | BK26: 14.9 | BL26: 15.2 | BM26: 14.9 | BN26: 15.5 | BO26: 15.6 | BP26: 15.4
A27: Bahrain | B27: BHR | C27: Income share held by third 20% | D27: SI.DST.03RD.20
A28: Bahamas, The | B28: BHS | C28: Income share held by third 20% | D28: SI.DST.03RD.20
A29: Bosnia and Herzegovina | B29: BIH | C29: Income share held by third 20% | D29: SI.DST.03RD.20 | AT29: 17 | AW29: 16.3 | AZ29: 16.6 | BD29: 16.7
A30: Belarus | B30: BLR | C30: Income share held by third 20% | D30: SI.DST.03RD.20 | AL30: 18.5 | AN30: 17.7 | AQ30: 16.9 | AR30: 17.2 | AS30: 17.2 | AT30: 17.2 | AU30: 17.3 | AV30: 17.5 | AW30: 17.9 | AX30: 17.8 | AY30: 17.7 | AZ30: 17.3 | BA30: 17.7 | BB30: 17.7 | BC30: 17.5 | BD30: 17.8 | BE30: 17.9 | BF30: 17.8 | BG30: 17.7 | BH30: 17.9 | BI30: 17.9 | BJ30: 17.8 | BK30: 17.8 | BL30: 17.9 | BM30: 18
A31: Belize | B31: BLZ | C31: Income share held by third 20% | D31: SI.DST.03RD.20 | AL31: 10 | AM31: 9.8 | AN31: 11.1 | AO31: 10.7 | AP31: 10.2 | AQ31: 11.3 | AR31: 12 | BK31: 15.2
A32: Bermuda | B32: BMU | C32: Income share held by third 20% | D32: SI.DST.03RD.20
A33: Bolivia | B33: BOL | C33: Income share held by third 20% | D33: SI.DST.03RD.20 | AI33: 14.5 | AK33: 12.5 | AP33: 11.1 | AR33: 11.7 | AS33: 10.7 | AT33: 11.6 | AU33: 11 | AW33: 11.4 | AX33: 10.8 | AY33: 11.3 | AZ33: 11.8 | BA33: 13.1 | BB33: 13.9 | BD33: 14.3 | BE33: 14.5 | BF33: 14 | BG33: 13.8 | BH33: 14.2 | BI33: 14.7 | BJ33: 14.9 | BK33: 15.2 | BL33: 15 | BM33: 14.5 | BN33: 15.3 | BO33: 15.2 | BP33: 14.8
A34: Brazil | B34: BRA | C34: Income share held by third 20% | D34: SI.DST.03RD.20 | Z34: 10.5 | AA34: 10.3 | AB34: 10 | AC34: 10.2 | AD34: 11 | AE34: 10.3 | AF34: 10.1 | AG34: 9.5 | AH34: 8.9 | AI34: 9.7 | AK34: 12.2 | AL34: 10.1 | AN34: 10.1 | AO34: 10 | AP34: 10 | AQ34: 10 | AR34: 10.2 | AT34: 10.5 | AU34: 10.5 | AV34: 10.7 | AW34: 11 | AX34: 11.1 | AY34: 11.2 | AZ34: 11.6 | BA34: 11.8 | BB34: 11.9 | BD34: 12.2 | BE34: 12 | BF34: 12.2 | BG34: 12.3 | BH34: 12.4 | BI34: 12 | BJ34: 12.1 | BK34: 12 | BL34: 12.2 | BM34: 12.9 | BN34: 12.1 | BO34: 12.3 | BP34: 12.5
A35: Barbados | B35: BRB | C35: Income share held by third 20% | D35: SI.DST.03RD.20 | BI35: 16.9
A36: Brunei Darussalam | B36: BRN | C36: Income share held by third 20% | D36: SI.DST.03RD.20
A37: Bhutan | B37: BTN | C37: Income share held by third 20% | D37: SI.DST.03RD.20 | AV37: 14.2 | AZ37: 15.3 | BE37: 15 | BJ37: 15.5 | BO37: 17.6
A38: Botswana | B38: BWA | C38: Income share held by third 20% | D38: SI.DST.03RD.20 | AD38: 11.4 | AL38: 9.9 | AU38: 8.8 | BB38: 10.6 | BH38: 10.7
A39: Central African Republic | B39: CAF | C39: Income share held by third 20% | D39: SI.DST.03RD.20 | AK39: 9.5 | BA39: 11.1 | BN39: 14.1
A40: Canada | B40: CAN | C40: Income share held by third 20% | D40: SI.DST.03RD.20 | P40: 16.4 | R40: 16.8 | T40: 16.9 | V40: 17.1 | X40: 17.1 | Z40: 17 | AA40: 17 | AC40: 17 | AD40: 17 | AE40: 17.4 | AF40: 17.3 | AG40: 17.3 | AH40: 17.5 | AI40: 17.5 | AJ40: 17.3 | AK40: 17.4 | AL40: 17.4 | AM40: 17.4 | AN40: 17.5 | AO40: 17.1 | AP40: 17 | AQ40: 17 | AR40: 17.1 | AS40: 17 | AT40: 16.9 | AU40: 16.9 | AV40: 16.9 | AW40: 16.9 | AX40: 16.9 | AY40: 16.7 | AZ40: 16.7 | BA40: 16.8 | BB40: 16.8 | BC40: 16.8 | BD40: 17 | BE40: 17.2 | BF40: 17.1 | BG40: 17.1 | BH40: 17 | BI40: 17.2 | BJ40: 17.1 | BK40: 17.1 | BL40: 17.2 | BM40: 17.3 | BN40: 17.1
A41: Central Europe and the Baltics | B41: CEB | C41: Income share held by third 20% | D41: SI.DST.03RD.20
A42: Switzerland | B42: CHE | C42: Income share held by third 20% | D42: SI.DST.03RD.20 | AA42: 15.7 | AK42: 16.5 | AS42: 16.3 | AU42: 16.8 | AW42: 16.7 | AY42: 16.5 | AZ42: 16.4 | BA42: 16.5 | BB42: 16.6 | BC42: 16.8 | BD42: 17 | BE42: 16.8 | BF42: 16.6 | BG42: 16.6 | BH42: 16.8 | BI42: 16.6 | BJ42: 16.7 | BK42: 16.8 | BL42: 16.4 | BM42: 16.5 | BN42: 16.5 | BO42: 16.6
A43: Channel Islands | B43: CHI | C43: Income share held by third 20% | D43: SI.DST.03RD.20
A44: Chile | B44: CHL | C44: Income share held by third 20% | D44: SI.DST.03RD.20 | AF44: 10.6 | AI44: 10.3 | AK44: 11 | AM44: 10.6 | AO44: 11 | AQ44: 10.9 | AS44: 11.8 | AV44: 12.2 | AY44: 12.9 | BB44: 12.9 | BD44: 12.9 | BF44: 12.9 | BH44: 13.3 | BJ44: 13.3 | BM44: 13.1 | BO44: 14
A45: China | B45: CHN | C45: Income share held by third 20% | D45: SI.DST.03RD.20 | Z45: 17.4 | AC45: 17.8 | AF45: 17.6 | AI45: 16.4 | AL45: 15.9 | AO45: 15.9 | AR45: 15.1 | AU45: 14.4 | AX45: 14.7 | BA45: 14.5 | BC45: 14.3 | BD45: 14.6 | BE45: 14.7 | BF45: 15 | BG45: 15.2 | BH45: 15.3 | BI45: 15.3 | BJ45: 15.1 | BK45: 15.3 | BL45: 15.2 | BM45: 15.3 | BN45: 15.7 | BO45: 15.7
A46: Cote d'Ivoire | B46: CIV | C46: Income share held by third 20% | D46: SI.DST.03RD.20 | AD46: 13.8 | AE46: 15.2 | AF46: 14.8 | AG46: 15.5 | AK46: 15.3 | AN46: 14.5 | AQ46: 15.2 | AU46: 13.7 | BA46: 14.2 | BH46: 14.6 | BK46: 15.4 | BN46: 15.7
A47: Cameroon | B47: CMR | C47: Income share held by third 20% | D47: SI.DST.03RD.20 | AO47: 13 | AT47: 14.2 | AZ47: 14 | BG47: 13.7 | BN47: 14.7
A48: Congo, Dem. Rep. | B48: COD | C48: Income share held by third 20% | D48: SI.DST.03RD.20 | AW48: 14.3 | BE48: 14.5 | BM48: 13.7
A49: Congo, Rep. | B49: COG | C49: Income share held by third 20% | D49: SI.DST.03RD.20 | AX49: 12.8 | BD49: 13.2
A50: Colombia | B50: COL | C50: Income share held by third 20% | D50: SI.DST.03RD.20 | Y50: 11.6 | AG50: 12.1 | AH50: 12 | AJ50: 12.6 | AK50: 12.2 | AO50: 11.3 | AR50: 10.9 | AS50: 11 | AT50: 11.1 | AU50: 10.9 | AV50: 11.7 | AW50: 11.1 | AX50: 11.5 | BA50: 11.4 | BB50: 11.6 | BC50: 11.4 | BD50: 11.7 | BE50: 12 | BF50: 12.1 | BG50: 12.1 | BH50: 12.5 | BI50: 12.6 | BJ50: 12.8 | BK50: 12.6 | BL50: 12.4 | BM50: 12 | BN50: 11.3 | BO50: 11.3 | BP50: 11.5
A51: Comoros | B51: COM | C51: Income share held by third 20% | D51: SI.DST.03RD.20 | AW51: 10.8 | BG51: 13.9
A52: Cabo Verde | B52: CPV | C52: Income share held by third 20% | D52: SI.DST.03RD.20 | AT52: 11.7 | AZ52: 13 | BH52: 14.3
A53: Costa Rica | B53: CRI | C53: Income share held by third 20% | D53: SI.DST.03RD.20 | Z53: 14.1 | AE53: 18.1 | AH53: 14.7 | AI53: 14.6 | AJ53: 14.4 | AK53: 14.4 | AL53: 14.3 | AM53: 14 | AN53: 14.3 | AO53: 14 | AP53: 14.2 | AQ53: 14.1 | AR53: 13.5 | AS53: 13.7 | AT53: 12.4 | AU53: 12.2 | AV53: 13 | AW53: 13.1 | AX53: 13.3 | AY53: 12.8 | AZ53: 12.6 | BA53: 12.8 | BB53: 12.3 | BC53: 12.9 | BD53: 12.9 | BE53: 13 | BF53: 12.6 | BG53: 12.8 | BH53: 12.8 | BI53: 12.8 | BJ53: 12.8 | BK53: 13 | BL53: 12.8 | BM53: 12.6 | BN53: 12.8 | BO53: 13.1 | BP53: 13.4 | BQ53: 13.8
A54: Caribbean small states | B54: CSS | C54: Income share held by third 20% | D54: SI.DST.03RD.20
A55: Cuba | B55: CUB | C55: Income share held by third 20% | D55: SI.DST.03RD.20
A56: Curacao | B56: CUW | C56: Income share held by third 20% | D56: SI.DST.03RD.20
A57: Cayman Islands | B57: CYM | C57: Income share held by third 20% | D57: SI.DST.03RD.20
A58: Cyprus | B58: CYP | C58: Income share held by third 20% | D58: SI.DST.03RD.20 | AW58: 17 | AX58: 16.9 | AY58: 16.7 | AZ58: 16.7 | BA58: 16.6 | BB58: 16.4 | BC58: 16.4 | BD58: 16.2 | BE58: 15.8 | BF58: 15.1 | BG58: 15.8 | BH58: 16.2 | BI58: 16.3 | BJ58: 16.7 | BK58: 16.3 | BL58: 16.7 | BM58: 16.5 | BN58: 16.8 | BO58: 16.5 | BP58: 16.5
A59: Czechia | B59: CZE | C59: Income share held by third 20% | D59: SI.DST.03RD.20 | AK59: 18.4 | AL59: 17 | AO59: 17.8 | AU59: 17.8 | AW59: 17.7 | AX59: 17.8 | AY59: 17.7 | AZ59: 17.7 | BA59: 17.6 | BB59: 17.7 | BC59: 17.7 | BD59: 17.9 | BE59: 17.9 | BF59: 17.8 | BG59: 17.8 | BH59: 17.8 | BI59: 17.7 | BJ59: 17.7 | BK59: 17.6 | BL59: 17.6 | BM59: 17.6 | BN59: 17.5 | BO59: 17.7 | BP59: 18.1
A60: Germany | B60: DEU | C60: Income share held by third 20% | D60: SI.DST.03RD.20 | AJ60: 17.1 | AK60: 17.2 | AL60: 17.2 | AM60: 17.6 | AN60: 17.6 | AO60: 17.6 | AP60: 17.6 | AQ60: 17.5 | AR60: 17.3 | AS60: 17.4 | AT60: 17 | AU60: 17.1 | AV60: 17.2 | AW60: 17 | AX60: 16.8 | AY60: 16.8 | AZ60: 16.8 | BA60: 17 | BB60: 17.1 | BC60: 17.1 | BD60: 16.9 | BE60: 17 | BF60: 16.9 | BG60: 17.2 | BH60: 17 | BI60: 17.2 | BJ60: 17.2 | BK60: 17 | BL60: 17.1 | BM60: 17
A61: Djibouti | B61: DJI | C61: Income share held by third 20% | D61: SI.DST.03RD.20 | AU61: 15.1 | BE61: 14.4 | BF61: 14.6 | BJ61: 15.1
A62: Dominica | B62: DMA | C62: Income share held by third 20% | D62: SI.DST.03RD.20
A63: Denmark | B63: DNK | C63: Income share held by third 20% | D63: SI.DST.03RD.20 | AF63: 18 | AK63: 18.3 | AN63: 18.3 | AS63: 18.1 | AV63: 17.9 | AW63: 18 | AX63: 17.9 | AY63: 17.7 | AZ63: 17.6 | BA63: 18 | BB63: 17.9 | BC63: 17.6 | BD63: 17.5 | BE63: 17.4 | BF63: 17.3 | BG63: 17.3 | BH63: 17.2 | BI63: 17.3 | BJ63: 17.2 | BK63: 17.3 | BL63: 17.3 | BM63: 17.5 | BN63: 17.3 | BO63: 17.1 | BP63: 16.8
A64: Dominican Republic | B64: DOM | C64: Income share held by third 20% | D64: SI.DST.03RD.20 | AE64: 13.8 | AH64: 12.5 | AK64: 12.3 | AO64: 13.5 | AP64: 13.3 | AS64: 12.3 | AT64: 12.7 | AU64: 13 | AV64: 12.1 | AW64: 12 | AX64: 12.6 | AY64: 12 | AZ64: 12.9 | BA64: 13 | BB64: 12.8 | BC64: 13.1 | BD64: 12.9 | BE64: 13.5 | BF64: 13 | BG64: 13.9 | BH64: 13.8 | BI64: 13.8 | BJ64: 14.4 | BK64: 13.9 | BL64: 14.4 | BM64: 14.9 | BN64: 15.2 | BO64: 15.7 | BP64: 15.6 | BQ64: 15.4
A65: Algeria | B65: DZA | C65: Income share held by third 20% | D65: SI.DST.03RD.20 | AG65: 15.6 | AN65: 16.2 | BD65: 17.5
A66: East Asia & Pacific (excluding high income) | B66: EAP | C66: Income share held by third 20% | D66: SI.DST.03RD.20
A67: Early-demographic dividend | B67: EAR | C67: Income share held by third 20% | D67: SI.DST.03RD.20
A68: East Asia & Pacific | B68: EAS | C68: Income share held by third 20% | D68: SI.DST.03RD.20
A69: Europe & Central Asia (excluding high income) | B69: ECA | C69: Income share held by third 20% | D69: SI.DST.03RD.20
A70: Europe & Central Asia | B70: ECS | C70: Income share held by third 20% | D70: SI.DST.03RD.20
A71: Ecuador | B71: ECU | C71: Income share held by third 20% | D71: SI.DST.03RD.20 | AF71: 13.3 | AM71: 12 | AN71: 12.5 | AQ71: 12.5 | AR71: 10.7 | AS71: 11.2 | AV71: 11.9 | AW71: 11.8 | AX71: 12 | AY71: 12.1 | AZ71: 11.7 | BA71: 12.9 | BB71: 13.1 | BC71: 13 | BD71: 13.9 | BE71: 14 | BF71: 13.5 | BG71: 14 | BH71: 13.8 | BI71: 14.1 | BJ71: 14.3 | BK71: 14 | BL71: 13.9 | BM71: 13.6 | BN71: 13.9 | BO71: 14 | BP71: 14.2 | BQ71: 14.4
A72: Egypt, Arab Rep. | B72: EGY | C72: Income share held by third 20% | D72: SI.DST.03RD.20 | AI72: 16.3 | AN72: 16.4 | AR72: 16.3 | AW72: 16.1 | BA72: 16.2 | BC72: 16.4 | BE72: 16.7 | BH72: 16 | BJ72: 16.2 | BL72: 16.1 | BN72: 16.9
A73: Euro area | B73: EMU | C73: Income share held by third 20% | D73: SI.DST.03RD.20
A74: Eritrea | B74: ERI | C74: Income share held by third 20% | D74: SI.DST.03RD.20
A75: Spain | B75: ESP | C75: Income share held by third 20% | D75: SI.DST.03RD.20 | Y75: 16.7 | AD75: 16.5 | AI75: 17.1 | AL75: 16.6 | AM75: 16.8 | AN75: 16.6 | AO75: 16.6 | AP75: 16.7 | AQ75: 16.8 | AR75: 16.8 | AS75: 16.8 | AV75: 17.5 | AW75: 17.1 | AX75: 17.4 | AY75: 17.2 | AZ75: 16.9 | BA75: 17 | BB75: 16.9 | BC75: 16.8 | BD75: 16.9 | BE75: 17 | BF75: 17 | BG75: 17 | BH75: 17 | BI75: 17.1 | BJ75: 17.2 | BK75: 17.1 | BL75: 17.3 | BM75: 17.2 | BN75: 17.2 | BO75: 17.2 | BP75: 17.3
A76: Estonia | B76: EST | C76: Income share held by third 20% | D76: SI.DST.03RD.20 | AL76: 15.2 | AN76: 17.5 | AQ76: 15.3 | AS76: 16.1 | AT76: 15.9 | AU76: 16 | AV76: 15.8 | AW76: 16.4 | AX76: 16.3 | AY76: 16.3 | AZ76: 16.7 | BA76: 16.6 | BB76: 16.9 | BC76: 17 | BD76: 16.6 | BE76: 16.5 | BF76: 15.9 | BG76: 16.1 | BH76: 16.4 | BI76: 16.8 | BJ76: 17 | BK76: 17.1 | BL76: 16.9 | BM76: 16.8 | BN76: 16.7 | BO76: 16.7 | BP76: 16.7
A77: Ethiopia | B77: ETH | C77: Income share held by third 20% | D77: SI.DST.03RD.20 | AN77: 13.4 | AR77: 16.8 | AW77: 16.9 | BC77: 16.3 | BH77: 16.3 | BN77: 16.8
A78: European Union | B78: EUU | C78: Income share held by third 20% | D78: SI.DST.03RD.20
A79: Fragile and conflict affected situations | B79: FCS | C79: Income share held by third 20% | D79: SI.DST.03RD.20
A80: Finland | B80: FIN | C80: Income share held by third 20% | D80: SI.DST.03RD.20 | AF80: 18.5 | AJ80: 18.2 | AN80: 17.9 | AS80: 17.5 | AV80: 17.4 | AW80: 17.2 | AX80: 17.3 | AY80: 17.3 | AZ80: 17.3 | BA80: 17.3 | BB80: 17.5 | BC80: 17.4 | BD80: 17.3 | BE80: 17.5 | BF80: 17.5 | BG80: 17.5 | BH80: 17.5 | BI80: 17.5 | BJ80: 17.4 | BK80: 17.5 | BL80: 17.4 | BM80: 17.4 | BN80: 17.3 | BO80: 17.3 | BP80: 17.6
A81: Fiji | B81: FJI | C81: Income share held by third 20% | D81: SI.DST.03RD.20 | AU81: 15.2 | BA81: 14.4 | BF81: 15.2 | BL81: 16.8
A82: France | B82: FRA | C82: Income share held by third 20% | D82: SI.DST.03RD.20 | O82: 15.4 | T82: 15.8 | X82: 16.4 | AC82: 16.7 | AI82: 16.9 | AO82: 17.2 | AP82: 17.2 | AQ82: 17.1 | AR82: 16.9 | AS82: 16.9 | AT82: 16.9 | AU82: 16.9 | AV82: 16.8 | AW82: 17 | AX82: 17.2 | AY82: 17.3 | AZ82: 16.5 | BA82: 16.5 | BB82: 16.7 | BC82: 16.3 | BD82: 16.4 | BE82: 16.5 | BF82: 16.6 | BG82: 16.7 | BH82: 16.7 | BI82: 16.9 | BJ82: 16.9 | BK82: 16.7 | BL82: 17.3 | BM82: 17.5 | BN82: 17.3 | BO82: 17.3 | BP82: 17.2
A83: Faroe Islands | B83: FRO | C83: Income share held by third 20% | D83: SI.DST.03RD.20
A84: Micronesia, Fed. Sts. | B84: FSM | C84: Income share held by third 20% | D84: SI.DST.03RD.20 | AX84: 14.7 | BF84: 15.3
A85: Gabon | B85: GAB | C85: Income share held by third 20% | D85: SI.DST.03RD.20 | AX85: 14.4 | BJ85: 15.7
A86: United Kingdom | B86: GBR | C86: Income share held by third 20% | D86: SI.DST.03RD.20 | M86: 17.4 | N86: 17.3 | O86: 17.2 | P86: 16.9 | Q86: 17.2 | R86: 16.9 | S86: 17 | T86: 17.3 | U86: 17.4 | V86: 17.5 | W86: 17.6 | X86: 17.4 | Y86: 17.1 | Z86: 17.1 | AA86: 17.1 | AB86: 17.1 | AC86: 17.3 | AD86: 16.9 | AE86: 16.8 | AF86: 16.2 | AG86: 16.1 | AH86: 16.5 | AI86: 15.9 | AJ86: 16.2 | AK86: 16.3 | AL86: 16.3 | AM86: 16 | AN86: 16.1 | AO86: 16.2 | AP86: 16.1 | AQ86: 15.9 | AR86: 15.9 | AS86: 15.3 | AT86: 15.7 | AU86: 16.3 | AV86: 16.3 | AW86: 16.2 | AX86: 16.2 | AY86: 16.1 | AZ86: 16.6 | BA86: 16.2 | BB86: 16.2 | BC86: 16.6 | BD86: 16.7 | BE86: 16.7 | BF86: 16.8 | BG86: 16.8 | BH86: 16.8 | BI86: 16.9 | BJ86: 17.1 | BK86: 16.8 | BL86: 17.2 | BM86: 16.9 | BN86: 17.1
A87: Georgia | B87: GEO | C87: Income share held by third 20% | D87: SI.DST.03RD.20 | AO87: 16.2 | AP87: 15.6 | AQ87: 15.5 | AR87: 15.6 | AS87: 15.4 | AT87: 15.4 | AU87: 16 | AV87: 16.2 | AW87: 16.5 | AX87: 16 | AY87: 16 | AZ87: 15.7 | BA87: 15.7 | BB87: 15.7 | BC87: 15.6 | BD87: 15.5 | BE87: 15.6 | BF87: 15.6 | BG87: 15.8 | BH87: 15.9 | BI87: 15.9 | BJ87: 15.8 | BK87: 16.2 | BL87: 16.2 | BM87: 16.7 | BN87: 16.9 | BO87: 17 | BP87: 16.6 | BQ87: 16.5
A88: Ghana | B88: GHA | C88: Income share held by third 20% | D88: SI.DST.03RD.20 | AF88: 16.3 | AG88: 16 | AJ88: 15.2 | AQ88: 15 | AX88: 14.6 | BE88: 14.6 | BI88: 14.8
A89: Gibraltar | B89: GIB | C89: Income share held by third 20% | D89: SI.DST.03RD.20
A90: Guinea | B90: GIN | C90: Income share held by third 20% | D90: SI.DST.03RD.20 | AJ90: 14.4 | AM90: 13.3 | AU90: 14.1 | AZ90: 14.8 | BE90: 16.4 | BK90: 17.3
A91: Gambia, The | B91: GMB | C91: Income share held by third 20% | D91: SI.DST.03RD.20 | AQ91: 12.9 | AV91: 13 | BC91: 14.1 | BH91: 15.7 | BM91: 15.2
A92: Guinea-Bissau | B92: GNB | C92: Income share held by third 20% | D92: SI.DST.03RD.20 | AJ92: 12 | AL92: 14.2 | AU92: 15.8 | BC92: 12.2 | BK92: 15.7 | BN92: 16.2
A93: Equatorial Guinea | B93: GNQ | C93: Income share held by third 20% | D93: SI.DST.03RD.20 | BO93: 15.2
A94: Greece | B94: GRC | C94: Income share held by third 20% | D94: SI.DST.03RD.20 | AN94: 16.5 | AS94: 16.9 | AU94: 16.6 | AV94: 17.2 | AW94: 16.9 | AX94: 16.7 | AY94: 16.7 | AZ94: 17 | BA94: 16.9 | BB94: 17.1 | BC94: 17.1 | BD94: 17.4 | BE94: 17.2 | BF94: 16.9 | BG94: 17 | BH94: 17 | BI94: 17.1 | BJ94: 17.1 | BK94: 17.2 | BL94: 17.2 | BM94: 17.2 | BN94: 17.2 | BO94: 16.9 | BP94: 16.9
A95: Grenada | B95: GRD | C95: Income share held by third 20% | D95: SI.DST.03RD.20 | BK95: 13.5
A96: Greenland | B96: GRL | C96: Income share held by third 20% | D96: SI.DST.03RD.20
A97: Guatemala | B97: GTM | C97: Income share held by third 20% | D97: SI.DST.03RD.20 | AE97: 11.8 | AH97: 10.7 | AQ97: 13.2 | AS97: 11.5 | AY97: 11.8 | BG97: 13.2 | BP97: 14
A98: Guam | B98: GUM | C98: Income share held by third 20% | D98: SI.DST.03RD.20
A99: Guyana | B99: GUY | C99: Income share held by third 20% | D99: SI.DST.03RD.20 | AK99: 15.9 | AQ99: 14.5
A100: High income | B100: HIC | C100: Income share held by third 20% | D100: SI.DST.03RD.20
A101: Hong Kong SAR, China | B101: HKG | C101: Income share held by third 20% | D101: SI.DST.03RD.20
...

Sheet fourth_20
A1: Data Source | B1: World Development Indicators
A2: Last Updated Date | B2: 46007
A4: Country Name | B4: Country Code | C4: Indicator Name | D4: Indicator Code | E4: 1960 | F4: 1961 | G4: 1962 | H4: 1963 | I4: 1964 | J4: 1965 | K4: 1966 | L4: 1967 | M4: 1968 | N4: 1969 | O4: 1970 | P4: 1971 | Q4: 1972 | R4: 1973 | S4: 1974 | T4: 1975 | U4: 1976 | V4: 1977 | W4: 1978 | X4: 1979 | Y4: 1980 | Z4: 1981 | AA4: 1982 | AB4: 1983 | AC4: 1984 | AD4: 1985 | AE4: 1986 | AF4: 1987 | AG4: 1988 | AH4: 1989 | AI4: 1990 | AJ4: 1991 | AK4: 1992 | AL4: 1993 | AM4: 1994 | AN4: 1995 | AO4: 1996 | AP4: 1997 | AQ4: 1998 | AR4: 1999 | AS4: 2000 | AT4: 2001 | AU4: 2002 | AV4: 2003 | AW4: 2004 | AX4: 2005 | AY4: 2006 | AZ4: 2007 | BA4: 2008 | BB4: 2009 | BC4: 2010 | BD4: 2011 | BE4: 2012 | BF4: 2013 | BG4: 2014 | BH4: 2015 | BI4: 2016 | BJ4: 2017 | BK4: 2018 | BL4: 2019 | BM4: 2020 | BN4: 2021 | BO4: 2022 | BP4: 2023 | BQ4: 2024
A5: Aruba | B5: ABW | C5: Income share held by fourth 20% | D5: SI.DST.04TH.20
A6: Africa Eastern and Southern | B6: AFE | C6: Income share held by fourth 20% | D6: SI.DST.04TH.20
A7: Afghanistan | B7: AFG | C7: Income share held by fourth 20% | D7: SI.DST.04TH.20
A8: Africa Western and Central | B8: AFW | C8: Income share held by fourth 20% | D8: SI.DST.04TH.20
A9: Angola | B9: AGO | C9: Income share held by fourth 20% | D9: SI.DST.04TH.20 | AS9: 20.2 | BA9: 21.9 | BK9: 20.4
A10: Albania | B10: ALB | C10: Income share held by fourth 20% | D10: SI.DST.04TH.20 | AO10: 23.4 | AU10: 22.2 | AX10: 22.5 | BA10: 22.2 | BE10: 22.8 | BG10: 23.3 | BH10: 23 | BI10: 23.2 | BJ10: 23.3 | BK10: 23.3 | BL10: 22.7 | BM10: 23
A11: Andorra | B11: AND | C11: Income share held by fourth 20% | D11: SI.DST.04TH.20
A12: Arab World | B12: ARB | C12: Income share held by fourth 20% | D12: SI.DST.04TH.20
A13: United Arab Emirates | B13: ARE | C13: Income share held by fourth 20% | D13: SI.DST.04TH.20 | BF13: 25.5 | BK13: 23.3
A14: Argentina | B14: ARG | C14: Income share held by fourth 20% | D14: SI.DST.04TH.20 | Y14: 22.6 | AE14: 21.8 | AF14: 21.5 | AJ14: 20.3 | AK14: 21.5 | AL14: 22 | AM14: 21.6 | AN14: 20.8 | AO14: 21.2 | AP14: 21.3 | AQ14: 21 | AR14: 21.3 | AS14: 21.3 | AT14: 21.1 | AU14: 20.3 | AV14: 21.5 | AW14: 22.1 | AX14: 22.1 | AY14: 22.5 | AZ14: 22.4 | BA14: 22.7 | BB14: 23 | BC14: 22.6 | BD14: 22.7 | BE14: 23.2 | BF14: 23.3 | BG14: 23.1 | BI14: 22.8 | BJ14: 23 | BK14: 23 | BL14: 22.8 | BM14: 23.2 | BN14: 22.5 | BO14: 22.7 | BP14: 22.7 | BQ14: 22.5
A15: Armenia | B15: ARM | C15: Income share held by fourth 20% | D15: SI.DST.04TH.20 | AO15: 20.6 | AR15: 21.2 | AT15: 20.8 | AU15: 20.8 | AV15: 20.8 | AW15: 20.2 | AX15: 20.2 | AY15: 22.1 | AZ15: 22.1 | BA15: 22.4 | BB15: 22.4 | BC15: 21.7 | BD15: 22.2 | BE15: 22 | BF15: 22.2 | BG15: 22 | BH15: 21.8 | BI15: 22.8 | BJ15: 20.9 | BK15: 20.8 | BL15: 21.7 | BM15: 22.2 | BN15: 21.8 | BO15: 22.4 | BP15: 22.1
A16: American Samoa | B16: ASM | C16: Income share held by fourth 20% | D16: SI.DST.04TH.20
A17: Antigua and Barbuda | B17: ATG | C17: Income share held by fourth 20% | D17: SI.DST.04TH.20
A18: Australia | B18: AUS | C18: Income share held by fourth 20% | D18: SI.DST.04TH.20 | Z18: 23.5 | AD18: 23 | AH18: 23.3 | AN18: 23 | AT18: 23.2 | AV18: 23.2 | AW18: 22.9 | BA18: 22.5 | BC18: 22.7 | BG18: 22.2 | BI18: 22.9 | BK18: 22.5 | BM18: 22.7
A19: Austria | B19: AUT | C19: Income share held by fourth 20% | D19: SI.DST.04TH.20 | AM19: 22.9 | AN19: 23 | AO19: 22.8 | AP19: 23.1 | AQ19: 22.4 | AR19: 22.7 | AS19: 22.9 | AV19: 22.7 | AW19: 22.5 | AX19: 22.8 | AY19: 22.6 | AZ19: 22.9 | BA19: 22.6 | BB19: 22.6 | BC19: 22.9 | BD19: 23 | BE19: 23 | BF19: 22.7 | BG19: 22.7 | BH19: 22.9 | BI19: 23 | BJ19: 23.1 | BK19: 23 | BL19: 23.1 | BM19: 23 | BN19: 22.9 | BO19: 22.3 | BP19: 22.5
A20: Azerbaijan | B20: AZE | C20: Income share held by fourth 20% | D20: SI.DST.04TH.20 | AN20: 22.5 | AT20: 21.2 | AU20: 21 | AV20: 21.4 | AW20: 20.8 | AX20: 20.9
A21: Burundi | B21: BDI | C21: Income share held by fourth 20% | D21: SI.DST.04TH.20 | AK21: 22 | AQ21: 21.3 | AY21: 20.9 | BF21: 20.8 | BM21: 21.4
A22: Belgium | B22: BEL | C22: Income share held by fourth 20% | D22: SI.DST.04TH.20 | AD22: 22.9 | AG22: 22.8 | AK22: 23.1 | AN22: 22.6 | AP22: 22.8 | AS22: 20.9 | AV22: 22.7 | AW22: 21.9 | AX22: 22.2 | AY22: 22.7 | AZ22: 22.3 | BA22: 22.7 | BB22: 22.7 | BC22: 22.5 | BD22: 22.7 | BE22: 22.8 | BF22: 23 | BG22: 22.8 | BH22: 22.7 | BI22: 22.7 | BJ22: 22.7 | BK22: 22.4 | BL22: 22.3 | BM22: 22.6 | BN22: 22.4 | BO22: 22.1 | BP22: 22.2
A23: Benin | B23: BEN | C23: Income share held by fourth 20% | D23: SI.DST.04TH.20 | AV23: 20.9 | BD23: 20.2 | BH23: 20.8 | BK23: 21.4 | BN23: 22.1
A24: Burkina Faso | B24: BFA | C24: Income share held by fourth 20% | D24: SI.DST.04TH.20 | AM24: 18.7 | AQ24: 17.5 | AV24: 20.8 | BB24: 20.9 | BG24: 20.6 | BK24: 20 | BN24: 21.1
A25: Bangladesh | B25: BGD | C25: Income share held by fourth 20% | D25: SI.DST.04TH.20 | AB25: 22.3 | AD25: 21.7 | AG25: 21.6 | AJ25: 22 | AN25: 20.6 | AS25: 21 | AX25: 20.9 | BC25: 21.2 | BI25: 21.4 | BO25: 21.8
A26: Bulgaria | B26: BGR | C26: Income share held by fourth 20% | D26: SI.DST.04TH.20 | AH26: 22.5 | AK26: 22.3 | AM26: 22.2 | AN26: 22 | AP26: 21.9 | AT26: 22.8 | AV26: 22.2 | AY26: 22.9 | AZ26: 22.3 | BA26: 22.6 | BB26: 22.8 | BC26: 22.7 | BD26: 22.7 | BE26: 22.4 | BF26: 22.6 | BG26: 22.1 | BH26: 22.6 | BI26: 21.8 | BJ26: 21.3 | BK26: 21 | BL26: 21.4 | BM26: 20.7 | BN26: 21.9 | BO26: 21.4 | BP26: 21.2
A27: Bahrain | B27: BHR | C27: Income share held by fourth 20% | D27: SI.DST.04TH.20
A28: Bahamas, The | B28: BHS | C28: Income share held by fourth 20% | D28: SI.DST.04TH.20
A29: Bosnia and Herzegovina | B29: BIH | C29: Income share held by fourth 20% | D29: SI.DST.04TH.20 | AT29: 22.1 | AW29: 22.4 | AZ29: 23 | BD29: 22.9
A30: Belarus | B30: BLR | C30: Income share held by fourth 20% | D30: SI.DST.04TH.20 | AL30: 22.2 | AN30: 22.9 | AQ30: 22.6 | AR30: 23.2 | AS30: 23 | AT30: 22.7 | AU30: 22.6 | AV30: 22.8 | AW30: 22.9 | AX30: 23 | AY30: 22.9 | AZ30: 22.5 | BA30: 22.9 | BB30: 22.4 | BC30: 22.8 | BD30: 22.8 | BE30: 22.5 | BF30: 22.5 | BG30: 22.4 | BH30: 22.6 | BI30: 22.3 | BJ30: 22.5 | BK30: 22.3 | BL30: 22.4 | BM30: 22.5
A31: Belize | B31: BLZ | C31: Income share held by fourth 20% | D31: SI.DST.04TH.20 | AL31: 16.2 | AM31: 15.2 | AN31: 19.7 | AO31: 17.6 | AP31: 16.6 | AQ31: 19 | AR31: 19.4 | BK31: 22.3
A32: Bermuda | B32: BMU | C32: Income share held by fourth 20% | D32: SI.DST.04TH.20
A33: Bolivia | B33: BOL | C33: Income share held by fourth 20% | D33: SI.DST.04TH.20 | AI33: 22 | AK33: 19.7 | AP33: 18.8 | AR33: 20.8 | AS33: 18.8 | AT33: 19.5 | AU33: 18.9 | AW33: 18.8 | AX33: 19.2 | AY33: 19.8 | AZ33: 19.8 | BA33: 20.9 | BB33: 21.3 | BD33: 22.2 | BE33: 22.5 | BF33: 21.7 | BG33: 21.3 | BH33: 21.8 | BI33: 22.8 | BJ33: 22.9 | BK33: 22.9 | BL33: 22.4 | BM33: 22.1 | BN33: 22.4 | BO33: 22.6 | BP33: 22.3
A34: Brazil | B34: BRA | C34: Income share held by fourth 20% | D34: SI.DST.04TH.20 | Z34: 18.4 | AA34: 18.3 | AB34: 18.1 | AC34: 18.1 | AD34: 19.6 | AE34: 18.2 | AF34: 18.1 | AG34: 17.5 | AH34: 16.8 | AI34: 17.9 | AK34: 20.8 | AL34: 17.5 | AN34: 17.9 | AO34: 18.2 | AP34: 18.1 | AQ34: 17.9 | AR34: 18 | AT34: 18.5 | AU34: 18.3 | AV34: 18.7 | AW34: 18.8 | AX34: 18.7 | AY34: 18.8 | AZ34: 19.2 | BA34: 19.3 | BB34: 19.4 | BD34: 19.5 | BE34: 19.2 | BF34: 19.3 | BG34: 19.5 | BH34: 19.6 | BI34: 19.3 | BJ34: 19.4 | BK34: 19.3 | BL34: 19.5 | BM34: 19.3 | BN34: 19.6 | BO34: 19.5 | BP34: 19.4
A35: Barbados | B35: BRB | C35: Income share held by fourth 20% | D35: SI.DST.04TH.20 | BI35: 22.8
A36: Brunei Darussalam | B36: BRN | C36: Income share held by fourth 20% | D36: SI.DST.04TH.20
A37: Bhutan | B37: BTN | C37: Income share held by fourth 20% | D37: SI.DST.04TH.20 | AV37: 21.3 | AZ37: 22.1 | BE37: 21.4 | BJ37: 22.7 | BO37: 22.8
A38: Botswana | B38: BWA | C38: Income share held by fourth 20% | D38: SI.DST.04TH.20 | AD38: 19.2 | AL38: 16.7 | AU38: 16.8 | BB38: 17.8 | BH38: 19.1
A39: Central African Republic | B39: CAF | C39: Income share held by fourth 20% | D39: SI.DST.04TH.20 | AK39: 18.3 | BA39: 17.7 | BN39: 21.4
A40: Canada | B40: CAN | C40: Income share held by fourth 20% | D40: SI.DST.04TH.20 | P40: 23.2 | R40: 23.3 | T40: 23.4 | V40: 23.6 | X40: 23.6 | Z40: 23.5 | AA40: 23.2 | AC40: 23.2 | AD40: 23.1 | AE40: 23.3 | AF40: 23.2 | AG40: 23.3 | AH40: 23.4 | AI40: 23.4 | AJ40: 23.4 | AK40: 23.3 | AL40: 23.4 | AM40: 23.3 | AN40: 23.3 | AO40: 23 | AP40: 22.8 | AQ40: 22.8 | AR40: 22.9 | AS40: 22.8 | AT40: 22.8 | AU40: 23 | AV40: 22.9 | AW40: 23 | AX40: 22.9 | AY40: 22.8 | AZ40: 22.7 | BA40: 22.8 | BB40: 22.9 | BC40: 22.8 | BD40: 22.9 | BE40: 23.2 | BF40: 23.4 | BG40: 23 | BH40: 23 | BI40: 23 | BJ40: 23 | BK40: 23 | BL40: 23.1 | BM40: 22.7 | BN40: 22.6
A41: Central Europe and the Baltics | B41: CEB | C41: Income share held by fourth 20% | D41: SI.DST.04TH.20
A42: Switzerland | B42: CHE | C42: Income share held by fourth 20% | D42: SI.DST.04TH.20 | AA42: 22 | AK42: 22.7 | AS42: 22.7 | AU42: 23.3 | AW42: 23.4 | AY42: 22.7 | AZ42: 22.5 | BA42: 22.6 | BB42: 22.7 | BC42: 22.6 | BD42: 22.7 | BE42: 22.5 | BF42: 22.5 | BG42: 22.5 | BH42: 22.6 | BI42: 22.5 | BJ42: 22.4 | BK42: 22.5 | BL42: 22.3 | BM42: 22.3 | BN42: 22.3 | BO42: 22.1
A43: Channel Islands | B43: CHI | C43: Income share held by fourth 20% | D43: SI.DST.04TH.20
A44: Chile | B44: CHL | C44: Income share held by fourth 20% | D44: SI.DST.04TH.20 | AF44: 17.9 | AI44: 17.3 | AK44: 17.9 | AM44: 17.7 | AO44: 18.2 | AQ44: 18 | AS44: 18.7 | AV44: 19.1 | AY44: 19.6 | BB44: 19.3 | BD44: 19.4 | BF44: 19.2 | BH44: 19.6 | BJ44: 19.6 | BM44: 19.7 | BO44: 20.3
A45: China | B45: CHN | C45: Income share held by fourth 20% | D45: SI.DST.04TH.20 | Z45: 23.2 | AC45: 23.2 | AF45: 23.4 | AI45: 22.1 | AL45: 22.1 | AO45: 22.4 | AR45: 22.3 | AU45: 22.4 | AX45: 22.3 | BA45: 22.5 | BC45: 22.3 | BD45: 22.3 | BE45: 22.4 | BF45: 22.1 | BG45: 22.3 | BH45: 22.3 | BI45: 22.2 | BJ45: 22.1 | BK45: 22.2 | BL45: 22 | BM45: 21.7 | BN45: 21.9 | BO45: 21.9
A46: Cote d'Ivoire | B46: CIV | C46: Income share held by fourth 20% | D46: SI.DST.04TH.20 | AD46: 20.7 | AE46: 21.6 | AF46: 21 | AG46: 22.6 | AK46: 22.3 | AN46: 21.3 | AQ46: 21.4 | AU46: 20.6 | BA46: 21.7 | BH46: 21.7 | BK46: 21.9 | BN46: 21.8
A47: Cameroon | B47: CMR | C47: Income share held by fourth 20% | D47: SI.DST.04TH.20 | AO47: 19.6 | AT47: 20.6 | AZ47: 21.5 | BG47: 21.6 | BN47: 22.5
A48: Congo, Dem. Rep. | B48: COD | C48: Income share held by fourth 20% | D48: SI.DST.04TH.20 | AW48: 21.5 | BE48: 21.6 | BM48: 20.2
A49: Congo, Rep. | B49: COG | C49: Income share held by fourth 20% | D49: SI.DST.04TH.20 | AX49: 20.4 | BD49: 20.7
A50: Colombia | B50: COL | C50: Income share held by fourth 20% | D50: SI.DST.04TH.20 | Y50: 20 | AG50: 20 | AH50: 19.8 | AJ50: 20.4 | AK50: 19.4 | AO50: 18.4 | AR50: 18.1 | AS50: 18.1 | AT50: 18.2 | AU50: 18.4 | AV50: 18.8 | AW50: 18.3 | AX50: 18.6 | BA50: 19 | BB50: 19.2 | BC50: 19 | BD50: 19.3 | BE50: 19.7 | BF50: 19.6 | BG50: 19.6 | BH50: 20 | BI50: 19.9 | BJ50: 20.1 | BK50: 19.9 | BL50: 19.8 | BM50: 19.5 | BN50: 18.8 | BO50: 18.8 | BP50: 19.1
A51: Comoros | B51: COM | C51: Income share held by fourth 20% | D51: SI.DST.04TH.20 | AW51: 16.5 | BG51: 22.2
A52: Cabo Verde | B52: CPV | C52: Income share held by fourth 20% | D52: SI.DST.04TH.20 | AT52: 18.5 | AZ52: 20 | BH52: 21.6
A53: Costa Rica | B53: CRI | C53: Income share held by fourth 20% | D53: SI.DST.04TH.20 | Z53: 22.8 | AE53: 24.9 | AH53: 22.2 | AI53: 22.5 | AJ53: 22.1 | AK53: 22 | AL53: 22.1 | AM53: 21.4 | AN53: 22 | AO53: 21.9 | AP53: 21.8 | AQ53: 21.6 | AR53: 21.1 | AS53: 21.5 | AT53: 20.1 | AU53: 19.7 | AV53: 21.1 | AW53: 21 | AX53: 21 | AY53: 20.1 | AZ53: 19.7 | BA53: 20.3 | BB53: 19.9 | BC53: 20.5 | BD53: 20.8 | BE53: 20.9 | BF53: 21 | BG53: 20.8 | BH53: 20.6 | BI53: 20.6 | BJ53: 20.5 | BK53: 20.9 | BL53: 20.7 | BM53: 20.9 | BN53: 20.6 | BO53: 21.1 | BP53: 21.4 | BQ53: 21.8
A54: Caribbean small states | B54: CSS | C54: Income share held by fourth 20% | D54: SI.DST.04TH.20
A55: Cuba | B55: CUB | C55: Income share held by fourth 20% | D55: SI.DST.04TH.20
A56: Curacao | B56: CUW | C56: Income share held by fourth 20% | D56: SI.DST.04TH.20
A57: Cayman Islands | B57: CYM | C57: Income share held by fourth 20% | D57: SI.DST.04TH.20
A58: Cyprus | B58: CYP | C58: Income share held by fourth 20% | D58: SI.DST.04TH.20 | AW58: 22.3 | AX58: 22 | AY58: 21.6 | AZ58: 21.9 | BA58: 21.6 | BB58: 21.9 | BC58: 21.8 | BD58: 21.6 | BE58: 21.4 | BF58: 20.7 | BG58: 21.3 | BH58: 21.7 | BI58: 21.7 | BJ58: 21.9 | BK58: 21.4 | BL58: 21.8 | BM58: 21.6 | BN58: 21.8 | BO58: 21.6 | BP58: 21.7
A59: Czechia | B59: CZE | C59: Income share held by fourth 20% | D59: SI.DST.04TH.20 | AK59: 21.7 | AL59: 21.3 | AO59: 21.9 | AU59: 21.9 | AW59: 21.9 | AX59: 21.7 | AY59: 21.9 | AZ59: 21.8 | BA59: 21.6 | BB59: 21.9 | BC59: 22 | BD59: 22 | BE59: 21.9 | BF59: 21.8 | BG59: 21.9 | BH59: 21.9 | BI59: 21.8 | BJ59: 22 | BK59: 22 | BL59: 22.1 | BM59: 21.7 | BN59: 22 | BO59: 22.1 | BP59: 22.2
A60: Germany | B60: DEU | C60: Income share held by fourth 20% | D60: SI.DST.04TH.20 | AJ60: 23 | AK60: 22.8 | AL60: 22.9 | AM60: 23 | AN60: 22.9 | AO60: 22.8 | AP60: 23 | AQ60: 23 | AR60: 22.8 | AS60: 22.8 | AT60: 22.5 | AU60: 22.7 | AV60: 22.5 | AW60: 22.5 | AX60: 22.3 | AY60: 22.5 | AZ60: 22.2 | BA60: 22.4 | BB60: 22.7 | BC60: 22.5 | BD60: 22.4 | BE60: 22.6 | BF60: 22.4 | BG60: 22.8 | BH60: 22.6 | BI60: 22.7 | BJ60: 22.7 | BK60: 22.4 | BL60: 22.4 | BM60: 22.5
A61: Djibouti | B61: DJI | C61: Income share held by fourth 20% | D61: SI.DST.04TH.20 | AU61: 21.8 | BE61: 21.2 | BF61: 20.9 | BJ61: 21.6
A62: Dominica | B62: DMA | C62: Income share held by fourth 20% | D62: SI.DST.04TH.20
A63: Denmark | B63: DNK | C63: Income share held by fourth 20% | D63: SI.DST.04TH.20 | AF63: 22.6 | AK63: 22.7 | AN63: 22.6 | AS63: 22.7 | AV63: 22.5 | AW63: 22.6 | AX63: 22.5 | AY63: 22.3 | AZ63: 22.1 | BA63: 22.5 | BB63: 22.5 | BC63: 22.3 | BD63: 22.3 | BE63: 22.1 | BF63: 21.9 | BG63: 22 | BH63: 21.8 | BI63: 22 | BJ63: 21.9 | BK63: 21.9 | BL63: 21.9 | BM63: 22.1 | BN63: 21.8 | BO63: 21.8 | BP63: 21.4
A64: Dominican Republic | B64: DOM | C64: Income share held by fourth 20% | D64: SI.DST.04TH.20 | AE64: 21.4 | AH64: 19.9 | AK64: 19 | AO64: 20.7 | AP64: 20.6 | AS64: 20.1 | AT64: 19.9 | AU64: 20.6 | AV64: 19.3 | AW64: 19.2 | AX64: 19.9 | AY64: 19.4 | AZ64: 19.8 | BA64: 20.2 | BB64: 19.8 | BC64: 20.8 | BD64: 20.6 | BE64: 20.5 | BF64: 19.9 | BG64: 21.5 | BH64: 20.9 | BI64: 20.8 | BJ64: 20.6 | BK64: 20.4 | BL64: 21 | BM64: 21.7 | BN64: 21.5 | BO64: 22.4 | BP64: 22.3 | BQ64: 22.3
A65: Algeria | B65: DZA | C65: Income share held by fourth 20% | D65: SI.DST.04TH.20 | AG65: 21.6 | AN65: 22.6 | BD65: 22.3
A66: East Asia & Pacific (excluding high income) | B66: EAP | C66: Income share held by fourth 20% | D66: SI.DST.04TH.20
A67: Early-demographic dividend | B67: EAR | C67: Income share held by fourth 20% | D67: SI.DST.04TH.20
A68: East Asia & Pacific | B68: EAS | C68: Income share held by fourth 20% | D68: SI.DST.04TH.20
A69: Europe & Central Asia (excluding high income) | B69: ECA | C69: Income share held by fourth 20% | D69: SI.DST.04TH.20
A70: Europe & Central Asia | B70: ECS | C70: Income share held by fourth 20% | D70: SI.DST.04TH.20
A71: Ecuador | B71: ECU | C71: Income share held by fourth 20% | D71: SI.DST.04TH.20 | AF71: 20.9 | AM71: 19.1 | AN71: 19.5 | AQ71: 20.7 | AR71: 17.7 | AS71: 18.1 | AV71: 19.5 | AW71: 19.4 | AX71: 19.9 | AY71: 19.6 | AZ71: 19.4 | BA71: 20.6 | BB71: 20.8 | BC71: 20.5 | BD71: 21.7 | BE71: 21.6 | BF71: 21 | BG71: 21.2 | BH71: 21.3 | BI71: 21.4 | BJ71: 21.5 | BK71: 21.2 | BL71: 21.5 | BM71: 21.1 | BN71: 21.2 | BO71: 21.3 | BP71: 22.1 | BQ71: 22.2
A72: Egypt, Arab Rep. | B72: EGY | C72: Income share held by fourth 20% | D72: SI.DST.04TH.20 | AI72: 21.4 | AN72: 21.1 | AR72: 21.2 | AW72: 20.8 | BA72: 20.8 | BC72: 21.1 | BE72: 21.2 | BH72: 20.6 | BJ72: 21 | BL72: 20.8 | BN72: 21.4
A73: Euro area | B73: EMU | C73: Income share held by fourth 20% | D73: SI.DST.04TH.20
A74: Eritrea | B74: ERI | C74: Income share held by fourth 20% | D74: SI.DST.04TH.20
A75: Spain | B75: ESP | C75: Income share held by fourth 20% | D75: SI.DST.04TH.20 | Y75: 22.7 | AD75: 22.3 | AI75: 22.7 | AL75: 22.9 | AM75: 23.1 | AN75: 22.7 | AO75: 23.1 | AP75: 23 | AQ75: 23.1 | AR75: 22.7 | AS75: 22.8 | AV75: 23.2 | AW75: 23.2 | AX75: 23.2 | AY75: 23.2 | AZ75: 23.1 | BA75: 23.2 | BB75: 23.2 | BC75: 23.2 | BD75: 23.5 | BE75: 23.4 | BF75: 23.7 | BG75: 23.6 | BH75: 23.5 | BI75: 23.5 | BJ75: 23.4 | BK75: 23.5 | BL75: 23.6 | BM75: 23.7 | BN75: 23.6 | BO75: 23.3 | BP75: 23.4
A76: Estonia | B76: EST | C76: Income share held by fourth 20% | D76: SI.DST.04TH.20 | AL76: 21.3 | AN76: 23.4 | AQ76: 21.6 | AS76: 22.2 | AT76: 22.1 | AU76: 22.4 | AV76: 22 | AW76: 22.4 | AX76: 22.3 | AY76: 21.9 | AZ76: 23 | BA76: 22.6 | BB76: 22.5 | BC76: 22.8 | BD76: 22.8 | BE76: 22.6 | BF76: 22.6 | BG76: 22.5 | BH76: 23.2 | BI76: 23.6 | BJ76: 23.7 | BK76: 23.7 | BL76: 23.2 | BM76: 23.1 | BN76: 23.1 | BO76: 23.2 | BP76: 22.8
A77: Ethiopia | B77: ETH | C77: Income share held by fourth 20% | D77: SI.DST.04TH.20 | AN77: 18.8 | AR77: 21.5 | AW77: 21.4 | BC77: 21.3 | BH77: 21.2 | BN77: 22.4
A78: European Union | B78: EUU | C78: Income share held by fourth 20% | D78: SI.DST.04TH.20
A79: Fragile and conflict affected situations | B79: FCS | C79: Income share held by fourth 20% | D79: SI.DST.04TH.20
A80: Finland | B80: FIN | C80: Income share held by fourth 20% | D80: SI.DST.04TH.20 | AF80: 22.6 | AJ80: 22.6 | AN80: 22.2 | AS80: 22.2 | AV80: 22.1 | AW80: 22.2 | AX80: 22.2 | AY80: 22.4 | AZ80: 22.3 | BA80: 22.3 | BB80: 22.4 | BC80: 22.6 | BD80: 22.4 | BE80: 22.5 | BF80: 22.6 | BG80: 22.5 | BH80: 22.4 | BI80: 22.5 | BJ80: 22.4 | BK80: 22.4 | BL80: 22.3 | BM80: 22.3 | BN80: 22.3 | BO80: 22.4 | BP80: 22.5
A81: Fiji | B81: FJI | C81: Income share held by fourth 20% | D81: SI.DST.04TH.20 | AU81: 21.7 | BA81: 20.5 | BF81: 21.3 | BL81: 22.5
A82: France | B82: FRA | C82: Income share held by fourth 20% | D82: SI.DST.04TH.20 | O82: 22.3 | T82: 22.3 | X82: 22.5 | AC82: 22.5 | AI82: 22.6 | AO82: 23 | AP82: 22.9 | AQ82: 22.8 | AR82: 22.6 | AS82: 22.6 | AT82: 22.5 | AU82: 22.6 | AV82: 22.3 | AW82: 22.4 | AX82: 22.5 | AY82: 22.7 | AZ82: 21.9 | BA82: 21.9 | BB82: 22.1 | BC82: 21.8 | BD82: 21.8 | BE82: 21.8 | BF82: 21.8 | BG82: 22 | BH82: 21.7 | BI82: 22 | BJ82: 21.9 | BK82: 21.6 | BL82: 22.4 | BM82: 22.4 | BN82: 22.5 | BO82: 22.6 | BP82: 22.5
A83: Faroe Islands | B83: FRO | C83: Income share held by fourth 20% | D83: SI.DST.04TH.20
A84: Micronesia, Fed. Sts. | B84: FSM | C84: Income share held by fourth 20% | D84: SI.DST.04TH.20 | AX84: 21.3 | BF84: 22.5
A85: Gabon | B85: GAB | C85: Income share held by fourth 20% | D85: SI.DST.04TH.20 | AX85: 21.1 | BJ85: 23
A86: United Kingdom | B86: GBR | C86: Income share held by fourth 20% | D86: SI.DST.04TH.20 | M86: 22.5 | N86: 22.4 | O86: 22.4 | P86: 22.4 | Q86: 22.8 | R86: 22.5 | S86: 22.4 | T86: 22.6 | U86: 22.8 | V86: 22.7 | W86: 22.9 | X86: 22.8 | Y86: 22.6 | Z86: 22.6 | AA86: 22.6 | AB86: 22.6 | AC86: 22.7 | AD86: 22.8 | AE86: 22.5 | AF86: 22.2 | AG86: 22.2 | AH86: 22.8 | AI86: 22.7 | AJ86: 22.7 | AK86: 22.7 | AL86: 22.8 | AM86: 22.4 | AN86: 22.5 | AO86: 22.5 | AP86: 22.4 | AQ86: 22.2 | AR86: 22.2 | AS86: 21.3 | AT86: 21.8 | AU86: 22.1 | AV86: 22.3 | AW86: 22.3 | AX86: 22.2 | AY86: 22 | AZ86: 22.6 | BA86: 22.3 | BB86: 22.3 | BC86: 22.4 | BD86: 22.6 | BE86: 22.6 | BF86: 22.8 | BG86: 22.8 | BH86: 22.8 | BI86: 22.8 | BJ86: 23 | BK86: 22.8 | BL86: 23 | BM86: 23 | BN86: 23
A87: Georgia | B87: GEO | C87: Income share held by fourth 20% | D87: SI.DST.04TH.20 | AO87: 22.7 | AP87: 22.8 | AQ87: 22.2 | AR87: 22.5 | AS87: 22.4 | AT87: 22.1 | AU87: 22.4 | AV87: 23 | AW87: 23.1 | AX87: 22.8 | AY87: 22.8 | AZ87: 22.4 | BA87: 22.3 | BB87: 22.5 | BC87: 22.5 | BD87: 22.3 | BE87: 22.4 | BF87: 22.5 | BG87: 22.3 | BH87: 22.6 | BI87: 22.2 | BJ87: 22.4 | BK87: 22.6 | BL87: 22.4 | BM87: 22.9 | BN87: 22.5 | BO87: 23.2 | BP87: 22.4 | BQ87: 22.5
A88: Ghana | B88: GHA | C88: Income share held by fourth 20% | D88: SI.DST.04TH.20 | AF88: 22.3 | AG88: 22.1 | AJ88: 21.7 | AQ88: 22.7 | AX88: 21.6 | BE88: 21.9 | BI88: 22.3
A89: Gibraltar | B89: GIB | C89: Income share held by fourth 20% | D89: SI.DST.04TH.20
A90: Guinea | B90: GIN | C90: Income share held by fourth 20% | D90: SI.DST.04TH.20 | AJ90: 23.7 | AM90: 20.6 | AU90: 20.9 | AZ90: 22 | BE90: 22.4 | BK90: 22.9
A91: Gambia, The | B91: GMB | C91: Income share held by fourth 20% | D91: SI.DST.04TH.20 | AQ91: 20.3 | AV91: 20.7 | BC91: 20.5 | BH91: 21.8 | BM91: 21.8
A92: Guinea-Bissau | B92: GNB | C92: Income share held by fourth 20% | D92: SI.DST.04TH.20 | AJ92: 20.4 | AL92: 21 | AU92: 22 | BC92: 18.3 | BK92: 21.8 | BN92: 22.4
A93: Equatorial Guinea | B93: GNQ | C93: Income share held by fourth 20% | D93: SI.DST.04TH.20 | BO93: 22.3
A94: Greece | B94: GRC | C94: Income share held by fourth 20% | D94: SI.DST.04TH.20 | AN94: 23 | AS94: 23.1 | AU94: 22.6 | AV94: 23.3 | AW94: 23 | AX94: 22.7 | AY94: 22.6 | AZ94: 22.6 | BA94: 22.5 | BB94: 22.5 | BC94: 22.9 | BD94: 23.3 | BE94: 23.2 | BF94: 23.2 | BG94: 23.3 | BH94: 23.5 | BI94: 23.2 | BJ94: 23 | BK94: 23.1 | BL94: 23.1 | BM94: 23 | BN94: 23.1 | BO94: 22.7 | BP94: 22.5
A95: Grenada | B95: GRD | C95: Income share held by fourth 20% | D95: SI.DST.04TH.20 | BK95: 20.9
A96: Greenland | B96: GRL | C96: Income share held by fourth 20% | D96: SI.DST.04TH.20
A97: Guatemala | B97: GTM | C97: Income share held by fourth 20% | D97: SI.DST.04TH.20 | AE97: 20.2 | AH97: 19.1 | AQ97: 21.3 | AS97: 18.5 | AY97: 19.2 | BG97: 20.1 | BP97: 21.4
A98: Guam | B98: GUM | C98: Income share held by fourth 20% | D98: SI.DST.04TH.20
A99: Guyana | B99: GUY | C99: Income share held by fourth 20% | D99: SI.DST.04TH.20 | AK99: 23.2 | AQ99: 21.3
A100: High income | B100: HIC | C100: Income share held by fourth 20% | D100: SI.DST.04TH.20
A101: Hong Kong SAR, China | B101: HKG | C101: Income share held by fourth 20% | D101: SI.DST.04TH.20
...

Sheet highest_20
A1: Data Source | B1: World Development Indicators
A2: Last Updated Date | B2: 46007
A4: Country Name | B4: Country Code | C4: Indicator Name | D4: Indicator Code | E4: 1960 | F4: 1961 | G4: 1962 | H4: 1963 | I4: 1964 | J4: 1965 | K4: 1966 | L4: 1967 | M4: 1968 | N4: 1969 | O4: 1970 | P4: 1971 | Q4: 1972 | R4: 1973 | S4: 1974 | T4: 1975 | U4: 1976 | V4: 1977 | W4: 1978 | X4: 1979 | Y4: 1980 | Z4: 1981 | AA4: 1982 | AB4: 1983 | AC4: 1984 | AD4: 1985 | AE4: 1986 | AF4: 1987 | AG4: 1988 | AH4: 1989 | AI4: 1990 | AJ4: 1991 | AK4: 1992 | AL4: 1993 | AM4: 1994 | AN4: 1995 | AO4: 1996 | AP4: 1997 | AQ4: 1998 | AR4: 1999 | AS4: 2000 | AT4: 2001 | AU4: 2002 | AV4: 2003 | AW4: 2004 | AX4: 2005 | AY4: 2006 | AZ4: 2007 | BA4: 2008 | BB4: 2009 | BC4: 2010 | BD4: 2011 | BE4: 2012 | BF4: 2013 | BG4: 2014 | BH4: 2015 | BI4: 2016 | BJ4: 2017 | BK4: 2018 | BL4: 2019 | BM4: 2020 | BN4: 2021 | BO4: 2022 | BP4: 2023 | BQ4: 2024
A5: Aruba | B5: ABW | C5: Income share held by highest 20% | D5: SI.DST.05TH.20
A6: Africa Eastern and Southern | B6: AFE | C6: Income share held by highest 20% | D6: SI.DST.05TH.20
A7: Afghanistan | B7: AFG | C7: Income share held by highest 20% | D7: SI.DST.05TH.20
A8: Africa Western and Central | B8: AFW | C8: Income share held by highest 20% | D8: SI.DST.05TH.20
A9: Angola | B9: AGO | C9: Income share held by highest 20% | D9: SI.DST.05TH.20 | AS9: 56.1 | BA9: 48.5 | BK9: 55.6
A10: Albania | B10: ALB | C10: Income share held by highest 20% | D10: SI.DST.05TH.20 | AO10: 36 | AU10: 40.3 | AX10: 39.2 | BA10: 39 | BE10: 37.8 | BG10: 41.7 | BH10: 40.6 | BI10: 41.2 | BJ10: 40.7 | BK10: 38.2 | BL10: 38.8 | BM10: 38
A11: Andorra | B11: AND | C11: Income share held by highest 20% | D11: SI.DST.05TH.20
A12: Arab World | B12: ARB | C12: Income share held by highest 20% | D12: SI.DST.05TH.20
A13: United Arab Emirates | B13: ARE | C13: Income share held by highest 20% | D13: SI.DST.05TH.20 | BF13: 38.2 | BK13: 34.8
A14: Argentina | B14: ARG | C14: Income share held by highest 20% | D14: SI.DST.05TH.20 | Y14: 46.6 | AE14: 48.5 | AF14: 50.6 | AJ14: 52.5 | AK14: 50.8 | AL14: 49.9 | AM14: 50.9 | AN14: 53.8 | AO14: 54 | AP14: 53.6 | AQ14: 55.1 | AR14: 54.1 | AS14: 55.1 | AT14: 57 | AU14: 57.8 | AV14: 55 | AW14: 52.6 | AX14: 52.1 | AY14: 50.7 | AZ14: 50.7 | BA14: 49.5 | BB14: 48.4 | BC14: 48.6 | BD14: 47.9 | BE14: 46.6 | BF14: 46.2 | BG14: 47 | BI14: 47.5 | BJ14: 46.7 | BK14: 46.9 | BL14: 48.3 | BM14: 47.7 | BN14: 47.8 | BO14: 46.6 | BP14: 47.8 | BQ14: 47.9
A15: Armenia | B15: ARM | C15: Income share held by highest 20% | D15: SI.DST.05TH.20 | AO15: 50.6 | AR15: 44.2 | AT15: 43.9 | AU15: 43.5 | AV15: 42.2 | AW15: 45.8 | AX15: 44.7 | AY15: 38.8 | AZ15: 40 | BA15: 38.4 | BB15: 37.5 | BC15: 39.4 | BD15: 38.6 | BE15: 38.7 | BF15: 39.4 | BG15: 40.1 | BH15: 40.7 | BI15: 40.2 | BJ15: 42.4 | BK15: 43 | BL15: 39.2 | BM15: 35.5 | BN15: 37.7 | BO15: 37.3 | BP15: 36.9
A16: American Samoa | B16: ASM | C16: Income share held by highest 20% | D16: SI.DST.05TH.20
A17: Antigua and Barbuda | B17: ATG | C17: Income share held by highest 20% | D17: SI.DST.05TH.20
A18: Australia | B18: AUS | C18: Income share held by highest 20% | D18: SI.DST.05TH.20 | Z18: 38.8 | AD18: 40.2 | AH18: 40.2 | AN18: 40 | AT18: 40.6 | AV18: 40.6 | AW18: 40.6 | BA18: 42.7 | BC18: 42 | BG18: 41.9 | BI18: 40.8 | BK18: 41.5 | BM18: 41
A19: Austria | B19: AUT | C19: Income share held by highest 20% | D19: SI.DST.05TH.20 | AM19: 38.7 | AN19: 37.9 | AO19: 37.7 | AP19: 37.3 | AQ19: 39.4 | AR19: 38 | AS19: 37.4 | AV19: 38 | AW19: 38.5 | AX19: 37.5 | AY19: 38.3 | AZ19: 38.7 | BA19: 38.6 | BB19: 39.3 | BC19: 38.4 | BD19: 38.7 | BE19: 38.4 | BF19: 38.9 | BG19: 38.7 | BH19: 38.4 | BI19: 38.6 | BJ19: 37.8 | BK19: 38.7 | BL19: 38.2 | BM19: 37.8 | BN19: 38.4 | BO19: 38.9 | BP19: 39
A20: Azerbaijan | B20: AZE | C20: Income share held by highest 20% | D20: SI.DST.05TH.20 | AN20: 42 | AT20: 44.5 | AU20: 36.7 | AV20: 37.4 | AW20: 37.8 | AX20: 37.8
A21: Burundi | B21: BDI | C21: Income share held by highest 20% | D21: SI.DST.05TH.20 | AK21: 41.6 | AQ21: 47.8 | AY21: 42.9 | BF21: 46.3 | BM21: 45
A22: Belgium | B22: BEL | C22: Income share held by highest 20% | D22: SI.DST.05TH.20 | AD22: 34.6 | AG22: 35 | AK22: 34.2 | AN22: 37 | AP22: 35.8 | AS22: 41.4 | AV22: 37 | AW22: 39.2 | AX22: 38.2 | AY22: 36.9 | AZ22: 38 | BA22: 37.2 | BB22: 37.2 | BC22: 37.2 | BD22: 36.8 | BE22: 36.4 | BF22: 36.4 | BG22: 36.9 | BH22: 36.5 | BI22: 36.4 | BJ22: 36.3 | BK22: 36.4 | BL22: 36.5 | BM22: 35.5 | BN22: 36 | BO22: 36.1 | BP22: 36.3
A23: Benin | B23: BEN | C23: Income share held by highest 20% | D23: SI.DST.05TH.20 | AV23: 46.2 | BD23: 50.7 | BH23: 52.1 | BK23: 45.5 | BN23: 42.3
A24: Burkina Faso | B24: BFA | C24: Income share held by highest 20% | D24: SI.DST.05TH.20 | AM24: 55 | AQ24: 56.5 | AV24: 49.7 | BB24: 47.1 | BG24: 44.3 | BK24: 50.3 | BN24: 45.3
A25: Bangladesh | B25: BGD | C25: Income share held by highest 20% | D25: SI.DST.05TH.20 | AB25: 35.8 | AD25: 37.2 | AG25: 38.6 | AJ25: 37.4 | AN25: 42.4 | AS25: 42.7 | AX25: 42.5 | BC25: 41.5 | BI25: 41.4 | BO25: 40.1
A26: Bulgaria | B26: BGR | C26: Income share held by highest 20% | D26: SI.DST.05TH.20 | AH26: 34 | AK26: 39.3 | AM26: 34.8 | AN26: 40.9 | AP26: 36.8 | AT26: 40 | AV26: 38 | AY26: 41.7 | AZ26: 43 | BA26: 41 | BB26: 40.9 | BC26: 42.2 | BD26: 41.1 | BE26: 42.7 | BF26: 42.8 | BG26: 43.9 | BH26: 44.3 | BI26: 46.3 | BJ26: 46.6 | BK26: 47.6 | BL26: 46.6 | BM26: 47.4 | BN26: 45.6 | BO26: 45.1 | BP26: 46.2
A27: Bahrain | B27: BHR | C27: Income share held by highest 20% | D27: SI.DST.05TH.20
A28: Bahamas, The | B28: BHS | C28: Income share held by highest 20% | D28: SI.DST.05TH.20
A29: Bosnia and Herzegovina | B29: BIH | C29: Income share held by highest 20% | D29: SI.DST.05TH.20 | AT29: 38.8 | AW29: 41.8 | AZ29: 40.7 | BD29: 40.7
A30: Belarus | B30: BLR | C30: Income share held by highest 20% | D30: SI.DST.05TH.20 | AL30: 32.9 | AN30: 37.4 | AQ30: 40.1 | AR30: 39.4 | AS30: 39.1 | AT30: 38.9 | AU30: 38.8 | AV30: 37.6 | AW30: 35.9 | AX30: 36.5 | AY30: 37.1 | AZ30: 38.4 | BA30: 36.8 | BB30: 37 | BC30: 37.5 | BD30: 36.3 | BE30: 36.1 | BF30: 36.2 | BG30: 36.7 | BH30: 35.4 | BI30: 35.4 | BJ30: 35.5 | BK30: 35.5 | BL30: 35.4 | BM30: 34.8
A31: Belize | B31: BLZ | C31: Income share held by highest 20% | D31: SI.DST.05TH.20 | AL31: 64.3 | AM31: 65.4 | AN31: 60.9 | AO31: 61.3 | AP31: 64.1 | AQ31: 59.3 | AR31: 57.7 | BK31: 46.3
A32: Bermuda | B32: BMU | C32: Income share held by highest 20% | D32: SI.DST.05TH.20
A33: Bolivia | B33: BOL | C33: Income share held by highest 20% | D33: SI.DST.05TH.20 | AI33: 48.2 | AK33: 54.7 | AP33: 61.7 | AR33: 60.5 | AS33: 64.1 | AT33: 60.6 | AU33: 62.3 | AW33: 59.5 | AX33: 61.9 | AY33: 60.1 | AZ33: 58.7 | BA33: 54.8 | BB33: 53.2 | BD33: 50.6 | BE33: 50.6 | BF33: 51.9 | BG33: 52.3 | BH33: 51.1 | BI33: 49.4 | BJ33: 49 | BK33: 47.5 | BL33: 47.3 | BM33: 49 | BN33: 46.7 | BO33: 46.7 | BP33: 47.7
A34: Brazil | B34: BRA | C34: Income share held by highest 20% | D34: SI.DST.05TH.20 | Z34: 62.3 | AA34: 62.7 | AB34: 63.4 | AC34: 62.9 | AD34: 60 | AE34: 62.8 | AF34: 63.7 | AG34: 65.5 | AH34: 67.3 | AI34: 64.6 | AK34: 57.1 | AL34: 64.2 | AN34: 63.8 | AO34: 63.9 | AP34: 63.8 | AQ34: 63.8 | AR34: 63.3 | AT34: 62.5 | AU34: 62.4 | AV34: 61.8 | AW34: 60.8 | AX34: 60.7 | AY34: 60.1 | AZ34: 59.3 | BA34: 58.6 | BB34: 58.2 | BD34: 57.5 | BE34: 58.1 | BF34: 57.5 | BG34: 56.9 | BH34: 56.7 | BI34: 58 | BJ34: 57.8 | BK34: 58.3 | BL34: 57.8 | BM34: 54.7 | BN34: 57.5 | BO34: 56.9 | BP34: 56.6
A35: Barbados | B35: BRB | C35: Income share held by highest 20% | D35: SI.DST.05TH.20 | BI35: 41.2
A36: Brunei Darussalam | B36: BRN | C36: Income share held by highest 20% | D36: SI.DST.05TH.20
A37: Bhutan | B37: BTN | C37: Income share held by highest 20% | D37: SI.DST.05TH.20 | AV37: 47.9 | AZ37: 45.1 | BE37: 46 | BJ37: 44.4 | BO37: 37.3
A38: Botswana | B38: BWA | C38: Income share held by highest 20% | D38: SI.DST.05TH.20 | AD38: 58.9 | AL38: 64.3 | AU38: 66.5 | BB38: 61.7 | BH38: 59.9
A39: Central African Republic | B39: CAF | C39: Income share held by highest 20% | D39: SI.DST.05TH.20 | AK39: 64.3 | BA39: 60.8 | BN39: 49.2
A40: Canada | B40: CAN | C40: Income share held by highest 20% | D40: SI.DST.05TH.20 | P40: 43 | R40: 41.2 | T40: 40.6 | V40: 40.1 | X40: 40 | Z40: 39.8 | AA40: 39.9 | AC40: 40.3 | AD40: 40.1 | AE40: 38.9 | AF40: 39 | AG40: 38.6 | AH40: 38.3 | AI40: 38.5 | AJ40: 39 | AK40: 38.8 | AL40: 38.8 | AM40: 38.6 | AN40: 38.7 | AO40: 39.9 | AP40: 40.3 | AQ40: 40.3 | AR40: 40.1 | AS40: 40.4 | AT40: 40.6 | AU40: 40.5 | AV40: 40.7 | AW40: 40.6 | AX40: 40.5 | AY40: 41 | AZ40: 40.9 | BA40: 40.9 | BB40: 40.8 | BC40: 40.6 | BD40: 39.9 | BE40: 40.2 | BF40: 40.3 | BG40: 40.1 | BH40: 40.5 | BI40: 39.8 | BJ40: 40.3 | BK40: 39.7 | BL40: 39.1 | BM40: 38.1 | BN40: 39.1
A41: Central Europe and the Baltics | B41: CEB | C41: Income share held by highest 20% | D41: SI.DST.05TH.20
A42: Switzerland | B42: CHE | C42: Income share held by highest 20% | D42: SI.DST.05TH.20 | AA42: 43.2 | AK42: 41 | AS42: 40.9 | AU42: 39.3 | AW42: 39.2 | AY42: 41.4 | AZ42: 41.8 | BA42: 41.3 | BB42: 40.6 | BC42: 40.4 | BD42: 39.7 | BE42: 39.8 | BF42: 40.5 | BG42: 40.5 | BH42: 40.2 | BI42: 40.8 | BJ42: 40.6 | BK42: 40.8 | BL42: 41.6 | BM42: 41.5 | BN42: 41.5 | BO42: 41.5
A43: Channel Islands | B43: CHI | C43: Income share held by highest 20% | D43: SI.DST.05TH.20
A44: Chile | B44: CHL | C44: Income share held by highest 20% | D44: SI.DST.05TH.20 | AF44: 61.4 | AI44: 62.5 | AK44: 60.1 | AM44: 61.5 | AO44: 60.1 | AQ44: 60.7 | AS44: 58 | AV44: 56.8 | AY44: 53.8 | BB44: 53.8 | BD44: 53.4 | BF44: 53.6 | BH44: 52.1 | BJ44: 52 | BM44: 53.3 | BO44: 49.9
A45: China | B45: CHN | C45: Income share held by highest 20% | D45: SI.DST.05TH.20 | Z45: 37.2 | AC45: 36.1 | AF45: 37.5 | AI45: 40.8 | AL45: 42.2 | AO45: 42.9 | AR45: 45.6 | AU45: 47.9 | AX45: 47.1 | BA45: 48.4 | BC45: 49 | BD45: 48.1 | BE45: 47.8 | BF45: 46.3 | BG45: 45.8 | BH45: 45.4 | BI45: 45.3 | BJ45: 45.9 | BK45: 45.4 | BL45: 45.3 | BM45: 44.7 | BN45: 43.6 | BO45: 43.7
A46: Cote d'Ivoire | B46: CIV | C46: Income share held by highest 20% | D46: SI.DST.05TH.20 | AD46: 51.2 | AE46: 45.4 | AF46: 47.5 | AG46: 43.8 | AK46: 45.8 | AN46: 47.4 | AQ46: 46.2 | AU46: 48.5 | BA46: 49 | BH46: 47.7 | BK46: 44.7 | BN46: 43.3
A47: Cameroon | B47: CMR | C47: Income share held by highest 20% | D47: SI.DST.05TH.20 | AO47: 51.7 | AT47: 49 | AZ47: 49.1 | BG47: 51.7 | BN47: 47.9
A48: Congo, Dem. Rep. | B48: COD | C48: Income share held by highest 20% | D48: SI.DST.05TH.20 | AW48: 48.3 | BE48: 48.4 | BM48: 51.1
A49: Congo, Rep. | B49: COG | C49: Income share held by highest 20% | D49: SI.DST.05TH.20 | AX49: 53.2 | BD49: 53.7
A50: Colombia | B50: COL | C50: Income share held by highest 20% | D50: SI.DST.05TH.20 | Y50: 59 | AG50: 57.3 | AH50: 57.3 | AJ50: 55.8 | AK50: 56.6 | AO50: 60.7 | AR50: 62.3 | AS50: 62.1 | AT50: 61.4 | AU50: 60.6 | AV50: 58.6 | AW50: 60 | AX50: 59 | BA50: 59.7 | BB50: 58.8 | BC50: 59.2 | BD50: 58.2 | BE50: 57.3 | BF50: 57.3 | BG50: 57.2 | BH50: 55.8 | BI50: 55.5 | BJ50: 54.8 | BK50: 55.4 | BL50: 56.1 | BM50: 57.9 | BN50: 59.8 | BO50: 59.6 | BP50: 58.7
A51: Comoros | B51: COM | C51: Income share held by highest 20% | D51: SI.DST.05TH.20 | AW51: 61.4 | BG51: 50.3
A52: Cabo Verde | B52: CPV | C52: Income share held by highest 20% | D52: SI.DST.05TH.20 | AT52: 58 | AZ52: 53.3 | BH52: 48.7
A53: Costa Rica | B53: CRI | C53: Income share held by highest 20% | D53: SI.DST.05TH.20 | Z53: 51.4 | AE53: 39.6 | AH53: 49.9 | AI53: 49.6 | AJ53: 50.8 | AK53: 50.3 | AL53: 50.5 | AM53: 51.5 | AN53: 50.3 | AO53: 51.1 | AP53: 50.6 | AQ53: 50.8 | AR53: 52.6 | AS53: 52.1 | AT53: 56.2 | AU53: 56.7 | AV53: 54 | AW53: 53.4 | AX53: 52.8 | AY53: 54.7 | AZ53: 55 | BA53: 54.1 | BB53: 55.9 | BC53: 53.6 | BD53: 53.9 | BE53: 53.6 | BF53: 54.2 | BG53: 53.9 | BH53: 53.9 | BI53: 54 | BJ53: 54 | BK53: 53.3 | BL53: 53.7 | BM53: 54.4 | BN53: 54.1 | BO53: 52.7 | BP53: 52.1 | BQ53: 51.1
A54: Caribbean small states | B54: CSS | C54: Income share held by highest 20% | D54: SI.DST.05TH.20
A55: Cuba | B55: CUB | C55: Income share held by highest 20% | D55: SI.DST.05TH.20
A56: Curacao | B56: CUW | C56: Income share held by highest 20% | D56: SI.DST.05TH.20
A57: Cayman Islands | B57: CYM | C57: Income share held by highest 20% | D57: SI.DST.05TH.20
A58: Cyprus | B58: CYP | C58: Income share held by highest 20% | D58: SI.DST.05TH.20 | AW58: 39 | AX58: 39.3 | AY58: 40.1 | AZ58: 40 | BA58: 40.6 | BB58: 40.8 | BC58: 40.4 | BD58: 41.3 | BE58: 42.7 | BF58: 45.1 | BG58: 43.6 | BH58: 42.1 | BI58: 41.4 | BJ58: 40.2 | BK58: 41.4 | BL58: 40.1 | BM58: 40.6 | BN58: 40.1 | BO58: 40.4 | BP58: 40.6
A59: Czechia | B59: CZE | C59: Income share held by highest 20% | D59: SI.DST.05TH.20 | AK59: 32.3 | AL59: 37.3 | AO59: 35.7 | AU59: 36.2 | AW59: 37 | AX59: 36.7 | AY59: 36.5 | AZ59: 36.2 | BA59: 36.5 | BB59: 36.2 | BC59: 36.4 | BD59: 36.2 | BE59: 36.1 | BF59: 36.4 | BG59: 36 | BH59: 35.9 | BI59: 35.8 | BJ59: 35.4 | BK59: 35.5 | BL59: 35.7 | BM59: 36.5 | BN59: 36.3 | BO59: 36 | BP59: 35.5
A60: Germany | B60: DEU | C60: Income share held by highest 20% | D60: SI.DST.05TH.20 | AJ60: 37.9 | AK60: 37.7 | AL60: 37.3 | AM60: 37.4 | AN60: 37.2 | AO60: 36.8 | AP60: 36.9 | AQ60: 36.9 | AR60: 37.6 | AS60: 37.5 | AT60: 38.5 | AU60: 38.2 | AV60: 38.3 | AW60: 38.6 | AX60: 39.8 | AY60: 39.3 | AZ60: 39.5 | BA60: 39.1 | BB60: 38.6 | BC60: 38.6 | BD60: 39 | BE60: 39.1 | BF60: 39.5 | BG60: 38.7 | BH60: 39.4 | BI60: 39.1 | BJ60: 39 | BK60: 39.7 | BL60: 39.5 | BM60: 40
A61: Djibouti | B61: DJI | C61: Income share held by highest 20% | D61: SI.DST.05TH.20 | AU61: 46.5 | BE61: 50.3 | BF61: 49.9 | BJ61: 47.6
A62: Dominica | B62: DMA | C62: Income share held by highest 20% | D62: SI.DST.05TH.20
A63: Denmark | B63: DNK | C63: Income share held by highest 20% | D63: SI.DST.05TH.20 | AF63: 35.4 | AK63: 34.2 | AN63: 33.3 | AS63: 33.9 | AV63: 35.5 | AW63: 34.9 | AX63: 35.1 | AY63: 35.8 | AZ63: 36.1 | BA63: 35.2 | BB63: 36.1 | BC63: 36.7 | BD63: 36.8 | BE63: 37.3 | BF63: 37.9 | BG63: 37.7 | BH63: 37.7 | BI63: 37.6 | BJ63: 38 | BK63: 37.7 | BL63: 37.3 | BM63: 37 | BN63: 37.8 | BO63: 38.4 | BP63: 39.2
A64: Dominican Republic | B64: DOM | C64: Income share held by highest 20% | D64: SI.DST.05TH.20 | AE64: 52.4 | AH64: 55.5 | AK64: 56.2 | AO64: 52.7 | AP64: 53.7 | AS64: 56.2 | AT64: 55.2 | AU64: 54.4 | AV64: 57.1 | AW64: 57.1 | AX64: 55.3 | AY64: 57 | AZ64: 54.4 | BA64: 53.6 | BB64: 54.6 | BC64: 52.9 | BD64: 53.2 | BE64: 52 | BF64: 53.6 | BG64: 50.2 | BH64: 51.1 | BI64: 51.5 | BJ64: 48.9 | BK64: 50.1 | BL64: 48.6 | BM64: 46.5 | BN64: 45.7 | BO64: 44 | BP64: 44.9 | BQ64: 45.4
A65: Algeria | B65: DZA | C65: Income share held by highest 20% | D65: SI.DST.05TH.20 | AG65: 44.6 | AN65: 42.6 | BD65: 37.2
A66: East Asia & Pacific (excluding high income) | B66: EAP | C66: Income share held by highest 20% | D66: SI.DST.05TH.20
A67: Early-demographic dividend | B67: EAR | C67: Income share held by highest 20% | D67: SI.DST.05TH.20
A68: East Asia & Pacific | B68: EAS | C68: Income share held by highest 20% | D68: SI.DST.05TH.20
A69: Europe & Central Asia (excluding high income) | B69: ECA | C69: Income share held by highest 20% | D69: SI.DST.05TH.20
A70: Europe & Central Asia | B70: ECS | C70: Income share held by highest 20% | D70: SI.DST.05TH.20
A71: Ecuador | B71: ECU | C71: Income share held by highest 20% | D71: SI.DST.05TH.20 | AF71: 54.4 | AM71: 57.9 | AN71: 56 | AQ71: 54.8 | AR71: 62.5 | AS71: 60.7 | AV71: 58.1 | AW71: 58.3 | AX71: 57.5 | AY71: 57 | AZ71: 58 | BA71: 54.6 | BB71: 53.5 | BC71: 53.9 | BD71: 51 | BE71: 51.1 | BF71: 52.2 | BG71: 50.6 | BH71: 51.3 | BI71: 50.5 | BJ71: 50.1 | BK71: 51 | BL71: 51 | BM71: 52.3 | BN71: 51.3 | BO71: 50.9 | BP71: 49.8 | BQ71: 50
A72: Egypt, Arab Rep. | B72: EGY | C72: Income share held by highest 20% | D72: SI.DST.05TH.20 | AI72: 41.1 | AN72: 40 | AR72: 40.4 | AW72: 41.4 | BA72: 40.8 | BC72: 40.1 | BE72: 38.6 | BH72: 41.5 | BJ72: 41 | BL72: 41.3 | BN72: 38.6
A73: Euro area | B73: EMU | C73: Income share held by highest 20% | D73: SI.DST.05TH.20
A74: Eritrea | B74: ERI | C74: Income share held by highest 20% | D74: SI.DST.05TH.20
A75: Spain | B75: ESP | C75: Income share held by highest 20% | D75: SI.DST.05TH.20 | Y75: 41.4 | AD75: 41.7 | AI75: 39.6 | AL75: 42.1 | AM75: 41.5 | AN75: 42.2 | AO75: 42.5 | AP75: 41.7 | AQ75: 41.1 | AR75: 40.9 | AS75: 41 | AV75: 39.1 | AW75: 40.3 | AX75: 39.6 | AY75: 40.4 | AZ75: 41 | BA75: 41 | BB75: 41.5 | BC75: 41.7 | BD75: 41.8 | BE75: 41.6 | BF75: 41.9 | BG75: 41.9 | BH75: 42.1 | BI75: 41.7 | BJ75: 41 | BK75: 41 | BL75: 40.6 | BM75: 41 | BN75: 40.4 | BO75: 40.4 | BP75: 40.2
A76: Estonia | B76: EST | C76: Income share held by highest 20% | D76: SI.DST.05TH.20 | AL76: 46.4 | AN76: 38.2 | AQ76: 45.1 | AS76: 43.1 | AT76: 43.4 | AU76: 43.1 | AV76: 44.2 | AW76: 41.2 | AX76: 41.3 | AY76: 41.7 | AZ76: 39.3 | BA76: 40.1 | BB76: 39.6 | BC76: 39.7 | BD76: 40.2 | BE76: 40.7 | BF76: 42.4 | BG76: 42.1 | BH76: 40.4 | BI76: 39.1 | BJ76: 38.3 | BK76: 38.3 | BL76: 38.9 | BM76: 39 | BN76: 39.9 | BO76: 40 | BP76: 39.3
A77: Ethiopia | B77: ETH | C77: Income share held by highest 20% | D77: SI.DST.05TH.20 | AN77: 51.6 | AR77: 39.4 | AW77: 39.3 | BC77: 41.7 | BH77: 43 | BN77: 39.7
A78: European Union | B78: EUU | C78: Income share held by highest 20% | D78: SI.DST.05TH.20
A79: Fragile and conflict affected situations | B79: FCS | C79: Income share held by highest 20% | D79: SI.DST.05TH.20
A80: Finland | B80: FIN | C80: Income share held by highest 20% | D80: SI.DST.05TH.20 | AF80: 32.7 | AJ80: 33.3 | AN80: 34.1 | AS80: 36.6 | AV80: 37.2 | AW80: 37.4 | AX80: 37.2 | AY80: 37.3 | AZ80: 37.6 | BA80: 37.2 | BB80: 36.9 | BC80: 37 | BD80: 37.1 | BE80: 36.7 | BF80: 36.6 | BG80: 36.4 | BH80: 36.7 | BI80: 36.6 | BJ80: 36.9 | BK80: 36.8 | BL80: 37.1 | BM80: 36.7 | BN80: 37.1 | BO80: 37.3 | BP80: 36.7
A81: Fiji | B81: FJI | C81: Income share held by highest 20% | D81: SI.DST.05TH.20 | AU81: 45.4 | BA81: 47.8 | BF81: 44.7 | BL81: 39.4
A82: France | B82: FRA | C82: Income share held by highest 20% | D82: SI.DST.05TH.20 | O82: 44.1 | T82: 43 | X82: 41.3 | AC82: 40.7 | AI82: 39.9 | AO82: 39.4 | AP82: 39.4 | AQ82: 39.3 | AR82: 40.1 | AS82: 40.2 | AT82: 40.1 | AU82: 39.7 | AV82: 39.8 | AW82: 39.2 | AX82: 38.5 | AY82: 38.3 | AZ82: 40.9 | BA82: 41.2 | BB82: 40.8 | BC82: 41.8 | BD82: 41.4 | BE82: 41.3 | BF82: 40.9 | BG82: 40.6 | BH82: 40.9 | BI82: 40.2 | BJ82: 40 | BK82: 40.8 | BL82: 39.2 | BM82: 38.8 | BN82: 39.4 | BO82: 39.2 | BP82: 39.7
A83: Faroe Islands | B83: FRO | C83: Income share held by highest 20% | D83: SI.DST.05TH.20
A84: Micronesia, Fed. Sts. | B84: FSM | C84: Income share held by highest 20% | D84: SI.DST.05TH.20 | AX84: 48.7 | BF84: 46
A85: Gabon | B85: GAB | C85: Income share held by highest 20% | D85: SI.DST.05TH.20 | AX85: 48.7 | BJ85: 44.4
A86: United Kingdom | B86: GBR | C86: Income share held by highest 20% | D86: SI.DST.05TH.20 | M86: 36.4 | N86: 37.2 | O86: 37.3 | P86: 38.3 | Q86: 37.5 | R86: 37.9 | S86: 37.9 | T86: 37 | U86: 36.8 | V86: 36.4 | W86: 36.3 | X86: 36.7 | Y86: 37.5 | Z86: 38.3 | AA86: 38.4 | AB86: 38.4 | AC86: 37.7 | AD86: 38.8 | AE86: 39.9 | AF86: 41.6 | AG86: 41.9 | AH86: 40.7 | AI86: 42.6 | AJ86: 42 | AK86: 42 | AL86: 41.9 | AM86: 42.9 | AN86: 42.5 | AO86: 42.2 | AP86: 42.6 | AQ86: 43.4 | AR86: 43.5 | AS86: 45.5 | AT86: 44 | AU86: 42.4 | AV86: 42 | AW86: 42.1 | AX86: 42.5 | AY86: 43 | AZ86: 41.5 | BA86: 42.4 | BB86: 42.2 | BC86: 41.2 | BD86: 40.6 | BE86: 40.6 | BF86: 40.2 | BG86: 40.5 | BH86: 40.5 | BI86: 40.3 | BJ86: 39.8 | BK86: 40.8 | BL86: 39.9 | BM86: 40 | BN86: 39.7
A87: Georgia | B87: GEO | C87: Income share held by highest 20% | D87: SI.DST.05TH.20 | AO87: 43.6 | AP87: 46.1 | AQ87: 46.6 | AR87: 45.9 | AS87: 46.2 | AT87: 45.8 | AU87: 43.9 | AV87: 43.2 | AW87: 42.6 | AX87: 43.8 | AY87: 43.5 | AZ87: 44.6 | BA87: 45 | BB87: 44.7 | BC87: 45.5 | BD87: 45.7 | BE87: 45.3 | BF87: 44.9 | BG87: 44.3 | BH87: 43.4 | BI87: 43.7 | BJ87: 44.5 | BK87: 43.2 | BL87: 42.9 | BM87: 41.5 | BN87: 41.5 | BO87: 40.6 | BP87: 42.1 | BQ87: 41.5
A88: Ghana | B88: GHA | C88: Income share held by highest 20% | D88: SI.DST.05TH.20 | AF88: 42.7 | AG88: 43.4 | AJ88: 45.5 | AQ88: 46.2 | AX88: 48.6 | BE88: 48.3 | BI88: 48.6
A89: Gibraltar | B89: GIB | C89: Income share held by highest 20% | D89: SI.DST.05TH.20
A90: Guinea | B90: GIN | C90: Income share held by highest 20% | D90: SI.DST.05TH.20 | AJ90: 49.7 | AM90: 52 | AU90: 49.4 | AZ90: 46.2 | BE90: 41.5 | BK90: 38.2
A91: Gambia, The | B91: GMB | C91: Income share held by highest 20% | D91: SI.DST.05TH.20 | AQ91: 53.8 | AV91: 52.8 | BC91: 49.8 | BH91: 43.6 | BM91: 45.6
A92: Guinea-Bissau | B92: GNB | C92: Income share held by highest 20% | D92: SI.DST.05TH.20 | AJ92: 58.8 | AL92: 49.6 | AU92: 43.1 | BC92: 56.7 | BK92: 43 | BN92: 41.6
A93: Equatorial Guinea | B93: GNQ | C93: Income share held by highest 20% | D93: SI.DST.05TH.20 | BO93: 45.4
A94: Greece | B94: GRC | C94: Income share held by highest 20% | D94: SI.DST.05TH.20 | AN94: 42.9 | AS94: 41.1 | AU94: 42.2 | AV94: 40 | AW94: 40.7 | AX94: 41.7 | AY94: 42 | AZ94: 41.1 | BA94: 40.9 | BB94: 40.9 | BC94: 41 | BD94: 41 | BE94: 42.1 | BF94: 42.2 | BG94: 41.8 | BH94: 41.8 | BI94: 41.3 | BJ94: 41.1 | BK94: 40.1 | BL94: 40.1 | BM94: 40.5 | BN94: 40.1 | BO94: 40.7 | BP94: 40.8
A95: Grenada | B95: GRD | C95: Income share held by highest 20% | D95: SI.DST.05TH.20 | BK95: 50.4
A96: Greenland | B96: GRL | C96: Income share held by highest 20% | D96: SI.DST.05TH.20
A97: Guatemala | B97: GTM | C97: Income share held by highest 20% | D97: SI.DST.05TH.20 | AE97: 58.2 | AH97: 62.1 | AQ97: 53.9 | AS97: 59.1 | AY97: 58.8 | BG97: 53.6 | BP97: 50.6
A98: Guam | B98: GUM | C98: Income share held by highest 20% | D98: SI.DST.05TH.20
A99: Guyana | B99: GUY | C99: Income share held by highest 20% | D99: SI.DST.05TH.20 | AK99: 45.1 | AQ99: 50.1
A100: High income | B100: HIC | C100: Income share held by highest 20% | D100: SI.DST.05TH.20
A101: Hong Kong SAR, China | B101: HKG | C101: Income share held by highest 20% | D101: SI.DST.05TH.20
...

Sheet highest_10
A1: Data Source | B1: World Development Indicators
A2: Last Updated Date | B2: 46007
A4: Country Name | B4: Country Code | C4: Indicator Name | D4: Indicator Code | E4: 1960 | F4: 1961 | G4: 1962 | H4: 1963 | I4: 1964 | J4: 1965 | K4: 1966 | L4: 1967 | M4: 1968 | N4: 1969 | O4: 1970 | P4: 1971 | Q4: 1972 | R4: 1973 | S4: 1974 | T4: 1975 | U4: 1976 | V4: 1977 | W4: 1978 | X4: 1979 | Y4: 1980 | Z4: 1981 | AA4: 1982 | AB4: 1983 | AC4: 1984 | AD4: 1985 | AE4: 1986 | AF4: 1987 | AG4: 1988 | AH4: 1989 | AI4: 1990 | AJ4: 1991 | AK4: 1992 | AL4: 1993 | AM4: 1994 | AN4: 1995 | AO4: 1996 | AP4: 1997 | AQ4: 1998 | AR4: 1999 | AS4: 2000 | AT4: 2001 | AU4: 2002 | AV4: 2003 | AW4: 2004 | AX4: 2005 | AY4: 2006 | AZ4: 2007 | BA4: 2008 | BB4: 2009 | BC4: 2010 | BD4: 2011 | BE4: 2012 | BF4: 2013 | BG4: 2014 | BH4: 2015 | BI4: 2016 | BJ4: 2017 | BK4: 2018 | BL4: 2019 | BM4: 2020 | BN4: 2021 | BO4: 2022 | BP4: 2023 | BQ4: 2024
A5: Aruba | B5: ABW | C5: Income share held by highest 10% | D5: SI.DST.10TH.10
A6: Africa Eastern and Southern | B6: AFE | C6: Income share held by highest 10% | D6: SI.DST.10TH.10
A7: Afghanistan | B7: AFG | C7: Income share held by highest 10% | D7: SI.DST.10TH.10
A8: Africa Western and Central | B8: AFW | C8: Income share held by highest 10% | D8: SI.DST.10TH.10
A9: Angola | B9: AGO | C9: Income share held by highest 10% | D9: SI.DST.10TH.10 | AS9: 40.2 | BA9: 32.3 | BK9: 39.6
A10: Albania | B10: ALB | C10: Income share held by highest 10% | D10: SI.DST.10TH.10 | AO10: 20.7 | AU10: 25.3 | AX10: 24.3 | BA10: 24.4 | BE10: 22.9 | BG10: 25.5 | BH10: 24.8 | BI10: 25 | BJ10: 24.6 | BK10: 22.7 | BL10: 23.6 | BM10: 22.8
A11: Andorra | B11: AND | C11: Income share held by highest 10% | D11: SI.DST.10TH.10
A12: Arab World | B12: ARB | C12: Income share held by highest 10% | D12: SI.DST.10TH.10
A13: United Arab Emirates | B13: ARE | C13: Income share held by highest 10% | D13: SI.DST.10TH.10 | BF13: 21.4 | BK13: 20.5
A14: Argentina | B14: ARG | C14: Income share held by highest 10% | D14: SI.DST.10TH.10 | Y14: 30.2 | AE14: 32.2 | AF14: 34.2 | AJ14: 36.6 | AK14: 34.3 | AL14: 33.2 | AM14: 34.4 | AN14: 37 | AO14: 36.9 | AP14: 36.4 | AQ14: 38 | AR14: 37 | AS14: 37.7 | AT14: 39.5 | AU14: 40.5 | AV14: 37.7 | AW14: 35.3 | AX14: 35 | AY14: 33.8 | AZ14: 33.7 | BA14: 32.5 | BB14: 31.3 | BC14: 31.8 | BD14: 31 | BE14: 29.8 | BF14: 29.5 | BG14: 30.1 | BI14: 30.7 | BJ14: 30 | BK14: 30.1 | BL14: 31.3 | BM14: 30.6 | BN14: 31.2 | BO14: 29.8 | BP14: 31 | BQ14: 31.2
A15: Armenia | B15: ARM | C15: Income share held by highest 10% | D15: SI.DST.10TH.10 | AO15: 35.2 | AR15: 29.6 | AT15: 29.1 | AU15: 29 | AV15: 28.2 | AW15: 31.7 | AX15: 30.8 | AY15: 24.4 | AZ15: 25.1 | BA15: 23.7 | BB15: 22.9 | BC15: 25 | BD15: 24 | BE15: 24.5 | BF15: 24.7 | BG15: 25.7 | BH15: 26.7 | BI15: 25.3 | BJ15: 28.4 | BK15: 29.2 | BL15: 25.2 | BM15: 21.5 | BN15: 23.6 | BO15: 23 | BP15: 22.9
A16: American Samoa | B16: ASM | C16: Income share held by highest 10% | D16: SI.DST.10TH.10
A17: Antigua and Barbuda | B17: ATG | C17: Income share held by highest 10% | D17: SI.DST.10TH.10
A18: Australia | B18: AUS | C18: Income share held by highest 10% | D18: SI.DST.10TH.10 | Z18: 22.9 | AD18: 24.3 | AH18: 24.2 | AN18: 24.2 | AT18: 24.7 | AV18: 24.7 | AW18: 24.9 | BA18: 27.4 | BC18: 26.5 | BG18: 26.6 | BI18: 25.5 | BK18: 26.2 | BM18: 25.5
A19: Austria | B19: AUT | C19: Income share held by highest 10% | D19: SI.DST.10TH.10 | AM19: 23.6 | AN19: 23 | AO19: 22.8 | AP19: 22.4 | AQ19: 24.6 | AR19: 23.4 | AS19: 22.6 | AV19: 23.5 | AW19: 23.8 | AX19: 22.8 | AY19: 23.7 | AZ19: 23.8 | BA19: 24.1 | BB19: 24.7 | BC19: 23.6 | BD19: 23.7 | BE19: 23.4 | BF19: 24.3 | BG19: 24.1 | BH19: 23.8 | BI19: 23.8 | BJ19: 23 | BK19: 23.9 | BL19: 23.2 | BM19: 23.1 | BN19: 23.8 | BO19: 24.6 | BP19: 24.8
A20: Azerbaijan | B20: AZE | C20: Income share held by highest 10% | D20: SI.DST.10TH.10 | AN20: 26.8 | AT20: 29.5 | AU20: 23.2 | AV20: 23.6 | AW20: 24.4 | AX20: 24.2
A21: Burundi | B21: BDI | C21: Income share held by highest 10% | D21: SI.DST.10TH.10 | AK21: 26.6 | AQ21: 32.5 | AY21: 28 | BF21: 31 | BM21: 29.9
A22: Belgium | B22: BEL | C22: Income share held by highest 10% | D22: SI.DST.10TH.10 | AD22: 20.3 | AG22: 20.7 | AK22: 19.8 | AN22: 22.5 | AP22: 21.2 | AS22: 28 | AV22: 22.2 | AW22: 25.1 | AX22: 23.9 | AY22: 22.4 | AZ22: 23.5 | BA22: 22.7 | BB22: 22.7 | BC22: 22.7 | BD22: 22.3 | BE22: 21.9 | BF22: 21.8 | BG22: 22.4 | BH22: 22.2 | BI22: 22.2 | BJ22: 21.9 | BK22: 22.2 | BL22: 22.3 | BM22: 21.4 | BN22: 21.9 | BO22: 22.2 | BP22: 22.2
A23: Benin | B23: BEN | C23: Income share held by highest 10% | D23: SI.DST.10TH.10 | AV23: 31.1 | BD23: 34.5 | BH23: 37.6 | BK23: 30 | BN23: 27.2
A24: Burkina Faso | B24: BFA | C24: Income share held by highest 10% | D24: SI.DST.10TH.10 | AM24: 39.4 | AQ24: 42.7 | AV24: 33.8 | BB24: 32 | BG24: 29.6 | BK24: 35.3 | BN24: 30.2
A25: Bangladesh | B25: BGD | C25: Income share held by highest 10% | D25: SI.DST.10TH.10 | AB25: 21.9 | AD25: 23.4 | AG25: 24.6 | AJ25: 23.3 | AN25: 28.1 | AS25: 27.9 | AX25: 28 | BC25: 26.9 | BI25: 26.8 | BO25: 25.5
A26: Bulgaria | B26: BGR | C26: Income share held by highest 10% | D26: SI.DST.10TH.10 | AH26: 20 | AK26: 24.7 | AM26: 21 | AN26: 26.3 | AP26: 22.8 | AT26: 24.9 | AV26: 23.6 | AY26: 26.6 | AZ26: 27.9 | BA26: 25.7 | BB26: 25.7 | BC26: 26.9 | BD26: 26 | BE26: 27.4 | BF26: 27.6 | BG26: 28.8 | BH26: 28.7 | BI26: 31.4 | BJ26: 31.9 | BK26: 32.6 | BL26: 31.4 | BM26: 32.6 | BN26: 29.9 | BO26: 30.1 | BP26: 31.1
A27: Bahrain | B27: BHR | C27: Income share held by highest 10% | D27: SI.DST.10TH.10
A28: Bahamas, The | B28: BHS | C28: Income share held by highest 10% | D28: SI.DST.10TH.10
A29: Bosnia and Herzegovina | B29: BIH | C29: Income share held by highest 10% | D29: SI.DST.10TH.10 | AT29: 24.7 | AW29: 26.4 | AZ29: 25.1 | BD29: 25.1
A30: Belarus | B30: BLR | C30: Income share held by highest 10% | D30: SI.DST.10TH.10 | AL30: 19.4 | AN30: 22.6 | AQ30: 24.9 | AR30: 24 | AS30: 24 | AT30: 24 | AU30: 24 | AV30: 22.6 | AW30: 21.3 | AX30: 21.8 | AY30: 22.4 | AZ30: 23.6 | BA30: 22.3 | BB30: 22.6 | BC30: 22.8 | BD30: 21.9 | BE30: 21.8 | BF30: 22.1 | BG30: 22.6 | BH30: 21.2 | BI30: 21.3 | BJ30: 21.3 | BK30: 21.4 | BL30: 21.3 | BM30: 20.7
A31: Belize | B31: BLZ | C31: Income share held by highest 10% | D31: SI.DST.10TH.10 | AL31: 51.1 | AM31: 52.5 | AN31: 44.1 | AO31: 46.5 | AP31: 50.3 | AQ31: 43.7 | AR31: 42.4 | BK31: 30
A32: Bermuda | B32: BMU | C32: Income share held by highest 10% | D32: SI.DST.10TH.10
A33: Bolivia | B33: BOL | C33: Income share held by highest 10% | D33: SI.DST.10TH.10 | AI33: 31.7 | AK33: 39.2 | AP33: 45.4 | AR33: 42.6 | AS33: 47.8 | AT33: 44.1 | AU33: 46.6 | AW33: 43.9 | AX33: 45.3 | AY33: 43.6 | AZ33: 41.8 | BA33: 38.5 | BB33: 36.9 | BD33: 33.7 | BE33: 33.7 | BF33: 35.2 | BG33: 36 | BH33: 34.8 | BI33: 32.4 | BJ33: 32 | BK33: 30.6 | BL33: 30.8 | BM33: 32.6 | BN33: 30.3 | BO33: 30.4 | BP33: 31.3
A34: Brazil | B34: BRA | C34: Income share held by highest 10% | D34: SI.DST.10TH.10 | Z34: 45.9 | AA34: 46.2 | AB34: 46.8 | AC34: 46.5 | AD34: 42.5 | AE34: 46.6 | AF34: 47.4 | AG34: 49.2 | AH34: 51.1 | AI34: 48.1 | AK34: 39.7 | AL34: 48.4 | AN34: 47.5 | AO34: 47.3 | AP34: 47.4 | AQ34: 47.6 | AR34: 47 | AT34: 46.1 | AU34: 46.1 | AV34: 45.4 | AW34: 44.5 | AX34: 44.6 | AY34: 44.1 | AZ34: 43.2 | BA34: 42.5 | BB34: 42.2 | BD34: 41.7 | BE34: 42.4 | BF34: 41.7 | BG34: 41 | BH34: 40.9 | BI34: 42.1 | BJ34: 42 | BK34: 42.5 | BL34: 42 | BM34: 39.5 | BN34: 41.6 | BO34: 41 | BP34: 40.8
A35: Barbados | B35: BRB | C35: Income share held by highest 10% | D35: SI.DST.10TH.10 | BI35: 25.8
A36: Brunei Darussalam | B36: BRN | C36: Income share held by highest 10% | D36: SI.DST.10TH.10
A37: Bhutan | B37: BTN | C37: Income share held by highest 10% | D37: SI.DST.10TH.10 | AV37: 32.2 | AZ37: 29.4 | BE37: 30.7 | BJ37: 27.9 | BO37: 22.7
A38: Botswana | B38: BWA | C38: Income share held by highest 10% | D38: SI.DST.10TH.10 | AD38: 42.9 | AL38: 50.4 | AU38: 50 | BB38: 46.5 | BH38: 42.9
A39: Central African Republic | B39: CAF | C39: Income share held by highest 10% | D39: SI.DST.10TH.10 | AK39: 47.2 | BA39: 46.2 | BN39: 33.1
A40: Canada | B40: CAN | C40: Income share held by highest 10% | D40: SI.DST.10TH.10 | P40: 26.6 | R40: 25.1 | T40: 24.5 | V40: 24.1 | X40: 24 | Z40: 23.9 | AA40: 24.1 | AC40: 24.6 | AD40: 24.5 | AE40: 23.3 | AF40: 23.4 | AG40: 23.1 | AH40: 22.8 | AI40: 23.1 | AJ40: 23.3 | AK40: 23.2 | AL40: 23.2 | AM40: 22.9 | AN40: 23.2 | AO40: 24.5 | AP40: 25 | AQ40: 25.1 | AR40: 24.7 | AS40: 25.2 | AT40: 25.2 | AU40: 25.1 | AV40: 25.3 | AW40: 25.2 | AX40: 25.2 | AY40: 25.7 | AZ40: 25.6 | BA40: 25.5 | BB40: 25.4 | BC40: 25.3 | BD40: 24.6 | BE40: 24.8 | BF40: 24.7 | BG40: 24.7 | BH40: 25.1 | BI40: 24.6 | BJ40: 24.9 | BK40: 24.4 | BL40: 24 | BM40: 23.4 | BN40: 24.1
A41: Central Europe and the Baltics | B41: CEB | C41: Income share held by highest 10% | D41: SI.DST.10TH.10
A42: Switzerland | B42: CHE | C42: Income share held by highest 10% | D42: SI.DST.10TH.10 | AA42: 28.2 | AK42: 26 | AS42: 25.5 | AU42: 23.7 | AW42: 23.6 | AY42: 26 | AZ42: 26.7 | BA42: 26.3 | BB42: 25.6 | BC42: 25.4 | BD42: 24.6 | BE42: 25 | BF42: 25.5 | BG42: 25.5 | BH42: 25.2 | BI42: 25.8 | BJ42: 25.5 | BK42: 25.8 | BL42: 26.6 | BM42: 26.4 | BN42: 26.6 | BO42: 26.6
A43: Channel Islands | B43: CHI | C43: Income share held by highest 10% | D43: SI.DST.10TH.10
A44: Chile | B44: CHL | C44: Income share held by highest 10% | D44: SI.DST.10TH.10 | AF44: 45.4 | AI44: 47 | AK44: 45.2 | AM44: 45.9 | AO44: 44.4 | AQ44: 45 | AS44: 42.6 | AV44: 41.4 | AY44: 38.2 | BB44: 38.4 | BD44: 38 | BF44: 38.2 | BH44: 36.8 | BJ44: 36.9 | BM44: 37.3 | BO44: 34.5
A45: China | B45: CHN | C45: Income share held by highest 10% | D45: SI.DST.10TH.10 | Z45: 21.7 | AC45: 21.3 | AF45: 22.4 | AI45: 25.8 | AL45: 26.6 | AO45: 27.3 | AR45: 29.4 | AU45: 31.4 | AX45: 30.9 | BA45: 32 | BC45: 32.6 | BD45: 31.8 | BE45: 31.5 | BF45: 30.3 | BG45: 29.7 | BH45: 29.4 | BI45: 29.3 | BJ45: 29.9 | BK45: 29.4 | BL45: 29.5 | BM45: 29.4 | BN45: 28.2 | BO45: 28.4
A46: Cote d'Ivoire | B46: CIV | C46: Income share held by highest 10% | D46: SI.DST.10TH.10 | AD46: 35.6 | AE46: 29.4 | AF46: 32 | AG46: 28.3 | AK46: 29.5 | AN46: 32.7 | AQ46: 30.1 | AU46: 31.3 | BA46: 32.6 | BH46: 31.9 | BK46: 29 | BN46: 27.8
A47: Cameroon | B47: CMR | C47: Income share held by highest 10% | D47: SI.DST.10TH.10 | AO47: 36.1 | AT47: 33.6 | AZ47: 33 | BG47: 35 | BN47: 31.1
A48: Congo, Dem. Rep. | B48: COD | C48: Income share held by highest 10% | D48: SI.DST.10TH.10 | AW48: 32.3 | BE48: 32 | BM48: 35.7
A49: Congo, Rep. | B49: COG | C49: Income share held by highest 10% | D49: SI.DST.10TH.10 | AX49: 36.8 | BD49: 37.9
A50: Colombia | B50: COL | C50: Income share held by highest 10% | D50: SI.DST.10TH.10 | Y50: 42.3 | AG50: 41.2 | AH50: 41.4 | AJ50: 39.5 | AK50: 40.4 | AO50: 45.6 | AR50: 46.8 | AS50: 46.9 | AT50: 46.3 | AU50: 45.2 | AV50: 42.8 | AW50: 44.5 | AX50: 43.2 | BA50: 43.7 | BB50: 42.9 | BC50: 43.4 | BD50: 42.4 | BE50: 41.3 | BF50: 41.4 | BG50: 41.4 | BH50: 39.9 | BI50: 39.8 | BJ50: 39 | BK50: 39.7 | BL50: 40.3 | BM50: 41.8 | BN50: 43.7 | BO50: 43.5 | BP50: 42.7
A51: Comoros | B51: COM | C51: Income share held by highest 10% | D51: SI.DST.10TH.10 | AW51: 48.1 | BG51: 33.6
A52: Cabo Verde | B52: CPV | C52: Income share held by highest 10% | D52: SI.DST.10TH.10 | AT52: 42.6 | AZ52: 37.1 | BH52: 32.3
A53: Costa Rica | B53: CRI | C53: Income share held by highest 10% | D53: SI.DST.10TH.10 | Z53: 33.7 | AE53: 23.1 | AH53: 33.2 | AI53: 33 | AJ53: 34.3 | AK53: 33.7 | AL53: 33.7 | AM53: 35.2 | AN53: 33.8 | AO53: 34.3 | AP53: 33.8 | AQ53: 34 | AR53: 35.9 | AS53: 35.7 | AT53: 39.7 | AU53: 40.4 | AV53: 37 | AW53: 36.6 | AX53: 35.9 | AY53: 38.3 | AZ53: 38.9 | BA53: 37.7 | BB53: 39.4 | BC53: 36.8 | BD53: 36.9 | BE53: 36.6 | BF53: 37 | BG53: 36.9 | BH53: 36.8 | BI53: 37.3 | BJ53: 37 | BK53: 36.3 | BL53: 36.7 | BM53: 37 | BN53: 37.2 | BO53: 35.7 | BP53: 35.1 | BQ53: 34.2
A54: Caribbean small states | B54: CSS | C54: Income share held by highest 10% | D54: SI.DST.10TH.10
A55: Cuba | B55: CUB | C55: Income share held by highest 10% | D55: SI.DST.10TH.10
A56: Curacao | B56: CUW | C56: Income share held by highest 10% | D56: SI.DST.10TH.10
A57: Cayman Islands | B57: CYM | C57: Income share held by highest 10% | D57: SI.DST.10TH.10
A58: Cyprus | B58: CYP | C58: Income share held by highest 10% | D58: SI.DST.10TH.10 | AW58: 24.3 | AX58: 24.9 | AY58: 26 | AZ58: 25.5 | BA58: 26.2 | BB58: 26.2 | BC58: 25.7 | BD58: 26.7 | BE58: 28 | BF58: 30.9 | BG58: 28.8 | BH58: 27.5 | BI58: 26.8 | BJ58: 25.5 | BK58: 27.2 | BL58: 25.5 | BM58: 26.3 | BN58: 25.7 | BO58: 26.2 | BP58: 26.3
A59: Czechia | B59: CZE | C59: Income share held by highest 10% | D59: SI.DST.10TH.10 | AK59: 19.2 | AL59: 23.7 | AO59: 21.8 | AU59: 22.2 | AW59: 23.1 | AX59: 22.9 | AY59: 22.6 | AZ59: 22.3 | BA59: 22.9 | BB59: 22.4 | BC59: 22.4 | BD59: 22.2 | BE59: 22.2 | BF59: 22.6 | BG59: 22.1 | BH59: 22.1 | BI59: 21.9 | BJ59: 21.4 | BK59: 21.5 | BL59: 21.5 | BM59: 22.5 | BN59: 22.2 | BO59: 21.8 | BP59: 21.5
A60: Germany | B60: DEU | C60: Income share held by highest 10% | D60: SI.DST.10TH.10 | AJ60: 22.8 | AK60: 22.7 | AL60: 22.5 | AM60: 22.6 | AN60: 22.4 | AO60: 22 | AP60: 22 | AQ60: 22 | AR60: 22.7 | AS60: 22.6 | AT60: 23.6 | AU60: 23.3 | AV60: 23.5 | AW60: 23.7 | AX60: 24.9 | AY60: 24.3 | AZ60: 24.7 | BA60: 24.2 | BB60: 23.6 | BC60: 23.7 | BD60: 24.1 | BE60: 24 | BF60: 24.5 | BG60: 23.6 | BH60: 24.6 | BI60: 24.2 | BJ60: 24.2 | BK60: 24.9 | BL60: 24.7 | BM60: 25
A61: Djibouti | B61: DJI | C61: Income share held by highest 10% | D61: SI.DST.10TH.10 | AU61: 30.8 | BE61: 34.4 | BF61: 34 | BJ61: 32.3
A62: Dominica | B62: DMA | C62: Income share held by highest 10% | D62: SI.DST.10TH.10
A63: Denmark | B63: DNK | C63: Income share held by highest 10% | D63: SI.DST.10TH.10 | AF63: 21.2 | AK63: 20.2 | AN63: 19.4 | AS63: 19.8 | AV63: 21.4 | AW63: 20.6 | AX63: 21 | AY63: 21.7 | AZ63: 22.1 | BA63: 21 | BB63: 21.8 | BC63: 22.5 | BD63: 22.7 | BE63: 23.1 | BF63: 23.7 | BG63: 23.6 | BH63: 23.8 | BI63: 23.7 | BJ63: 24 | BK63: 23.5 | BL63: 23.5 | BM63: 22.9 | BN63: 23.8 | BO63: 24.5 | BP63: 25.5
A64: Dominican Republic | B64: DOM | C64: Income share held by highest 10% | D64: SI.DST.10TH.10 | AE64: 36.1 | AH64: 39.8 | AK64: 41.6 | AO64: 36.5 | AP64: 37.9 | AS64: 40.2 | AT64: 39.2 | AU64: 38.3 | AV64: 41.7 | AW64: 41.7 | AX64: 39 | AY64: 41.2 | AZ64: 38.6 | BA64: 37.8 | BB64: 38.7 | BC64: 36.5 | BD64: 37.5 | BE64: 36 | BF64: 37.9 | BG64: 33.4 | BH64: 34.8 | BI64: 35.4 | BJ64: 33.5 | BK64: 35.1 | BL64: 33.1 | BM64: 30.4 | BN64: 30.2 | BO64: 28.3 | BP64: 29.1 | BQ64: 29.5
A65: Algeria | B65: DZA | C65: Income share held by highest 10% | D65: SI.DST.10TH.10 | AG65: 29.6 | AN65: 26.9 | BD65: 22.9
A66: East Asia & Pacific (excluding high income) | B66: EAP | C66: Income share held by highest 10% | D66: SI.DST.10TH.10
A67: Early-demographic dividend | B67: EAR | C67: Income share held by highest 10% | D67: SI.DST.10TH.10
A68: East Asia & Pacific | B68: EAS | C68: Income share held by highest 10% | D68: SI.DST.10TH.10
A69: Europe & Central Asia (excluding high income) | B69: ECA | C69: Income share held by highest 10% | D69: SI.DST.10TH.10
A70: Europe & Central Asia | B70: ECS | C70: Income share held by highest 10% | D70: SI.DST.10TH.10
A71: Ecuador | B71: ECU | C71: Income share held by highest 10% | D71: SI.DST.10TH.10 | AF71: 38.4 | AM71: 42.5 | AN71: 40 | AQ71: 37.8 | AR71: 47.8 | AS71: 45.9 | AV71: 42 | AW71: 42.4 | AX71: 41.1 | AY71: 41.1 | AZ71: 42 | BA71: 38.1 | BB71: 37.1 | BC71: 37.5 | BD71: 34.1 | BE71: 34.6 | BF71: 35.7 | BG71: 34.4 | BH71: 34.9 | BI71: 34.3 | BJ71: 33.8 | BK71: 34.4 | BL71: 34.5 | BM71: 36 | BN71: 34.7 | BO71: 34.3 | BP71: 33.2 | BQ71: 33.4
A72: Egypt, Arab Rep. | B72: EGY | C72: Income share held by highest 10% | D72: SI.DST.10TH.10 | AI72: 26.7 | AN72: 26.1 | AR72: 26.4 | AW72: 27.4 | BA72: 27 | BC72: 26.1 | BE72: 24.7 | BH72: 27.8 | BJ72: 26.9 | BL72: 27.5 | BN72: 24.6
A73: Euro area | B73: EMU | C73: Income share held by highest 10% | D73: SI.DST.10TH.10
A74: Eritrea | B74: ERI | C74: Income share held by highest 10% | D74: SI.DST.10TH.10
A75: Spain | B75: ESP | C75: Income share held by highest 10% | D75: SI.DST.10TH.10 | Y75: 25.9 | AD75: 26.4 | AI75: 24.5 | AL75: 26.2 | AM75: 25.6 | AN75: 26.5 | AO75: 26.3 | AP75: 25.9 | AQ75: 25.5 | AR75: 25.4 | AS75: 25.4 | AV75: 24 | AW75: 24.8 | AX75: 24.3 | AY75: 24.9 | AZ75: 25.6 | BA75: 25.6 | BB75: 25.9 | BC75: 26 | BD75: 25.9 | BE75: 25.8 | BF75: 25.9 | BG75: 26 | BH75: 26.2 | BI75: 25.8 | BJ75: 25.4 | BK75: 25.3 | BL75: 24.9 | BM75: 25 | BN75: 24.7 | BO75: 24.8 | BP75: 24.5
A76: Estonia | B76: EST | C76: Income share held by highest 10% | D76: SI.DST.10TH.10 | AL76: 31.3 | AN76: 22.7 | AQ76: 29.8 | AS76: 27.6 | AT76: 27.9 | AU76: 27.3 | AV76: 28.4 | AW76: 25.9 | AX76: 26.1 | AY76: 26.8 | AZ76: 24 | BA76: 24.9 | BB76: 24.4 | BC76: 24.3 | BD76: 24.7 | BE76: 25.2 | BF76: 26.6 | BG76: 26.3 | BH76: 24.4 | BI76: 23.1 | BJ76: 22.5 | BK76: 22.4 | BL76: 23.3 | BM76: 23.5 | BN76: 24.3 | BO76: 24.4 | BP76: 23.7
A77: Ethiopia | B77: ETH | C77: Income share held by highest 10% | D77: SI.DST.10TH.10 | AN77: 38 | AR77: 25.5 | AW77: 25.6 | BC77: 27.4 | BH77: 28.5 | BN77: 24.8
A78: European Union | B78: EUU | C78: Income share held by highest 10% | D78: SI.DST.10TH.10
A79: Fragile and conflict affected situations | B79: FCS | C79: Income share held by highest 10% | D79: SI.DST.10TH.10
A80: Finland | B80: FIN | C80: Income share held by highest 10% | D80: SI.DST.10TH.10 | AF80: 18.8 | AJ80: 19.3 | AN80: 20.2 | AS80: 22.4 | AV80: 23 | AW80: 23.2 | AX80: 23 | AY80: 23 | AZ80: 23.3 | BA80: 22.9 | BB80: 22.6 | BC80: 22.5 | BD80: 22.8 | BE80: 22.3 | BF80: 22.2 | BG80: 22 | BH80: 22.4 | BI80: 22.4 | BJ80: 22.6 | BK80: 22.6 | BL80: 23 | BM80: 22.6 | BN80: 22.9 | BO80: 23.1 | BP80: 22.5
A81: Fiji | B81: FJI | C81: Income share held by highest 10% | D81: SI.DST.10TH.10 | AU81: 29.6 | BA81: 32.9 | BF81: 29.7 | BL81: 24.2
A82: France | B82: FRA | C82: Income share held by highest 10% | D82: SI.DST.10TH.10 | O82: 28.2 | T82: 27.5 | X82: 26.2 | AC82: 25.7 | AI82: 24.8 | AO82: 24 | AP82: 24 | AQ82: 24.1 | AR82: 24.9 | AS82: 25 | AT82: 25 | AU82: 24.6 | AV82: 25.2 | AW82: 24.5 | AX82: 23.9 | AY82: 23.5 | AZ82: 26.2 | BA82: 26.7 | BB82: 26.1 | BC82: 27.1 | BD82: 26.9 | BE82: 26.9 | BF82: 26.4 | BG82: 26.1 | BH82: 26.6 | BI82: 25.9 | BJ82: 25.8 | BK82: 26.7 | BL82: 24.8 | BM82: 24.5 | BN82: 24.9 | BO82: 24.6 | BP82: 25
A83: Faroe Islands | B83: FRO | C83: Income share held by highest 10% | D83: SI.DST.10TH.10
A84: Micronesia, Fed. Sts. | B84: FSM | C84: Income share held by highest 10% | D84: SI.DST.10TH.10 | AX84: 32.4 | BF84: 29.7
A85: Gabon | B85: GAB | C85: Income share held by highest 10% | D85: SI.DST.10TH.10 | AX85: 33.1 | BJ85: 27.7
A86: United Kingdom | B86: GBR | C86: Income share held by highest 10% | D86: SI.DST.10TH.10 | M86: 21.9 | N86: 22.7 | O86: 22.7 | P86: 23.4 | Q86: 22.5 | R86: 22.9 | S86: 23.1 | T86: 22.2 | U86: 21.8 | V86: 21.6 | W86: 21.5 | X86: 21.6 | Y86: 22.5 | Z86: 23.3 | AA86: 23.3 | AB86: 23.2 | AC86: 22.8 | AD86: 23.4 | AE86: 24.9 | AF86: 26.3 | AG86: 26.5 | AH86: 25.2 | AI86: 27.1 | AJ86: 26.3 | AK86: 26.1 | AL86: 26.4 | AM86: 27.4 | AN86: 26.9 | AO86: 26.8 | AP86: 27.2 | AQ86: 28.1 | AR86: 28.3 | AS86: 30.8 | AT86: 28.9 | AU86: 27.3 | AV86: 26.9 | AW86: 26.9 | AX86: 27.4 | AY86: 27.9 | AZ86: 26.1 | BA86: 27.2 | BB86: 27 | BC86: 26 | BD86: 25.5 | BE86: 25.3 | BF86: 24.9 | BG86: 25.2 | BH86: 25.3 | BI86: 25.1 | BJ86: 24.5 | BK86: 25.4 | BL86: 24.7 | BM86: 24.6 | BN86: 24.6
A87: Georgia | B87: GEO | C87: Income share held by highest 10% | D87: SI.DST.10TH.10 | AO87: 27.9 | AP87: 29.9 | AQ87: 31.2 | AR87: 29.9 | AS87: 30.3 | AT87: 30 | AU87: 28.2 | AV87: 27.1 | AW87: 26.7 | AX87: 27.7 | AY87: 27.5 | AZ87: 28.9 | BA87: 29.1 | BB87: 28.9 | BC87: 29.5 | BD87: 29.8 | BE87: 29.3 | BF87: 29.1 | BG87: 28.6 | BH87: 27.8 | BI87: 28.1 | BJ87: 28.9 | BK87: 27.5 | BL87: 27.6 | BM87: 26.2 | BN87: 26.2 | BO87: 25.2 | BP87: 26.9 | BQ87: 26.2
A88: Ghana | B88: GHA | C88: Income share held by highest 10% | D88: SI.DST.10TH.10 | AF88: 27.3 | AG88: 28.1 | AJ88: 30.1 | AQ88: 29.6 | AX88: 32.7 | BE88: 31.7 | BI88: 32.2
A89: Gibraltar | B89: GIB | C89: Income share held by highest 10% | D89: SI.DST.10TH.10
A90: Guinea | B90: GIN | C90: Income share held by highest 10% | D90: SI.DST.10TH.10 | AJ90: 31.4 | AM90: 36 | AU90: 34 | AZ90: 30.1 | BE90: 26.4 | BK90: 23.1
A91: Gambia, The | B91: GMB | C91: Income share held by highest 10% | D91: SI.DST.10TH.10 | AQ91: 37.6 | AV91: 36.7 | BC91: 34.9 | BH91: 28.7 | BM91: 30.5
A92: Guinea-Bissau | B92: GNB | C92: Income share held by highest 10% | D92: SI.DST.10TH.10 | AJ92: 42.2 | AL92: 34.4 | AU92: 28 | BC92: 42 | BK92: 27.6 | BN92: 26.1
A93: Equatorial Guinea | B93: GNQ | C93: Income share held by highest 10% | D93: SI.DST.10TH.10 | BO93: 29.1
A94: Greece | B94: GRC | C94: Income share held by highest 10% | D94: SI.DST.10TH.10 | AN94: 26.9 | AS94: 25.5 | AU94: 26.7 | AV94: 24.6 | AW94: 25.5 | AX94: 26.3 | AY94: 26.7 | AZ94: 26 | BA94: 26 | BB94: 26 | BC94: 25.6 | BD94: 25.6 | BE94: 26.6 | BF94: 26.4 | BG94: 26.1 | BH94: 26.2 | BI94: 25.9 | BJ94: 25.9 | BK94: 24.9 | BL94: 24.9 | BM94: 25.2 | BN94: 24.8 | BO94: 25.7 | BP94: 26
A95: Grenada | B95: GRD | C95: Income share held by highest 10% | D95: SI.DST.10TH.10 | BK95: 33.7
A96: Greenland | B96: GRL | C96: Income share held by highest 10% | D96: SI.DST.10TH.10
A97: Guatemala | B97: GTM | C97: Income share held by highest 10% | D97: SI.DST.10TH.10 | AE97: 41.5 | AH97: 45.7 | AQ97: 37 | AS97: 43.9 | AY97: 43 | BG97: 38 | BP97: 34.1
A98: Guam | B98: GUM | C98: Income share held by highest 10% | D98: SI.DST.10TH.10
A99: Guyana | B99: GUY | C99: Income share held by highest 10% | D99: SI.DST.10TH.10 | AK99: 28.5 | AQ99: 34.4
A100: High income | B100: HIC | C100: Income share held by highest 10% | D100: SI.DST.10TH.10
A101: Hong Kong SAR, China | B101: HKG | C101: Income share held by highest 10% | D101: SI.DST.10TH.10
...

Sheet INC_DIST_2015
A1: Country Name | B1: Country Code | C1: P0-10 | D1: P10-20 | E1: P20-40 | F1: P40-60 | G1: P60-80 | H1: P80-90 | I1: P90-100 | J1: P10 | K1: P20 | L1: P40 | M1: P60 | N1: P80 | O1: P90 | P1: P100
A2: Aruba | B2: ABW | C2: =VLOOKUP($B2,lowest_10!$B$5:$BH$270,59,0) -> 0 | D2: =VLOOKUP($B2,lowest_20!$B$5:$BH$270,59,0)-C2 -> 0 | E2: =VLOOKUP($B2,second_20!$B$5:$BH$270,59,0) -> 0 | F2: =VLOOKUP($B2,third_20!$B$5:$BH$270,59,0) -> 0 | G2: =VLOOKUP($B2,fourth_20!$B$5:$BH$270,59,0) -> 0 | H2: =VLOOKUP($B2,highest_20!$B$5:$BH$270,59,0)-I2 -> 0 | I2: =VLOOKUP($B2,highest_10!$B$5:$BH$270,59,0) -> 0 | J2: =SUM($C2:C2) -> 0 | K2: =SUM($C2:D2) -> 0 | L2: =SUM($C2:E2) -> 0 | M2: =SUM($C2:F2) -> 0 | N2: =SUM($C2:G2) -> 0 | O2: =SUM($C2:H2) -> 0 | P2: =SUM($C2:I2) -> 0
A3: Africa Eastern and Southern | B3: AFE | C3: =VLOOKUP($B3,lowest_10!$B$5:$BH$270,59,0) -> 0 | D3: =VLOOKUP($B3,lowest_20!$B$5:$BH$270,59,0)-C3 -> 0 | E3: =VLOOKUP($B3,second_20!$B$5:$BH$270,59,0) -> 0 | F3: =VLOOKUP($B3,third_20!$B$5:$BH$270,59,0) -> 0 | G3: =VLOOKUP($B3,fourth_20!$B$5:$BH$270,59,0) -> 0 | H3: =VLOOKUP($B3,highest_20!$B$5:$BH$270,59,0)-I3 -> 0 | I3: =VLOOKUP($B3,highest_10!$B$5:$BH$270,59,0) -> 0 | J3: =SUM($C3:C3) -> 0 | K3: =SUM($C3:D3) -> 0 | L3: =SUM($C3:E3) -> 0 | M3: =SUM($C3:F3) -> 0 | N3: =SUM($C3:G3) -> 0 | O3: =SUM($C3:H3) -> 0 | P3: =SUM($C3:I3) -> 0
A4: Afghanistan | B4: AFG | C4: =VLOOKUP($B4,lowest_10!$B$5:$BH$270,59,0) -> 0 | D4: =VLOOKUP($B4,lowest_20!$B$5:$BH$270,59,0)-C4 -> 0 | E4: =VLOOKUP($B4,second_20!$B$5:$BH$270,59,0) -> 0 | F4: =VLOOKUP($B4,third_20!$B$5:$BH$270,59,0) -> 0 | G4: =VLOOKUP($B4,fourth_20!$B$5:$BH$270,59,0) -> 0 | H4: =VLOOKUP($B4,highest_20!$B$5:$BH$270,59,0)-I4 -> 0 | I4: =VLOOKUP($B4,highest_10!$B$5:$BH$270,59,0) -> 0 | J4: =SUM($C4:C4) -> 0 | K4: =SUM($C4:D4) -> 0 | L4: =SUM($C4:E4) -> 0 | M4: =SUM($C4:F4) -> 0 | N4: =SUM($C4:G4) -> 0 | O4: =SUM($C4:H4) -> 0 | P4: =SUM($C4:I4) -> 0
A5: Africa Western and Central | B5: AFW | C5: =VLOOKUP($B5,lowest_10!$B$5:$BH$270,59,0) -> 0 | D5: =VLOOKUP($B5,lowest_20!$B$5:$BH$270,59,0)-C5 -> 0 | E5: =VLOOKUP($B5,second_20!$B$5:$BH$270,59,0) -> 0 | F5: =VLOOKUP($B5,third_20!$B$5:$BH$270,59,0) -> 0 | G5: =VLOOKUP($B5,fourth_20!$B$5:$BH$270,59,0) -> 0 | H5: =VLOOKUP($B5,highest_20!$B$5:$BH$270,59,0)-I5 -> 0 | I5: =VLOOKUP($B5,highest_10!$B$5:$BH$270,59,0) -> 0 | J5: =SUM($C5:C5) -> 0 | K5: =SUM($C5:D5) -> 0 | L5: =SUM($C5:E5) -> 0 | M5: =SUM($C5:F5) -> 0 | N5: =SUM($C5:G5) -> 0 | O5: =SUM($C5:H5) -> 0 | P5: =SUM($C5:I5) -> 0
A6: Angola | B6: AGO | C6: =VLOOKUP($B6,lowest_10!$B$5:$BH$270,59,0) -> 0 | D6: =VLOOKUP($B6,lowest_20!$B$5:$BH$270,59,0)-C6 -> 0 | E6: =VLOOKUP($B6,second_20!$B$5:$BH$270,59,0) -> 0 | F6: =VLOOKUP($B6,third_20!$B$5:$BH$270,59,0) -> 0 | G6: =VLOOKUP($B6,fourth_20!$B$5:$BH$270,59,0) -> 0 | H6: =VLOOKUP($B6,highest_20!$B$5:$BH$270,59,0)-I6 -> 0 | I6: =VLOOKUP($B6,highest_10!$B$5:$BH$270,59,0) -> 0 | J6: =SUM($C6:C6) -> 0 | K6: =SUM($C6:D6) -> 0 | L6: =SUM($C6:E6) -> 0 | M6: =SUM($C6:F6) -> 0 | N6: =SUM($C6:G6) -> 0 | O6: =SUM($C6:H6) -> 0 | P6: =SUM($C6:I6) -> 0
A7: Albania | B7: ALB | C7: =VLOOKUP($B7,lowest_10!$B$5:$BH$270,59,0) -> 3.2 | D7: =VLOOKUP($B7,lowest_20!$B$5:$BH$270,59,0)-C7 -> 4.5 | E7: =VLOOKUP($B7,second_20!$B$5:$BH$270,59,0) -> 12.1 | F7: =VLOOKUP($B7,third_20!$B$5:$BH$270,59,0) -> 16.5 | G7: =VLOOKUP($B7,fourth_20!$B$5:$BH$270,59,0) -> 23 | H7: =VLOOKUP($B7,highest_20!$B$5:$BH$270,59,0)-I7 -> 15.8 | I7: =VLOOKUP($B7,highest_10!$B$5:$BH$270,59,0) -> 24.8 | J7: =SUM($C7:C7) -> 3.2 | K7: =SUM($C7:D7) -> 7.7 | L7: =SUM($C7:E7) -> 19.8 | M7: =SUM($C7:F7) -> 36.3 | N7: =SUM($C7:G7) -> 59.3 | O7: =SUM($C7:H7) -> 75.1 | P7: =SUM($C7:I7) -> 99.9
A8: Andorra | B8: AND | C8: =VLOOKUP($B8,lowest_10!$B$5:$BH$270,59,0) -> 0 | D8: =VLOOKUP($B8,lowest_20!$B$5:$BH$270,59,0)-C8 -> 0 | E8: =VLOOKUP($B8,second_20!$B$5:$BH$270,59,0) -> 0 | F8: =VLOOKUP($B8,third_20!$B$5:$BH$270,59,0) -> 0 | G8: =VLOOKUP($B8,fourth_20!$B$5:$BH$270,59,0) -> 0 | H8: =VLOOKUP($B8,highest_20!$B$5:$BH$270,59,0)-I8 -> 0 | I8: =VLOOKUP($B8,highest_10!$B$5:$BH$270,59,0) -> 0 | J8: =SUM($C8:C8) -> 0 | K8: =SUM($C8:D8) -> 0 | L8: =SUM($C8:E8) -> 0 | M8: =SUM($C8:F8) -> 0 | N8: =SUM($C8:G8) -> 0 | O8: =SUM($C8:H8) -> 0 | P8: =SUM($C8:I8) -> 0
A9: Arab World | B9: ARB | C9: =VLOOKUP($B9,lowest_10!$B$5:$BH$270,59,0) -> 0 | D9: =VLOOKUP($B9,lowest_20!$B$5:$BH$270,59,0)-C9 -> 0 | E9: =VLOOKUP($B9,second_20!$B$5:$BH$270,59,0) -> 0 | F9: =VLOOKUP($B9,third_20!$B$5:$BH$270,59,0) -> 0 | G9: =VLOOKUP($B9,fourth_20!$B$5:$BH$270,59,0) -> 0 | H9: =VLOOKUP($B9,highest_20!$B$5:$BH$270,59,0)-I9 -> 0 | I9: =VLOOKUP($B9,highest_10!$B$5:$BH$270,59,0) -> 0 | J9: =SUM($C9:C9) -> 0 | K9: =SUM($C9:D9) -> 0 | L9: =SUM($C9:E9) -> 0 | M9: =SUM($C9:F9) -> 0 | N9: =SUM($C9:G9) -> 0 | O9: =SUM($C9:H9) -> 0 | P9: =SUM($C9:I9) -> 0
A10: United Arab Emirates | B10: ARE | C10: =VLOOKUP($B10,lowest_10!$B$5:$BH$270,59,0) -> 0 | D10: =VLOOKUP($B10,lowest_20!$B$5:$BH$270,59,0)-C10 -> 0 | E10: =VLOOKUP($B10,second_20!$B$5:$BH$270,59,0) -> 0 | F10: =VLOOKUP($B10,third_20!$B$5:$BH$270,59,0) -> 0 | G10: =VLOOKUP($B10,fourth_20!$B$5:$BH$270,59,0) -> 0 | H10: =VLOOKUP($B10,highest_20!$B$5:$BH$270,59,0)-I10 -> 0 | I10: =VLOOKUP($B10,highest_10!$B$5:$BH$270,59,0) -> 0 | J10: =SUM($C10:C10) -> 0 | K10: =SUM($C10:D10) -> 0 | L10: =SUM($C10:E10) -> 0 | M10: =SUM($C10:F10) -> 0 | N10: =SUM($C10:G10) -> 0 | O10: =SUM($C10:H10) -> 0 | P10: =SUM($C10:I10) -> 0
A11: Argentina | B11: ARG | C11: =VLOOKUP($B11,lowest_10!$B$5:$BH$270,59,0) -> 0 | D11: =VLOOKUP($B11,lowest_20!$B$5:$BH$270,59,0)-C11 -> 0 | E11: =VLOOKUP($B11,second_20!$B$5:$BH$270,59,0) -> 0 | F11: =VLOOKUP($B11,third_20!$B$5:$BH$270,59,0) -> 0 | G11: =VLOOKUP($B11,fourth_20!$B$5:$BH$270,59,0) -> 0 | H11: =VLOOKUP($B11,highest_20!$B$5:$BH$270,59,0)-I11 -> 0 | I11: =VLOOKUP($B11,highest_10!$B$5:$BH$270,59,0) -> 0 | J11: =SUM($C11:C11) -> 0 | K11: =SUM($C11:D11) -> 0 | L11: =SUM($C11:E11) -> 0 | M11: =SUM($C11:F11) -> 0 | N11: =SUM($C11:G11) -> 0 | O11: =SUM($C11:H11) -> 0 | P11: =SUM($C11:I11) -> 0
A12: Armenia | B12: ARM | C12: =VLOOKUP($B12,lowest_10!$B$5:$BH$270,59,0) -> 3.4 | D12: =VLOOKUP($B12,lowest_20!$B$5:$BH$270,59,0)-C12 -> 4.8 | E12: =VLOOKUP($B12,second_20!$B$5:$BH$270,59,0) -> 12.6 | F12: =VLOOKUP($B12,third_20!$B$5:$BH$270,59,0) -> 16.7 | G12: =VLOOKUP($B12,fourth_20!$B$5:$BH$270,59,0) -> 21.8 | H12: =VLOOKUP($B12,highest_20!$B$5:$BH$270,59,0)-I12 -> 14 | I12: =VLOOKUP($B12,highest_10!$B$5:$BH$270,59,0) -> 26.7 | J12: =SUM($C12:C12) -> 3.4 | K12: =SUM($C12:D12) -> 8.2 | L12: =SUM($C12:E12) -> 20.8 | M12: =SUM($C12:F12) -> 37.5 | N12: =SUM($C12:G12) -> 59.3 | O12: =SUM($C12:H12) -> 73.3 | P12: =SUM($C12:I12) -> 100
A13: American Samoa | B13: ASM | C13: =VLOOKUP($B13,lowest_10!$B$5:$BH$270,59,0) -> 0 | D13: =VLOOKUP($B13,lowest_20!$B$5:$BH$270,59,0)-C13 -> 0 | E13: =VLOOKUP($B13,second_20!$B$5:$BH$270,59,0) -> 0 | F13: =VLOOKUP($B13,third_20!$B$5:$BH$270,59,0) -> 0 | G13: =VLOOKUP($B13,fourth_20!$B$5:$BH$270,59,0) -> 0 | H13: =VLOOKUP($B13,highest_20!$B$5:$BH$270,59,0)-I13 -> 0 | I13: =VLOOKUP($B13,highest_10!$B$5:$BH$270,59,0) -> 0 | J13: =SUM($C13:C13) -> 0 | K13: =SUM($C13:D13) -> 0 | L13: =SUM($C13:E13) -> 0 | M13: =SUM($C13:F13) -> 0 | N13: =SUM($C13:G13) -> 0 | O13: =SUM($C13:H13) -> 0 | P13: =SUM($C13:I13) -> 0
... A267: Zimbabwe | B267: ZWE | C267: =VLOOKUP($B267,lowest_10!$B$5:$BH$270,59,0) -> 0 | D267: =VLOOKUP($B267,lowest_20!$B$5:$BH$270,59,0)-C267 -> 0 | E267: =VLOOKUP($B267,second_20!$B$5:$BH$270,59,0) -> 0 | F267: =VLOOKUP($B267,third_20!$B$5:$BH$270,59,0) -> 0 | G267: =VLOOKUP($B267,fourth_20!$B$5:$BH$270,59,0) -> 0 | H267: =VLOOKUP($B267,highest_20!$B$5:$BH$270,59,0)-I267 -> 0 | I267: =VLOOKUP($B267,highest_10!$B$5:$BH$270,59,0) -> 0 | J267: =SUM($C267:C267) -> 0 | K267: =SUM($C267:D267) -> 0 | L267: =SUM($C267:E267) -> 0 | M267: =SUM($C267:F267) -> 0 | N267: =SUM($C267:G267) -> 0 | O267: =SUM($C267:H267) -> 0 | P267: =SUM($C267:I267) -> 0

Sheet Metadata - Countries
A1: Country Code | B1: Region | C1: IncomeGroup | D1: SpecialNotes | E1: TableName
A2: ABW | B2: Latin America & Caribbean | C2: High income | E2: Aruba
A3: AFE | D3: 26 countries, stretching from the Red Sea in the North to the Cape of Good Hope in the South (https://www.worldbank.org/en/region/afr/eastern-and-southern-africa) | E3: Africa Eastern and Southern
A4: AFG | B4: Middle East & North Africa | C4: Low income | D4: The reporting period for national accounts data is designated as either calendar year basis (CY) or fiscal year basis (FY). For this country, it is fiscal year-based (fiscal year-end: March 20). Also, an estimate (PA.NUS.ATLS) of the exchange rate covers the same period and thus differs from the official exchange rate (CY). In addition, the World Bank systematically assesses the appropriateness of official exchange rates as conversion factors. In this country, multiple or dual exchange rate activity exists and must be accounted for appropriately in underlying statistics. An alternative estimate (“alternative conversion factor” - PA.NUS.ATLS) is thus calculated as a weighted average of the different exchange rates in use in the country. Doing so better reflects economic reality and leads to more accurate cross-country comparisons and country classifications by income level. For this country, this applies to the period 1960-2006. Alternative conversion factors are used in the Atlas methodology and elsewhere in World Development Indicators as single-year conversion factors. | E4: Afghanistan
A5: AFW | D5: 22 countries, stretching from the westernmost point of Africa, across the equator, and partly along the Atlantic Ocean till the Republic of Congo in the South (https://www.worldbank.org/en/region/afr/western-and-central-africa) | E5: Africa Western and Central
A6: AGO | B6: Sub-Saharan Africa | C6: Lower middle income | D6: The World Bank systematically assesses the appropriateness of official exchange rates as conversion factors. In this country, multiple or dual exchange rate activity exists and must be accounted for appropriately in underlying statistics. An alternative estimate (“alternative conversion factor” - PA.NUS.ATLS) is thus calculated as a weighted average of the different exchange rates in use in the country. Doing so better reflects economic reality and leads to more accurate cross-country comparisons and country classifications by income level. For this country, this applies to the period 1994-2024. Alternative conversion factors are used in the Atlas methodology and elsewhere in World Development Indicators as single-year conversion factors. | E6: Angola
A7: ALB | B7: Europe & Central Asia | C7: Upper middle income | E7: Albania
A8: AND | B8: Europe & Central Asia | C8: High income | E8: Andorra
A9: ARB | D9: Arab World aggregate. Arab World is composed of members of the League of Arab States. | E9: Arab World
A10: ARE | B10: Middle East & North Africa | C10: High income | E10: United Arab Emirates
A11: ARG | B11: Latin America & Caribbean | C11: Upper middle income | D11: The World Bank systematically assesses the appropriateness of official exchange rates as conversion factors. In this country, multiple or dual exchange rate activity exists and must be accounted for appropriately in underlying statistics. An alternative estimate (“alternative conversion factor” - PA.NUS.ATLS) is thus calculated as a weighted average of the different exchange rates in use in the country. Doing so better reflects economic reality and leads to more accurate cross-country comparisons and country classifications by income level. For this country, this applies to the period 1971-2018. Alternative conversion factors are used in the Atlas methodology and elsewhere in World Development Indicators as single-year conversion factors. | E11: Argentina
A12: ARM | B12: Europe & Central Asia | C12: Upper middle income | E12: Armenia
A13: ASM | B13: East Asia & Pacific | C13: High income | E13: American Samoa
A14: ATG | B14: Latin America & Caribbean | C14: High income | E14: Antigua and Barbuda
A15: AUS | B15: East Asia & Pacific | C15: High income | D15: The reporting period for national accounts data is designated as either calendar year basis (CY) or fiscal year basis (FY). For this country, it is fiscal year-based (fiscal year-end: June 30). Also, an estimate (PA.NUS.ATLS) of the exchange rate covers the same period and thus differs from the official exchange rate (CY). | E15: Australia
A16: AUT | B16: Europe & Central Asia | C16: High income | D16: A simple multiplier is used to convert the national currencies of EMU members to euros. The following irrevocable euro conversion rate was adopted by the EU Council on January 1, 1999: 1 euro = 13.7603 Austrian schilling. Please note that historical data before 1999 are not actual euros and are not comparable or suitable for aggregation across countries. | E16: Austria
A17: AZE | B17: Europe & Central Asia | C17: Upper middle income | E17: Azerbaijan
A18: BDI | B18: Sub-Saharan Africa | C18: Low income | D18: The World Bank systematically assesses the appropriateness of official exchange rates as conversion factors. In this country, multiple or dual exchange rate activity exists and must be accounted for appropriately in underlying statistics. An alternative estimate (“alternative conversion factor” - PA.NUS.ATLS) is thus calculated as a weighted average of the different exchange rates in use in the country. Doing so better reflects economic reality and leads to more accurate cross-country comparisons and country classifications by income level. For this country, this applies to the period 1983-2024. Alternative conversion factors are used in the Atlas methodology and elsewhere in World Development Indicators as single-year conversion factors. | E18: Burundi
A19: BEL | B19: Europe & Central Asia | C19: High income | D19: A simple multiplier is used to convert the national currencies of EMU members to euros. The following irrevocable euro conversion rate was adopted by the EU Council on January 1, 1999: 1 euro = 40.3399 Belgian franc. Please note that historical data before 1999 are not actual euros and are not comparable or suitable for aggregation across countries. | E19: Belgium
A20: BEN | B20: Sub-Saharan Africa | C20: Lower middle income | E20: Benin
A21: BFA | B21: Sub-Saharan Africa | C21: Low income | E21: Burkina Faso
A22: BGD | B22: South Asia | C22: Lower middle income | D22: The reporting period for national accounts data is designated as either calendar year basis (CY) or fiscal year basis (FY). For this country, it is fiscal year-based (fiscal year-end: June 30). Also, an estimate (PA.NUS.ATLS) of the exchange rate covers the same period and thus differs from the official exchange rate (CY). | E22: Bangladesh
A23: BGR | B23: Europe & Central Asia | C23: High income | E23: Bulgaria
A24: BHR | B24: Middle East & North Africa | C24: High income | E24: Bahrain
A25: BHS | B25: Latin America & Caribbean | C25: High income | E25: Bahamas, The
A26: BIH | B26: Europe & Central Asia | C26: Upper middle income | E26: Bosnia and Herzegovina
A27: BLR | B27: Europe & Central Asia | C27: Upper middle income | D27: Data before 2015 were adjusted to reflect the new denomination effective from July 1, 2016 (BYN), a decrease of 10,000 times (1 BYN = 10,000 BYR) | E27: Belarus
A28: BLZ | B28: Latin America & Caribbean | C28: Upper middle income | E28: Belize
A29: BMU | B29: North America | C29: High income | E29: Bermuda
A30: BOL | B30: Latin America & Caribbean | C30: Lower middle income | E30: Bolivia
A31: BRA | B31: Latin America & Caribbean | C31: Upper middle income | E31: Brazil
A32: BRB | B32: Latin America & Caribbean | C32: High income | E32: Barbados
A33: BRN | B33: East Asia & Pacific | C33: High income | E33: Brunei Darussalam
A34: BTN | B34: South Asia | C34: Lower middle income | E34: Bhutan
A35: BWA | B35: Sub-Saharan Africa | C35: Upper middle income | E35: Botswana
A36: CAF | B36: Sub-Saharan Africa | C36: Low income | E36: Central African Republic
A37: CAN | B37: North America | C37: High income | D37: Fiscal year end: March 31; reporting period for national accounts data: CY. | E37: Canada
A38: CEB | D38: Central Europe and the Baltics aggregate. | E38: Central Europe and the Baltics
A39: CHE | B39: Europe & Central Asia | C39: High income | E39: Switzerland
A40: CHI | B40: Europe & Central Asia | C40: High income | E40: Channel Islands
A41: CHL | B41: Latin America & Caribbean | C41: High income | E41: Chile
A42: CHN | B42: East Asia & Pacific | C42: Upper middle income | D42: On 1 July 1997 China resumed its exercise of sovereignty over Hong Kong, and on 20 December 1999, China resumed its exercise of sovereignty over Macao. Unless otherwise noted, data for China do not include data for Hong Kong SAR, China; Macao SAR, China; or Taiwan, China. The World Bank systematically assesses the appropriateness of official exchange rates as conversion factors. In this country, multiple or dual exchange rate activity exists and must be accounted for appropriately in underlying statistics. An alternative estimate (“alternative conversion factor” - PA.NUS.ATLS) is thus calculated as a weighted average of the different exchange rates in use in the country. Doing so better reflects economic reality and leads to more accurate cross-country comparisons and country classifications by income level. For this country, this applies to the period 1978-1993. Alternative conversion factors are used in the Atlas methodology and elsewhere in World Development Indicators as single-year conversion factors. | E42: China
A43: CIV | B43: Sub-Saharan Africa | C43: Lower middle income | E43: Côte d'Ivoire
A44: CMR | B44: Sub-Saharan Africa | C44: Lower middle income | E44: Cameroon
A45: COD | B45: Sub-Saharan Africa | C45: Low income | D45: The World Bank systematically assesses the appropriateness of official exchange rates as conversion factors. In this country, multiple or dual exchange rate activity exists and must be accounted for appropriately in underlying statistics. An alternative estimate (“alternative conversion factor” - PA.NUS.ATLS) is thus calculated as a weighted average of the different exchange rates in use in the country. Doing so better reflects economic reality and leads to more accurate cross-country comparisons and country classifications by income level. For this country, this applies to the period 1999-2004. Alternative conversion factors are used in the Atlas methodology and elsewhere in World Development Indicators as single-year conversion factors. | E45: Congo, Dem. Rep.
A46: COG | B46: Sub-Saharan Africa | C46: Lower middle income | E46: Congo, Rep.
A47: COL | B47: Latin America & Caribbean | C47: Upper middle income | E47: Colombia
A48: COM | B48: Sub-Saharan Africa | C48: Lower middle income | E48: Comoros
A49: CPV | B49: Sub-Saharan Africa | C49: Upper middle income | E49: Cabo Verde
A50: CRI | B50: Latin America & Caribbean | C50: High income | E50: Costa Rica
A51: CSS | D51: Caribbean small states aggregate. | E51: Caribbean small states
A52: CUB | B52: Latin America & Caribbean | C52: Upper middle income | E52: Cuba
A53: CUW | B53: Latin America & Caribbean | C53: High income | E53: Curaçao
A54: CYM | B54: Latin America & Caribbean | C54: High income | E54: Cayman Islands
A55: CYP | B55: Europe & Central Asia | C55: High income | D55: A simple multiplier is used to convert the national currencies of EMU members to euros. The following irrevocable euro conversion rate entered into force on January 1, 2008: 1 euro = 0.585274 Cyprus pounds. Please note that historical data are not actual euros and are not comparable or suitable for aggregation across countries. | E55: Cyprus
A56: CZE | B56: Europe & Central Asia | C56: High income | E56: Czechia
A57: DEU | B57: Europe & Central Asia | C57: High income | D57: A simple multiplier is used to convert the national currencies of EMU members to euros. The following irrevocable euro conversion rate was adopted by the EU Council on January 1, 1999: 1 euro = 1.95583 Deutsche Mark. Please note that historical data before 1999 are not actual euros and are not comparable or suitable for aggregation across countries. GDP data before 1991 are calculated by applying backward GDP growth rates of the former Federal Republic of Germany starting from the first official GDP value for the unified Germany (1991). | E57: Germany
A58: DJI | B58: Middle East & North Africa | C58: Lower middle income | E58: Djibouti
A59: DMA | B59: Latin America & Caribbean | C59: Upper middle income | E59: Dominica
A60: DNK | B60: Europe & Central Asia | C60: High income | E60: Denmark
A61: DOM | B61: Latin America & Caribbean | C61: Upper middle income | E61: Dominican Republic
A62: DZA | B62: Middle East & North Africa | C62: Upper middle income | E62: Algeria
A63: EAP | E63: East Asia & Pacific (excluding high income)
A64: EAR | D64: Early-dividend countries are mostly lower-middle-income countries further along the fertility transition. Fertility rates have fallen below four births per woman and the working-age share of the population is likely rising considerably. | E64: Early-demographic dividend
A65: EAS | D65: East Asia and Pacific regional aggregate (includes all income levels). | E65: East Asia & Pacific
A66: ECA | E66: Europe & Central Asia (excluding high income)
A67: ECS | D67: Europe and Central Asia regional aggregate (includes all income levels). | E67: Europe & Central Asia
A68: ECU | B68: Latin America & Caribbean | C68: Upper middle income | E68: Ecuador
A69: EGY | B69: Middle East & North Africa | C69: Lower middle income | D69: The reporting period for national accounts data is designated as either calendar year basis (CY) or fiscal year basis (FY). For this country, it is fiscal year-based (fiscal year-end: June 30) for the years 1980 and after. The data from 1973 to 1979 refer to the calendar year data. Also, an estimate (PA.NUS.ATLS) of the exchange rate covers the same period and thus differs from the official exchange rate (CY). In addition, the World Bank systematically assesses the appropriateness of official exchange rates as conversion factors. In this country, multiple or dual exchange rate activity exists and must be accounted for appropriately in underlying statistics. An alternative estimate (“alternative conversion factor” - PA.NUS.ATLS) is thus calculated as a weighted average of the different exchange rates in use in the country. Doing so better reflects economic reality and leads to more accurate cross-country comparisons and country classifications by income level. For this country, this applies to the period 1965-2021. Alternative conversion factors are used in the Atlas methodology and elsewhere in World Development Indicators as single-year conversion factors. The national accounts data for Egypt has been updated to reflect local constant prices in the year 2022, moving from the previous reference of 2017. | E69: Egypt, Arab Rep.
A70: EMU | D70: Euro area aggregate. | E70: Euro area
A71: ERI | B71: Sub-Saharan Africa | C71: Low income | D71: The World Bank systematically assesses the appropriateness of official exchange rates as conversion factors. In this country, multiple or dual exchange rate activity exists and must be accounted for appropriately in underlying statistics. An alternative estimate (“alternative conversion factor” - PA.NUS.ATLS) is thus calculated as a weighted average of the different exchange rates in use in the country. Doing so better reflects economic reality and leads to more accurate cross-country comparisons and country classifications by income level. For this country, this applies to the period 1992-1997. Alternative conversion factors are used in the Atlas methodology and elsewhere in World Development Indicators as single-year conversion factors. | E71: Eritrea
A72: ESP | B72: Europe & Central Asia | C72: High income | D72: A simple multiplier is used to convert the national currencies of EMU members to euros. The following irrevocable euro conversion rate was adopted by the EU Council on January 1, 1999: 1 euro = 166.386 Spanish peseta. Please note that historical data before 1999 are not actual euros and are not comparable or suitable for aggregation across countries. | E72: Spain
A73: EST | B73: Europe & Central Asia | C73: High income | D73: The following irrevocable euro conversion rate entered into force on January 1, 2011: 1 euro = 15.6466 Estonian kroon. Please note that historical data are not actual euros and are not comparable or suitable for aggregation across countries. | E73: Estonia
A74: ETH | B74: Sub-Saharan Africa | D74: The reporting period for national accounts data is designated as either calendar year basis (CY) or fiscal year basis (FY). For this country, it is fiscal year-based (fiscal year-end: July 7). Also, an estimate (PA.NUS.ATLS) of the exchange rate covers the same period and thus differs from the official exchange rate (CY). The World Bank systematically assesses the appropriateness of official exchange rates as conversion factors. In this country, multiple or dual exchange rate activity exists and must be accounted for appropriately in underlying statistics. An alternative estimate (“alternative conversion factor” - PA.NUS.ATLS) is thus calculated by using an inflation-adjustment method. Doing so better reflects economic reality and leads to more accurate cross-country comparisons and country classifications by income level. For this country, this applies to the period 2015-2024. Alternative conversion factors are used in the Atlas methodology and elsewhere in World Development Indicators as single-year conversion factors. | E74: Ethiopia
A75: EUU | D75: European Union aggregate. | E75: European Union
A76: FCS | D76: Fragile and conflict-affected situations aggregate as of FY25 (July 1, 2024-June 30, 2025). Countries are distinguished based on the nature and severity of issues they face and classified into two categories: (i) Countries with significant institutional and social fragility, determined by indicators of policy quality and fragility. (ii) Countries experiencing violent conflict, classified by conflict-related deaths per capita and further divided into high-intensity and medium-intensity conflict subcategories. For more information, please visit https://www.worldbank.org/en/topic/fragilityconflictviolence/brief/classification-of-fragile-and-conflict-affected-situations. | E76: Fragile and conflict affected situations
A77: FIN | B77: Europe & Central Asia | C77: High income | D77: A simple multiplier is used to convert the national currencies of EMU members to euros. The following irrevocable euro conversion rate was adopted by the EU Council on January 1, 1999: 1 euro = 5.94573 Finnish markka. Please note that historical data before 1999 are not actual euros and are not comparable or suitable for aggregation across countries. | E77: Finland
A78: FJI | B78: East Asia & Pacific | C78: Upper middle income | E78: Fiji
A79: FRA | B79: Europe & Central Asia | C79: High income | D79: The following irrevocable euro conversion rate was adopted by the EU Council on January 1, 1999: 1 euro = 6.55957 French franc. Please note that historical data before 1999 are not actual euros and are not comparable or suitable for aggregation across countries. | E79: France
A80: FRO | B80: Europe & Central Asia | C80: High income | E80: Faroe Islands
A81: FSM | B81: East Asia & Pacific | C81: Lower middle income | D81: Fiscal year ends on September 30; reporting period for national accounts data: FY. The source for national accounts data is the Pacific and Virgin Islands Training Initiative. | E81: Micronesia, Fed. Sts.
A82: GAB | B82: Sub-Saharan Africa | C82: Upper middle income | E82: Gabon
A83: GBR | B83: Europe & Central Asia | C83: High income | E83: United Kingdom
A84: GEO | B84: Europe & Central Asia | C84: Upper middle income | D84: Includes self-governed areas only, which mostly exclude Abkhazia and South Ossetia, but small areas in Abkhazia and South Ossetia are included before 2008 or 2009 because of the changes in self-governed areas. | E84: Georgia
A85: GHA | B85: Sub-Saharan Africa | C85: Lower middle income | D85: The World Bank systematically assesses the appropriateness of official exchange rates as conversion factors. In this country, multiple or dual exchange rate activity exists and must be accounted for appropriately in underlying statistics. An alternative estimate (“alternative conversion factor” - PA.NUS.ATLS) is thus calculated as a weighted average of the different exchange rates in use in the country. Doing so better reflects economic reality and leads to more accurate cross-country comparisons and country classifications by income level. For this country, this applies to the period 1974-1987. Alternative conversion factors are used in the Atlas methodology and elsewhere in World Development Indicators as single-year conversion factors. | E85: Ghana
A86: GIB | B86: Europe & Central Asia | C86: High income | D86: The DEC conversion is not reported when national accounts data are unavailable. | E86: Gibraltar
A87: GIN | B87: Sub-Saharan Africa | C87: Lower middle income | E87: Guinea
A88: GMB | B88: Sub-Saharan Africa | C88: Low income | E88: Gambia, The
A89: GNB | B89: Sub-Saharan Africa | C89: Low income | E89: Guinea-Bissau
A90: GNQ | B90: Sub-Saharan Africa | C90: Upper middle income | E90: Equatorial Guinea
A91: GRC | B91: Europe & Central Asia | C91: High income | D91: A simple multiplier is used to convert the national currencies of EMU members to euros. The following irrevocable euro conversion rate was adopted by the EU Council on January 1, 1999: 1 euro = 340.75 Greek drachma. Please note that historical data before 1999 are not actual euros and are not comparable or suitable for aggregation across countries. | E91: Greece
A92: GRD | B92: Latin America & Caribbean | C92: Upper middle income | E92: Grenada
A93: GRL | B93: Europe & Central Asia | C93: High income | E93: Greenland
A94: GTM | B94: Latin America & Caribbean | C94: Upper middle income | D94: The World Bank systematically assesses the appropriateness of official exchange rates as conversion factors. In this country, multiple or dual exchange rate activity exists and must be accounted for appropriately in underlying statistics. An alternative estimate (“alternative conversion factor” - PA.NUS.ATLS) is thus calculated as a weighted average of the different exchange rates in use in the country. Doing so better reflects economic reality and leads to more accurate cross-country comparisons and country classifications by income level. For this country, this applies to the period 1985-2003. Alternative conversion factors are used in the Atlas methodology and elsewhere in World Development Indicators as single-year conversion factors. | E94: Guatemala
A95: GUM | B95: East Asia & Pacific | C95: High income | E95: Guam
A96: GUY | B96: Latin America & Caribbean | C96: High income | E96: Guyana
A97: HIC | D97: High income group aggregate. High-income economies are those in which 2024 Atlas GNI per capita was more than $13,935. | E97: High income
A98: HKG | B98: East Asia & Pacific | C98: High income | D98: On 1 July 1997 China resumed its exercise of sovereignty over Hong Kong. Unless otherwise noted, data for China do not include data for Hong Kong SAR, China; Macao SAR, China; or Taiwan, China. Agriculture value added includes mining and quarrying. | E98: Hong Kong SAR, China
A99: HND | B99: Latin America & Caribbean | C99: Lower middle income | D99: The World Bank systematically assesses the appropriateness of official exchange rates as conversion factors. In this country, multiple or dual exchange rate activity exists and must be accounted for appropriately in underlying statistics. An alternative estimate (“alternative conversion factor” - PA.NUS.ATLS) is thus calculated as a weighted average of the different exchange rates in use in the country. Doing so better reflects economic reality and leads to more accurate cross-country comparisons and country classifications by income level. For this country, this applies to the period 1988-1989. Alternative conversion factors are used in the Atlas methodology and elsewhere in World Development Indicators as single-year conversion factors. | E99: Honduras
A100: HPC | D100: The Heavily Indebted Poor Countries (HIPC) Initiative, launched in 1996 by the IMF and World Bank, aims to reduce the external debt burdens of the most indebted poor countries. Most participants have completed the program, receiving a total of $76 billion in debt-service relief. For more information, visit https://www.imf.org/en/About/Factsheets/Sheets/2016/08/01/16/11/Debt-Relief-Under-the-Heavily-Indebted-Poor-Countries-Initiative. Data presented are aggregates for HIPC countries. | E100: Heavily indebted poor countries (HIPC)
...

Sheet Metadata - Indicators
A1: INDICATOR_CODE | B1: INDICATOR_NAME | C1: SOURCE_NOTE | D1: SOURCE_ORGANIZATION
A2: SI.DST.FRST.10 | B2: Income share held by lowest 10% | C2: Percentage share of income or consumption is the share that accrues to subgroups of population indicated by deciles or quintiles. | D2: World Bank, Poverty and Inequality Platform. Data are based on primary household survey data obtained from government statistical agencies and World Bank country departments. Data for high-income economies are mostly from the Luxembourg Income Study database. For more information and methodology, please see http://pip.worldbank.org., World Bank (WB), uri: http://pip.worldbank.org, note: Data are based on primary household survey data obtained from government statistical agencies and World Bank country departments. Data for high-income economies are mostly from the Luxembourg Income Study database.
A3: SI.DST.FRST.20 | B3: Income share held by lowest 20% | C3: Percentage share of income or consumption is the share that accrues to subgroups of population indicated by deciles or quintiles. Percentage shares by quintile may not sum to 100 because of rounding. | D3: World Bank, Poverty and Inequality Platform. Data are based on primary household survey data obtained from government statistical agencies and World Bank country departments. Data for high-income economies are mostly from the Luxembourg Income Study database. For more information and methodology, please see http://pip.worldbank.org., World Bank (WB), uri: http://pip.worldbank.org, note: Data are based on primary household survey data obtained from government statistical agencies and World Bank country departments. Data for high-income economies are mostly from the Luxembourg Income Study database.
A4: SI.DST.02ND.20 | B4: Income share held by second 20% | C4: Percentage share of income or consumption is the share that accrues to subgroups of population indicated by deciles or quintiles. Percentage shares by quintile may not sum to 100 because of rounding. | D4: World Bank, Poverty and Inequality Platform. Data are based on primary household survey data obtained from government statistical agencies and World Bank country departments. Data for high-income economies are mostly from the Luxembourg Income Study database. For more information and methodology, please see http://pip.worldbank.org., World Bank (WB), uri: http://pip.worldbank.org, note: Data are based on primary household survey data obtained from government statistical agencies and World Bank country departments. Data for high-income economies are mostly from the Luxembourg Income Study database.
A5: SI.DST.03RD.20 | B5: Income share held by third 20% | C5: Percentage share of income or consumption is the share that accrues to subgroups of population indicated by deciles or quintiles. Percentage shares by quintile may not sum to 100 because of rounding. | D5: World Bank, Poverty and Inequality Platform. Data are based on primary household survey data obtained from government statistical agencies and World Bank country departments. Data for high-income economies are mostly from the Luxembourg Income Study database. For more information and methodology, please see http://pip.worldbank.org., World Bank (WB), uri: http://pip.worldbank.org, note: Data are based on primary household survey data obtained from government statistical agencies and World Bank country departments. Data for high-income economies are mostly from the Luxembourg Income Study database.
A6: SI.DST.04TH.20 | B6: Income share held by fourth 20% | C6: Percentage share of income or consumption is the share that accrues to subgroups of population indicated by deciles or quintiles. Percentage shares by quintile may not sum to 100 because of rounding. | D6: World Bank, Poverty and Inequality Platform. Data are based on primary household survey data obtained from government statistical agencies and World Bank country departments. Data for high-income economies are mostly from the Luxembourg Income Study database. For more information and methodology, please see http://pip.worldbank.org., World Bank (WB), uri: http://pip.worldbank.org, note: Data are based on primary household survey data obtained from government statistical agencies and World Bank country departments. Data for high-income economies are mostly from the Luxembourg Income Study database.
A7: SI.DST.05TH.20 | B7: Income share held by highest 20% | C7: Percentage share of income or consumption is the share that accrues to subgroups of population indicated by deciles or quintiles. Percentage shares by quintile may not sum to 100 because of rounding. | D7: World Bank, Poverty and Inequality Platform. Data are based on primary household survey data obtained from government statistical agencies and World Bank country departments. Data for high-income economies are mostly from the Luxembourg Income Study database. For more information and methodology, please see http://pip.worldbank.org., World Bank (WB), uri: http://pip.worldbank.org, note: Data are based on primary household survey data obtained from government statistical agencies and World Bank country departments. Data for high-income economies are mostly from the Luxembourg Income Study database.
A8: SI.DST.10TH.10 | B8: Income share held by highest 10% | C8: Percentage share of income or consumption is the share that accrues to subgroups of population indicated by deciles or quintiles. | D8: World Bank, Poverty and Inequality Platform. Data are based on primary household survey data obtained from government statistical agencies and World Bank country departments. Data for high-income economies are mostly from the Luxembourg Income Study database. For more information and methodology, please see http://pip.worldbank.org., World Bank (WB), uri: http://pip.worldbank.org, note: Data are based on primary household survey data obtained from government statistical agencies and World Bank country departments. Data for high-income economies are mostly from the Luxembourg Income Study database.
